Workbook

Sheet Organograma
A1: Nº diretoria | B1: Diretoria | C1: Nº da Gerência | D1: GERÊNCIA OU COORDENAÇÃO | E1: Responsavel pela gerência ou coordenação | F1: Nº do setor | G1: SETOR | H1: Responsável pelo Setor
A2: 1.1 | B2: Diretoria Geral | C2: 0 | D2: Ligado direto a diretoria | E2: Mylena Justino da Silva Brito | F2: 1.1.1 | G2: APGQ - Assessoria de Planejamento e Gestão da Qualidade | H2: Mylena Justino da Silva Brito
A3: 1.1 | B3: Diretoria Geral | C3: 0 | D3: Ligado direto a diretoria | E3: Rita De Cassia Rotterdan Lisboa | F3: 1.1.10 | G3: AC - Assessoria de Comunicação | H3: Rita De Cassia Rotterdan Lisboa
A4: 1.1 | B4: Diretoria Geral | C4: 0 | D4: Ligado direto a diretoria | E4: Cintia Kelciane Gomes de Oliveira | F4: 1.1.3 | G4: CEP - Centro de Ensino e Pesquisa | H4: Cintia Kelciane Gomes de Oliveira
A5: 1.1 | B5: Diretoria Geral | C5: 0 | D5: Ligado direto a diretoria | E5: Yuri Amorim Braga | F5: 1.1.5 | G5: Diretoria Geral | H5: Yuri Amorim Braga
A6: 1.1 | B6: Diretoria Geral | C6: 0 | D6: Ligado direto a diretoria | E6: Yuri Amorim Braga | F6: 1.1.6 | G6: Assessoria da Diretoria Geral | H6: Natacha Flora Alves de Moraes
A7: 1.1 | B7: Diretoria Geral | C7: 0 | D7: Ligado direto a diretoria | E7: Rafaela Braga Simões | F7: 1.1.6 | G7: NGAH - Núcleo de Gestão de Atendimento e Humanização | H7: Rafaela Braga Simões
A8: 1.1 | B8: Diretoria Geral | C8: 0 | D8: Ligado direto a diretoria | E8: Mylena Justino da Silva Brito | F8: 1.1.7 | G8: NSP - Núcleo de Segurança do Paciente | H8: Mylena Justino da Silva Brito
A9: 1.1 | B9: Diretoria Geral | C9: 0 | D9: Ligado direto a diretoria | E9: Regia Carla da Silva Conceicao | F9: 1.1.8 | G9: OUV - Ouvidoria | H9: Regia Carla da Silva Conceicao
A10: 1.1 | B10: Diretoria Geral | C10: 0 | D10: Ligado direto a diretoria | E10: Andrew Silva de Lima | F10: 1.1.9 | G10: TI - Serviço de Tecnologia de Informação | H10: Andrew Silva de Lima
A11: 2.1 | B11: Diretoria Técnica | C11: 2.1.34 | D11: Gerência Ambulatorial e do Apoio Diagnóstico | E11: Camila Amanda Cardoso dos Santos | F11: 2.1.34.1 | G11: AMB - Unidade Ambulatorial | H11: Camila Amanda Cardoso dos Santos
A12: 2.1 | B12: Diretoria Técnica | C12: 2.1.34 | D12: Gerência Ambulatorial e do Apoio Diagnóstico | E12: Camila Amanda Cardoso dos Santos | F12: 2.1.34.5 | G12: AT - Agência Transfusional | H12: Camila Amanda Cardoso dos Santos
A13: 2.1 | B13: Diretoria Técnica | C13: 2.1.33 | D13: Gerência de Cuidado Materno/Infantil | E13: Camila Nascimento Santos Santana | F13: 2.1.33.1 | G13: BLH - Banco de Leite Humano | H13: Flavia de Souza Moura
A14: 2.1 | B14: Diretoria Técnica | C14: 2.1.8 | D14: Coordenação de Internação | E14: Janaina Bernardes Ayer | F14: 2.1.8.8 | G14: CA - Controle de Acesso | H14: Janaina Bernardes Ayer
A15: 2.1 | B15: Diretoria Técnica | C15: 2.1.35 | D15: Gerência de Cuidados Cirúrgicos | E15: Evila Ellen Sa De Moraes Matias | F15: 2.1.35.1 | G15: CC - Centro Cirúrgico | H15: Evila Ellen Sa De Moraes Matias
A16: 2.1 | B16: Diretoria Técnica | C16: 2.1.33 | D16: Gerência de Cuidado Materno/Infantil | E16: Camila Nascimento Santos Santana | F16: 2.1.33.2 | G16: CGO - Unidade de Internação Ginecobstétrica | H16: Daniella Gomes De Oliveira Costa
A17: 2.1 | B17: Diretoria Técnica | C17: 2.1.35 | D17: Gerência de Cuidados Cirúrgicos | E17: Evila Ellen Sa De Moraes Matias | F17: 2.1.35.2 | G17: CME - Centro de Material e Esterilização | H17: Olivia Alves dos Santos
A18: 2.1 | B18: Diretoria Técnica | C18: 2.1.33 | D18: Gerência de Cuidado Materno/Infantil | E18: Camila Nascimento Santos Santana | F18: 2.1.33.3 | G18: CPN - Centro de Parto Normal | H18: Lorena do Nascimento Barreto
A19: 2.1 | B19: Diretoria Técnica | C19: 2.1.34 | D19: Gerência Ambulatorial e do Apoio Diagnóstico | E19: Camila Amanda Cardoso dos Santos | F19: 2.1.34.2 | G19: CTI - Centro de Terapia Infusional | H19: Camila Amanda Cardoso dos Santos
A20: 2.1 | B20: Diretoria Técnica | C20: 00 | D20: Diretoria | E20: Marcelo Lopes Ribeiro | F20: 2.1.11 | G20: Diretoria Técnica | H20: Marcelo Lopes Ribeiro
A21: 2.1 | B21: Diretoria Técnica | C21: 2.1.37 | D21: Equipe Multiprofissional | E21: Alfredo Gomes Barbosa | F21: 2.1.37.1 | G21: FIS - Fisioterapia | H21: Alfredo Gomes Barbosa
A22: 2.1 | B22: Diretoria Técnica | C22: 2.1.37 | D22: Equipe Multiprofissional | E22: Webete da Silva Costa | F22: 2.1.37.2 | G22: FONO - Fonoaudiologia | H22: Webete da Silva Costa
A23: 2.1 | B23: Diretoria Técnica | C23: 0 | D23: Ligado direto a diretoria | E23: Clariane Acário Martins | F23: 2.1.13 | G23: GA - Gerência Assistencial | H23: Clariane Acário Martins
A24: 2.1 | B24: Diretoria Técnica | C24: 00 | D24: Ligado direto a diretoria | E24: Aliny Lopes Coelho | F24: 2.1.14 | G24: GRSS - Gerenciamento de Resíduos de Serviço de Saúde | H24: Aliny Lopes Coelho
A25: 2.1 | B25: Diretoria Técnica | C25: 2.1.34 | D25: Gerência Ambulatorial e do Apoio Diagnóstico | E25: Camila Amanda Cardoso dos Santos | F25: 2.1.34.4 | G25: LAB - Unidade de Análises Clínicas | H25: Camila Amanda Cardoso dos Santos
A26: 2.1 | B26: Diretoria Técnica | C26: 2.1.8 | D26: Coordenação de Internação | E26: Janaina Bernardes Ayer | F26: 2.1.8.5 | G26: NIR - Núcleo Interno de Regulação | H26: Janaina Bernardes Ayer
A27: 2.1 | B27: Diretoria Técnica | C27: 2.1.37 | D27: Equipe Multiprofissional | E27: Flavia de Souza Moura | F27: 2.1.37.3 | G27: Nutrição Clínica | H27: Flavia de Souza Moura
A28: 2.1 | B28: Diretoria Técnica | C28: 00 | D28: Ligado direto a diretoria | E28: Aliny Lopes Coelho | F28: 2.1.18 | G28: NVEH - Núcleo de Vigilância Epidemiológica Hospitalar | H28: Aliny Lopes Coelho
A29: 2.1 | B29: Diretoria Técnica | C29: 2.1.36 | D29: Gerência de Cuidados Clínicos Intensivos | E29: Mayara Soares Honório | F29: 2.1.36.1 | G29: P.S - Pronto Socorro | H29: Mayara Soares Honório
A30: 2.1 | B30: Diretoria Técnica | C30: 2.1.33 | D30: Gerência de Cuidado Materno/Infantil | E30: Camila Nascimento Santos Santana | F30: 2.1.33.4 | G30: PAM - Pronto Atendimento Materno | H30: Camila Nascimento Santos Santana
A31: 2.1 | B31: Diretoria Técnica | C31: 2.1.33 | D31: Gerência de Cuidado Materno/Infantil | E31: Camila Nascimento Santos Santana | F31: 2.1.33.5 | G31: PED - Unidade de Internação Pediátrica | H31: Larissa Talita da Silva
A32: 2.1 | B32: Diretoria Técnica | C32: 2.1.37 | D32: Equipe Multiprofissional | E32: Mariana Lopes de Almeida | F32: 2.1.37.4 | G32: PSICC- Psicologia Clínica | H32: Mariana Lopes de Almeida
A33: 2.1 | B33: Diretoria Técnica | C33: 2.1.36 | D33: Gerência de Cuidados Clínicos Intensivos | E33: Mayara Soares Honório | F33: 2.1.36.2 | G33: PSICO - Unidade de Atendimento a Saúde Mental | H33: Marisol Luise Vilhene da Silva
A34: 2.1 | B34: Diretoria Técnica | C34: 2.1.8 | D34: Coordenação de Internação | E34: Janaina Bernardes Ayer | F34: 2.1.8.7 | G34: REC - Recepção | H34: Janaina Bernardes Ayer
A35: 2.1 | B35: Diretoria Técnica | C35: 2.1.34 | D35: Gerência Ambulatorial e do Apoio Diagnóstico | E35: Camila Amanda Cardoso dos Santos | F35: 2.1.34.3 | G35: SADT - Unidade de Diagnóstico Por Imagem | H35: Nadja Keilane Dantas Espinola
... A63: 3.1 | B63: Dir. Administrativa/Financeira | C63: 000 | D63: Ligado direto a diretoria | E63: Gleyce Kelly Damaceno Barros Cavalcante | F63: 3.1.8 | G63: OPME - Órtese Prótese e Materiais Especiais | H63: Gleyce Kelly Damaceno Barros Cavalcante

Sheet AÇÕES
A1: Título | B1: Plano de Ação | C1: Tipo | D1: Setor | E1: Responsável | F1: Início Previsto | G1: Início Realizado | H1: Fim Previsto | I1: Fim Realizado | J1: Progresso | K1: Status
A2: Nível 1 - 1.1.17.1 Requisito: Definir diretrizes formais para prevenção, controle de infecção e biossegurança e implementa ações sistemáticas (CORE) | B2: ONA 2026: Grupo 1.1.17 - Prevenção e Controle de Infecção e Biossegurança | C2: ONA | D2: =_xlfn.XLOOKUP(E2,Organograma!H:H,Organograma!G:G,"") -> GRSS - Gerenciamento de Resíduos de Serviço de Saúde | E2: Aliny Lopes Coelho | F2: 46025 | G2: 46331 | H2: 46173 | I2: n/d | J2: 0.5 | K2: Em Andamento
A3: Nível 1 - 1.1.17.2 Requisito: Prover condições para que o Serviço de Prevenção, Controle de Infecção e Biossegurança assessore tecnicamente os processos | B3: ONA 2026: Grupo 1.1.17 - Prevenção e Controle de Infecção e Biossegurança | C3: ONA | D3: =_xlfn.XLOOKUP(E3,Organograma!H:H,Organograma!G:G,"") -> GRSS - Gerenciamento de Resíduos de Serviço de Saúde | E3: Aliny Lopes Coelho | F3: 46025 | G3: 46331 | H3: 46173 | I3: n/d | J3: 0.5 | K3: Em Andamento
A4: Nível 2 - 1.1.17.3 Requisito: Monitorar e gerenciar o Programa de Prevenção, Controle de Infecção e Biossegurança com base em evidências, análises de causa | B4: ONA 2026: Grupo 1.1.17 - Prevenção e Controle de Infecção e Biossegurança | C4: ONA | D4: =_xlfn.XLOOKUP(E4,Organograma!H:H,Organograma!G:G,"") -> GRSS - Gerenciamento de Resíduos de Serviço de Saúde | E4: Aliny Lopes Coelho | F4: 46025 | G4: n/d | H4: 46173 | I4: n/d | J4: 0 | K4: Não Iniciada
A5: Nível 3 - 1.1.17.4 Requisito: Utilizar os resultados do Programa de Prevenção, Controle de Infecção e Biossegurança para promover ciclos de melhoria (CORE) | B5: ONA 2026: Grupo 1.1.17 - Prevenção e Controle de Infecção e Biossegurança | C5: ONA | D5: =_xlfn.XLOOKUP(E5,Organograma!H:H,Organograma!G:G,"") -> GRSS - Gerenciamento de Resíduos de Serviço de Saúde | E5: Aliny Lopes Coelho | F5: 46025 | G5: n/d | H5: 46173 | I5: n/d | J5: 0 | K5: Não Iniciada
A6: Nível 1 - 1.1.18.1 Requisito: Estabelecer canal formal para comunicação de questões relacionadas à integridade, conformidade (compliance), dilemas éticos | B6: ONA 2026: Grupo 1.1.17 - Prevenção e Controle de Infecção e Biossegurança | C6: ONA | D6: =_xlfn.XLOOKUP(E6,Organograma!H:H,Organograma!G:G,"") -> GRSS - Gerenciamento de Resíduos de Serviço de Saúde | E6: Aliny Lopes Coelho | F6: 46025 | G6: n/d | H6: 46173 | I6: n/d | J6: 0 | K6: Não Iniciada
A7: Nível 1 - 1.1.18.2 Requisito: Estabelecer, implementar e manter um plano de comunicação estruturado para interação com os públicos interno e externo. | B7: ONA 2026: Grupo 1.1.17 - Prevenção e Controle de Infecção e Biossegurança | C7: ONA | D7: =_xlfn.XLOOKUP(E7,Organograma!H:H,Organograma!G:G,"") -> GRSS - Gerenciamento de Resíduos de Serviço de Saúde | E7: Aliny Lopes Coelho | F7: 46025 | G7: n/d | H7: 46173 | I7: n/d | J7: 0 | K7: Não Iniciada
A8: Nível 1 - 1.1.18.3 Requisito: Estabelecer, implementar e manter meios e canais acessíveis e eficazes de comunicação com pacientes/clientes (CORE) | B8: ONA 2026: Grupo 1.1.17 - Prevenção e Controle de Infecção e Biossegurança | C8: ONA | D8: =_xlfn.XLOOKUP(E8,Organograma!H:H,Organograma!G:G,"") -> GRSS - Gerenciamento de Resíduos de Serviço de Saúde | E8: Aliny Lopes Coelho | F8: 46025 | G8: n/d | H8: 46173 | I8: n/d | J8: 0 | K8: Não Iniciada
A9: Nível 1 - 1.1.18.4 Requisito: Estabelecer, implementar e manter meios e canais de comunicação eficazes entre os diferentes níveis hierárquicos e perfis | B9: ONA 2026: Grupo 1.1.17 - Prevenção e Controle de Infecção e Biossegurança | C9: ONA | D9: =_xlfn.XLOOKUP(E9,Organograma!H:H,Organograma!G:G,"") -> GRSS - Gerenciamento de Resíduos de Serviço de Saúde | E9: Aliny Lopes Coelho | F9: 46025 | G9: n/d | H9: 46173 | I9: n/d | J9: 0 | K9: Não Iniciada
A10: Nível 2 - .1.18.5 Requisito: Avaliar os canais de comunicação, identificando causas de falhas e promovendo ações de melhoria contínua. | B10: ONA 2026: Grupo 1.1.17 - Prevenção e Controle de Infecção e Biossegurança | C10: ONA | D10: =_xlfn.XLOOKUP(E10,Organograma!H:H,Organograma!G:G,"") -> GRSS - Gerenciamento de Resíduos de Serviço de Saúde | E10: Aliny Lopes Coelho | F10: 46025 | G10: n/d | H10: 46173 | I10: n/d | J10: 0 | K10: Não Iniciada
A11: Nível 3 - 1.1.18.6 Requisito: Utilizar os resultados da comunicação para avaliar a efetividade dos canais e promover ciclos de melhoria. | B11: ONA 2026: Grupo 1.1.17 - Prevenção e Controle de Infecção e Biossegurança | C11: ONA | D11: =_xlfn.XLOOKUP(E11,Organograma!H:H,Organograma!G:G,"") -> GRSS - Gerenciamento de Resíduos de Serviço de Saúde | E11: Aliny Lopes Coelho | F11: 46025 | G11: n/d | H11: 46173 | I11: n/d | J11: 0 | K11: Não Iniciada
A12: Nível 1 - 1.1.19.1 Requisito: Definir, divulgar e assegurar o cumprimento dos direitos e deveres dos pacientes e usuários dos serviços | B12: ONA 2026: Grupo 1.1.17 - Prevenção e Controle de Infecção e Biossegurança | C12: ONA | D12: =_xlfn.XLOOKUP(E12,Organograma!H:H,Organograma!G:G,"") -> GRSS - Gerenciamento de Resíduos de Serviço de Saúde | E12: Aliny Lopes Coelho | F12: 46025 | G12: n/d | H12: 46173 | I12: n/d | J12: 0 | K12: Não Iniciada
A13: Nível 1 - 1.1.19.2 Requisito: Assegurar que todos os profissionais envolvidos na assistência recebam educação e capacitação que promovam o cuidado centrado | B13: ONA 2026: Grupo 1.1.17 - Prevenção e Controle de Infecção e Biossegurança | C13: ONA | D13: =_xlfn.XLOOKUP(E13,Organograma!H:H,Organograma!G:G,"") -> GRSS - Gerenciamento de Resíduos de Serviço de Saúde | E13: Aliny Lopes Coelho | F13: 46025 | G13: n/d | H13: 46173 | I13: n/d | J13: 0 | K13: Não Iniciada
A14: Nível 1 - 1.1.19.3 Requisito: Fornecer aos pacientes e usuários informações claras, acessíveis e compreensíveis sobre suas necessidades de cuidado, alternativas | B14: ONA 2026: Grupo 1.1.17 - Prevenção e Controle de Infecção e Biossegurança | C14: ONA | D14: =_xlfn.XLOOKUP(E14,Organograma!H:H,Organograma!G:G,"") -> GRSS - Gerenciamento de Resíduos de Serviço de Saúde | E14: Aliny Lopes Coelho | F14: 46025 | G14: n/d | H14: 46173 | I14: n/d | J14: 0 | K14: Não Iniciada
A15: Nível 1 - 1.1.19.4 Requisito: Assegurar a participação ativa do paciente e/ou de seus representantes nas decisões relacionadas ao seu cuidado e tratamento | B15: ONA 2026: Grupo 1.1.17 - Prevenção e Controle de Infecção e Biossegurança | C15: ONA | D15: =_xlfn.XLOOKUP(E15,Organograma!H:H,Organograma!G:G,"") -> GRSS - Gerenciamento de Resíduos de Serviço de Saúde | E15: Aliny Lopes Coelho | F15: 46025 | G15: n/d | H15: 46173 | I15: n/d | J15: 0 | K15: Não Iniciada
... A22: Nível 3 - 1.1.19.11 Requisito: Possuir processos sistemáticos para consultar e envolver pacientes, familiares e a comunidade na avaliação e melhoria contínua | B22: ONA 2026: Grupo 1.1.17 - Prevenção e Controle de Infecção e Biossegurança | C22: ONA | D22: =_xlfn.XLOOKUP(E22,Organograma!H:H,Organograma!G:G,"") -> GRSS - Gerenciamento de Resíduos de Serviço de Saúde | E22: Aliny Lopes Coelho | F22: 46025 | G22: n/d | H22: 46173 | I22: n/d | J22: 0 | K22: Não Iniciada
A23: 4.8.1 Requisito: Monitorar a qualidade da água em todas as etapas relacionadas à assistência nutricional (CORE) | B23: ONA 2026: Subseção 4.8 Nutrição | C23: ONA | D23: =_xlfn.XLOOKUP(E23,Organograma!H:H,Organograma!G:G,"") -> SND - Serviço de Nutrição e Dietética | E23: Ana Luiza Timoteo Costa | F23: 46025 | G23: 46147 | H23: 46173 | I23: n/d | J23: 0.5 | K23: Em Andamento
A24: 4.8.2 Requisito: Planejar e monitorar a demanda de dietas | B24: ONA 2026: Subseção 4.8 Nutrição | C24: ONA | D24: =_xlfn.XLOOKUP(E24,Organograma!H:H,Organograma!G:G,"") -> SND - Serviço de Nutrição e Dietética | E24: Ana Luiza Timoteo Costa | F24: 46025 | G24: 46105 | H24: 46173 | I24: n/d | J24: 0.5 | K24: Em Andamento
A25: 4.8.3 Requisito: Dispor de mecanismos e procedimentos para a identificação e rastreabilidade de alimentos e refeições | B25: ONA 2026: Subseção 4.8 Nutrição | C25: ONA | D25: =_xlfn.XLOOKUP(E25,Organograma!H:H,Organograma!G:G,"") -> SND - Serviço de Nutrição e Dietética | E25: Ana Luiza Timoteo Costa | F25: 46025 | G25: 46104 | H25: 46173 | I25: n/d | J25: 0.75 | K25: Em Andamento
A26: 4.8.4 Requisito: Dispor de mecanismos e procedimentos para o monitoramento e conservação de alimentos e refeições (CORE) | B26: ONA 2026: Subseção 4.8 Nutrição | C26: ONA | D26: =_xlfn.XLOOKUP(E26,Organograma!H:H,Organograma!G:G,"") -> SND - Serviço de Nutrição e Dietética | E26: Ana Luiza Timoteo Costa | F26: 46025 | G26: 46104 | H26: 46173 | I26: n/d | J26: 0.75 | K26: Em Andamento
A27: 4.8.5 Requisito: Dispor de mecanismos e procedimentos para o porcionamento, transporte, distribuição e amostragem de alimentos e refeições (CORE) | B27: ONA 2026: Subseção 4.8 Nutrição | C27: ONA | D27: =_xlfn.XLOOKUP(E27,Organograma!H:H,Organograma!G:G,"") -> SND - Serviço de Nutrição e Dietética | E27: Ana Luiza Timoteo Costa | F27: 46025 | G27: 46145 | H27: 46173 | I27: n/d | J27: 0.5 | K27: Em Andamento
A28: 4.8.7 Requisito: Planejar e monitorar a demanda de terapia nutricional parenteral. | B28: ONA 2026: Subseção 4.8 Nutrição | C28: ONA | D28: =_xlfn.XLOOKUP(E28,Organograma!H:H,Organograma!G:G,"") -> SND - Serviço de Nutrição e Dietética | E28: Ana Luiza Timoteo Costa | F28: 46025 | G28: 46106 | H28: 46173 | I28: n/d | J28: 0.75 | K28: Em Andamento
A29: 4.8.8 Requisito: Dispor de mecanismos e procedimentos para a identificação e rastreabilidade de dietas enterais, módulos e suplementos/complementos nutricionais | B29: ONA 2026: Subseção 4.8 Nutrição | C29: ONA | D29: =_xlfn.XLOOKUP(E29,Organograma!H:H,Organograma!G:G,"") -> SND - Serviço de Nutrição e Dietética | E29: Ana Luiza Timoteo Costa | F29: 46025 | G29: 46267 | H29: 46173 | I29: n/d | J29: 0.5 | K29: Em Andamento
A30: 4.8.9 Requisito: Dispor de mecanismos e procedimentos para o monitoramento e a conservação de dietas enterais, módulos e suplementos/complementos nutricionais | B30: ONA 2026: Subseção 4.8 Nutrição | C30: ONA | D30: =_xlfn.XLOOKUP(E30,Organograma!H:H,Organograma!G:G,"") -> SND - Serviço de Nutrição e Dietética | E30: Ana Luiza Timoteo Costa | F30: 46025 | G30: 46108 | H30: 46173 | I30: n/d | J30: 0.75 | K30: Em Andamento
A31: 4.8.10 Requisito: Dispor de mecanismos e procedimentos para o encaminhamento, distribuição e amostragem de dietas enterais, módulos e suplementos/complementos | B31: ONA 2026: Subseção 4.8 Nutrição | C31: ONA | D31: =_xlfn.XLOOKUP(E31,Organograma!H:H,Organograma!G:G,"") -> SND - Serviço de Nutrição e Dietética | E31: Ana Luiza Timoteo Costa | F31: 46025 | G31: 46099 | H31: 46173 | I31: n/d | J31: 0.75 | K31: Em Andamento
A32: 4.8.11 Requisito: Estabelecer e implementar critérios e procedimentos para a análise técnica das prescrições dietéticas e nutricionais, assegurando a adequação | B32: ONA 2026: Subseção 4.8 Nutrição | C32: ONA | D32: =_xlfn.XLOOKUP(E32,Organograma!H:H,Organograma!G:G,"") -> SND - Serviço de Nutrição e Dietética | E32: Ana Luiza Timoteo Costa | F32: 46025 | G32: 46097 | H32: 46173 | I32: n/d | J32: 0.75 | K32: Em Andamento
A33: 4.8.12 Requisito: Planejar e acompanhar a demanda de leite humano e fórmulas infantis, conforme perfil de pacientes | B33: ONA 2026: Subseção 4.8 Nutrição | C33: ONA | D33: =_xlfn.XLOOKUP(E33,Organograma!H:H,Organograma!G:G,"") -> SND - Serviço de Nutrição e Dietética | E33: Ana Luiza Timoteo Costa | F33: 46142 | G33: 46105 | H33: 46173 | I33: n/d | J33: 0.5 | K33: Em Andamento
A34: 4.8.13 Requisito: Dispor de uma sistemática para mobilização de doadoras de leite humano | B34: ONA 2026: Subseção 4.8 Nutrição | C34: ONA | D34: =_xlfn.XLOOKUP(E34,Organograma!H:H,Organograma!G:G,"") -> SND - Serviço de Nutrição e Dietética | E34: Ana Luiza Timoteo Costa | F34: 46025 | G34: 46106 | H34: 46173 | I34: n/d | J34: 0.5 | K34: Em Andamento
... A41: 4.8.20 Requisito: Dispor de mecanismos e procedimentos para o encaminhamento, distribuição e amostragem do leite humano | B41: ONA 2026: Subseção 4.8 Nutrição | C41: ONA | D41: =_xlfn.XLOOKUP(E41,Organograma!H:H,Organograma!G:G,"") -> SND - Serviço de Nutrição e Dietética | E41: Ana Luiza Timoteo Costa | F41: 46025 | G41: 46111 | H41: 46173 | I41: n/d | J41: 0.5 | K41: Em Andamento
A42: 4.10.1 Requisito: Estabelecer, implementar e manter um plano de contingência para situações de descontinuidade no acesso a dados e informações (CORE) | B42: ONA 2026: Subseção 4.10 Gestão da Tecnologia e Segurança da Informação | C42: ONA | D42: =_xlfn.XLOOKUP(E42,Organograma!H:H,Organograma!G:G,"") -> TI - Serviço de Tecnologia de Informação | E42: Andrew Silva de Lima | F42: 46025 | G42: n/d | H42: 46173 | I42: n/d | J42: 0 | K42: Não Iniciada
A43: 4.10.2 Requisito: Dispor de informações integradas do paciente/cliente, permitindo acesso ao histórico dos atendimentos realizados pela equipe multidisciplinar | B43: ONA 2026: Subseção 4.10 Gestão da Tecnologia e Segurança da Informação | C43: ONA | D43: =_xlfn.XLOOKUP(E43,Organograma!H:H,Organograma!G:G,"") -> TI - Serviço de Tecnologia de Informação | E43: Andrew Silva de Lima | F43: 46025 | G43: n/d | H43: 46173 | I43: n/d | J43: 0 | K43: Não Iniciada
A44: 4.10.3 Requisito: Estabelecer, implementar e manter sistemática p/ registros e evoluções da equipe multidisciplinar, permitindo a continuidade do cuidado (CORE) | B44: ONA 2026: Subseção 4.10 Gestão da Tecnologia e Segurança da Informação | C44: ONA | D44: =_xlfn.XLOOKUP(E44,Organograma!H:H,Organograma!G:G,"") -> TI - Serviço de Tecnologia de Informação | E44: Andrew Silva de Lima | F44: 46025 | G44: n/d | H44: 46173 | I44: n/d | J44: 0 | K44: Não Iniciada
A45: 4.10.4 Requisito: Estabelecer, implementar e manter procedimento para avaliação sistemática da qualidade das evoluções, registros e informações (CORE) | B45: ONA 2026: Subseção 4.10 Gestão da Tecnologia e Segurança da Informação | C45: ONA | D45: =_xlfn.XLOOKUP(E45,Organograma!H:H,Organograma!G:G,"") -> TI - Serviço de Tecnologia de Informação | E45: Andrew Silva de Lima | F45: 46025 | G45: n/d | H45: 46173 | I45: n/d | J45: 0 | K45: Não Iniciada
A46: 4.10.5 Requisito: Estabelecer, implementar e manter um método de coleta, análise e disponibilização de dados para apoiar a tomada de decisão em todas as áreas | B46: ONA 2026: Subseção 4.10 Gestão da Tecnologia e Segurança da Informação | C46: ONA | D46: =_xlfn.XLOOKUP(E46,Organograma!H:H,Organograma!G:G,"") -> TI - Serviço de Tecnologia de Informação | E46: Andrew Silva de Lima | F46: 46025 | G46: n/d | H46: 46173 | I46: n/d | J46: 0 | K46: Não Iniciada
A47: 4.10.6 Requisito: Estabelecer e manter orientações claras aos usuários quanto às regras de segurança da informação (CORE) | B47: ONA 2026: Subseção 4.10 Gestão da Tecnologia e Segurança da Informação | C47: ONA | D47: =_xlfn.XLOOKUP(E47,Organograma!H:H,Organograma!G:G,"") -> TI - Serviço de Tecnologia de Informação | E47: Andrew Silva de Lima | F47: 46025 | G47: n/d | H47: 46173 | I47: n/d | J47: 0 | K47: Não Iniciada
A48: 4.10.7 Requisito: Estabelecer e implementar diretrizes claras para as permissões de acesso ao prontuário, assegurando a privacidade e a confidencialidade | B48: ONA 2026: Subseção 4.10 Gestão da Tecnologia e Segurança da Informação | C48: ONA | D48: =_xlfn.XLOOKUP(E48,Organograma!H:H,Organograma!G:G,"") -> TI - Serviço de Tecnologia de Informação | E48: Andrew Silva de Lima | F48: 46025 | G48: n/d | H48: 46173 | I48: n/d | J48: 0 | K48: Não Iniciada
A49: 4.10.8 Requisito: Estabelecer, implementar e manter uma sistemática para a organização e padronização da estrutura e do conteúdo do prontuário/dados do paciente | B49: ONA 2026: Subseção 4.10 Gestão da Tecnologia e Segurança da Informação | C49: ONA | D49: =_xlfn.XLOOKUP(E49,Organograma!H:H,Organograma!G:G,"") -> TI - Serviço de Tecnologia de Informação | E49: Andrew Silva de Lima | F49: 46025 | G49: n/d | H49: 46173 | I49: n/d | J49: 0 | K49: Não Iniciada
A50: 4.10.9 Requisito: Estabelecer programa de privacidade de dados, especificando o fluxo de acesso e a tratativa das informações. | B50: ONA 2026: Subseção 4.10 Gestão da Tecnologia e Segurança da Informação | C50: ONA | D50: =_xlfn.XLOOKUP(E50,Organograma!H:H,Organograma!G:G,"") -> TI - Serviço de Tecnologia de Informação | E50: Andrew Silva de Lima | F50: 46025 | G50: n/d | H50: 46173 | I50: n/d | J50: 0 | K50: Não Iniciada
A51: 4.10.10 Requisito: Estabelecer mecanismos de segurança para garantir a proteção, confidencialidade e integridade nas comunicações virtuais com pacientes/usuário | B51: ONA 2026: Subseção 4.10 Gestão da Tecnologia e Segurança da Informação | C51: ONA | D51: =_xlfn.XLOOKUP(E51,Organograma!H:H,Organograma!G:G,"") -> TI - Serviço de Tecnologia de Informação | E51: Andrew Silva de Lima | F51: 46025 | G51: n/d | H51: 46173 | I51: n/d | J51: 0 | K51: Não Iniciada
A52: 4.10.11 Requisito: Estabelecer, implementar e manter uma sistemática para qualificar e testar os sistemas de informática e softwares antes da entrada em uso | B52: ONA 2026: Subseção 4.10 Gestão da Tecnologia e Segurança da Informação | C52: ONA | D52: =_xlfn.XLOOKUP(E52,Organograma!H:H,Organograma!G:G,"") -> TI - Serviço de Tecnologia de Informação | E52: Andrew Silva de Lima | F52: 46025 | G52: n/d | H52: 46173 | I52: n/d | J52: 0 | K52: Não Iniciada
A53: 4.10.12 Requisito: Capacitar os usuários periodicamente para o uso correto e seguro dos sistemas de informática. | B53: ONA 2026: Subseção 4.10 Gestão da Tecnologia e Segurança da Informação | C53: ONA | D53: =_xlfn.XLOOKUP(E53,Organograma!H:H,Organograma!G:G,"") -> TI - Serviço de Tecnologia de Informação | E53: Andrew Silva de Lima | F53: 46025 | G53: n/d | H53: 46173 | I53: n/d | J53: 0 | K53: Não Iniciada
... A68: 4.10.27 Requisito: Garantir que pacientes, clientes e usuários dos serviços sejam informados, de forma clara, acessível e transparente | B68: ONA 2026: Subseção 4.10 Gestão da Tecnologia e Segurança da Informação | C68: ONA | D68: =_xlfn.XLOOKUP(E68,Organograma!H:H,Organograma!G:G,"") -> TI - Serviço de Tecnologia de Informação | E68: Andrew Silva de Lima | F68: 46025 | G68: n/d | H68: 46173 | I68: n/d | J68: 0 | K68: Não Iniciada
A69: Nível 1 - 2.2.1 Requisito: Desenvolver e implementar ações de promoção da saúde alinhadas ao perfil epidemiológico da população atendida | B69: ONA 2026: Subseção 2.2 Atendimento Ambulatorial | C69: ONA | D69: =_xlfn.XLOOKUP(E69,Organograma!H:H,Organograma!G:G,"") -> AMB - Unidade Ambulatorial | E69: Camila Amanda Cardoso dos Santos | F69: 46025 | G69: 46298 | H69: 46173 | I69: n/d | J69: 0.5 | K69: Em Andamento
A70: Nível 1 - 2.2.2 Requisito: Adotar métodos sistematizados para o agendamento e acompanhamento da demanda por consultas, exames e atendimentos especializados | B70: ONA 2026: Subseção 2.2 Atendimento Ambulatorial | C70: ONA | D70: =_xlfn.XLOOKUP(E70,Organograma!H:H,Organograma!G:G,"") -> AMB - Unidade Ambulatorial | E70: Camila Amanda Cardoso dos Santos | F70: 46025 | G70: 46105 | H70: 46173 | I70: n/d | J70: 0.25 | K70: Em Andamento
A71: Nível 1 - 2.2.3 Requisito: Estruturar o processo assistencial para garantir acesso oportuno a públicos prioritários, como pacientes com urgências médicas | B71: ONA 2026: Subseção 2.2 Atendimento Ambulatorial | C71: ONA | D71: =_xlfn.XLOOKUP(E71,Organograma!H:H,Organograma!G:G,"") -> AMB - Unidade Ambulatorial | E71: Camila Amanda Cardoso dos Santos | F71: 46025 | G71: 46105 | H71: 46173 | I71: n/d | J71: 0.25 | K71: Em Andamento
A72: Nível 1 - 2.2.4 Requisito: Estruturar o processo assistencial de modo a promover a adesão ao tratamento, por meio da oferta regular de orientações e uso correto | B72: ONA 2026: Subseção 2.2 Atendimento Ambulatorial | C72: ONA | D72: =_xlfn.XLOOKUP(E72,Organograma!H:H,Organograma!G:G,"") -> AMB - Unidade Ambulatorial | E72: Camila Amanda Cardoso dos Santos | F72: 46025 | G72: 46105 | H72: 46173 | I72: n/d | J72: 0.25 | K72: Em Andamento
A73: Nível 1 - 2.2.5 Requisito: Estruturar as atividades da equipe multiprofissional de forma integrada, promovendo a interdisciplinaridade e o trabalho colaborativo | B73: ONA 2026: Subseção 2.2 Atendimento Ambulatorial | C73: ONA | D73: =_xlfn.XLOOKUP(E73,Organograma!H:H,Organograma!G:G,"") -> AMB - Unidade Ambulatorial | E73: Camila Amanda Cardoso dos Santos | F73: 46025 | G73: 46105 | H73: 46173 | I73: n/d | J73: 0.25 | K73: Em Andamento
A74: Nível 1 - 2.2.6 Requisito: Estabelecer critérios sistematizados para o diagnóstico das patologias, alinhados às especialidades e serviços oferecidos (CORE) | B74: ONA 2026: Subseção 2.2 Atendimento Ambulatorial | C74: ONA | D74: =_xlfn.XLOOKUP(E74,Organograma!H:H,Organograma!G:G,"") -> AMB - Unidade Ambulatorial | E74: Camila Amanda Cardoso dos Santos | F74: 46025 | G74: 46105 | H74: 46173 | I74: n/d | J74: 0.25 | K74: Em Andamento
A75: Nível 1 - 3.1.1 Requisito: Dispor de procedimentos e protocolos formalizados, padronizados e monitorados para o atendimento ao paciente/usuário | B75: ONA 2026: Subseção 3.1 Serviços de Análises Clínicas | C75: ONA | D75: =_xlfn.XLOOKUP(E75,Organograma!H:H,Organograma!G:G,"") -> AMB - Unidade Ambulatorial | E75: Camila Amanda Cardoso dos Santos | F75: 46025 | G75: n/d | H75: 46173 | I75: n/d | J75: 0 | K75: Não Iniciada
A76: Nível 1 - 3.1.2 Requisito: Estabelecer procedimentos padronizados, formais e rastreáveis que assegurem o atendimento prioritário, a execução e liberação (CORE) | B76: ONA 2026: Subseção 3.1 Serviços de Análises Clínicas | C76: ONA | D76: =_xlfn.XLOOKUP(E76,Organograma!H:H,Organograma!G:G,"") -> AMB - Unidade Ambulatorial | E76: Camila Amanda Cardoso dos Santos | F76: 46025 | G76: n/d | H76: 46173 | I76: n/d | J76: 0 | K76: Não Iniciada
A77: Nível 1 - 3.1.3 Requisito: Estabelecer procedimentos formalizados e atualizados, baseados em boas práticas laboratoriais e evidências científicas | B77: ONA 2026: Subseção 3.1 Serviços de Análises Clínicas | C77: ONA | D77: =_xlfn.XLOOKUP(E77,Organograma!H:H,Organograma!G:G,"") -> AMB - Unidade Ambulatorial | E77: Camila Amanda Cardoso dos Santos | F77: 46025 | G77: n/d | H77: 46173 | I77: n/d | J77: 0 | K77: Não Iniciada
A78: Nível 1 - 3.1.4 Requisito: Estabelecer, implementar e disseminar procedimentos padronizados para o preparo dos pacientes na realização dos exames laboratoriais | B78: ONA 2026: Subseção 3.1 Serviços de Análises Clínicas | C78: ONA | D78: =_xlfn.XLOOKUP(E78,Organograma!H:H,Organograma!G:G,"") -> AMB - Unidade Ambulatorial | E78: Camila Amanda Cardoso dos Santos | F78: 46025 | G78: n/d | H78: 46173 | I78: n/d | J78: 0 | K78: Não Iniciada
A79: Nível 1 - 3.1.5 Requisito: Estabelecer, implementar e garantir o uso do TCLE (Termo de Consentimento Livre e Esclarecido) para a realização de exames laborato | B79: ONA 2026: Subseção 3.1 Serviços de Análises Clínicas | C79: ONA | D79: =_xlfn.XLOOKUP(E79,Organograma!H:H,Organograma!G:G,"") -> AMB - Unidade Ambulatorial | E79: Camila Amanda Cardoso dos Santos | F79: 46025 | G79: n/d | H79: 46173 | I79: n/d | J79: 0 | K79: Não Iniciada
A80: Nível 1 - 3.1.6 Requisito: Estabelecer e implementar uma sistemática que assegure a rastreabilidade, conservação, estabilidade, armazenamento e descarte | B80: ONA 2026: Subseção 3.1 Serviços de Análises Clínicas | C80: ONA | D80: =_xlfn.XLOOKUP(E80,Organograma!H:H,Organograma!G:G,"") -> AMB - Unidade Ambulatorial | E80: Camila Amanda Cardoso dos Santos | F80: 46025 | G80: n/d | H80: 46173 | I80: n/d | J80: 0 | K80: Não Iniciada
A81: Nível 1 - 3.1.7 Requisito: Estabelecer e implementar procedimentos específicos e seguros para o transporte de materiais biológicos, assegurando sua integridade | B81: ONA 2026: Subseção 3.1 Serviços de Análises Clínicas | C81: ONA | D81: =_xlfn.XLOOKUP(E81,Organograma!H:H,Organograma!G:G,"") -> AMB - Unidade Ambulatorial | E81: Camila Amanda Cardoso dos Santos | F81: 46025 | G81: n/d | H81: 46173 | I81: n/d | J81: 0 | K81: Não Iniciada
A82: Nível 1 - 3.1.8 Requisito: Estabelecer e implementar critérios claros, objetivos e documentados para aceitação, restrição ou rejeição de materiais (CORE) | B82: ONA 2026: Subseção 3.1 Serviços de Análises Clínicas | C82: ONA | D82: =_xlfn.XLOOKUP(E82,Organograma!H:H,Organograma!G:G,"") -> AMB - Unidade Ambulatorial | E82: Camila Amanda Cardoso dos Santos | F82: 46025 | G82: n/d | H82: 46173 | I82: n/d | J82: 0 | K82: Não Iniciada
A83: Nível 1 - 3.1.9 Requisito: Estabelecer e implementar procedimentos específicos para o atendimento de situações de urgência, emergência e intercorrências | B83: ONA 2026: Subseção 3.1 Serviços de Análises Clínicas | C83: ONA | D83: =_xlfn.XLOOKUP(E83,Organograma!H:H,Organograma!G:G,"") -> AMB - Unidade Ambulatorial | E83: Camila Amanda Cardoso dos Santos | F83: 46025 | G83: n/d | H83: 46173 | I83: n/d | J83: 0 | K83: Não Iniciada
A84: Nível 1 - 3.1.10 Requisito: Estabelecer e implementar o controle de qualidade interno, considerando as regras de validação. | B84: ONA 2026: Subseção 3.1 Serviços de Análises Clínicas | C84: ONA | D84: =_xlfn.XLOOKUP(E84,Organograma!H:H,Organograma!G:G,"") -> AMB - Unidade Ambulatorial | E84: Camila Amanda Cardoso dos Santos | F84: 46025 | G84: n/d | H84: 46173 | I84: n/d | J84: 0 | K84: Não Iniciada
A85: Nível 1 - 3.1.11 Requisito: O laboratório deve participar de programas externos de avaliação da qualidade reconhecidos, abrangendo os diferentes tipos de exames | B85: ONA 2026: Subseção 3.1 Serviços de Análises Clínicas | C85: ONA | D85: =_xlfn.XLOOKUP(E85,Organograma!H:H,Organograma!G:G,"") -> AMB - Unidade Ambulatorial | E85: Camila Amanda Cardoso dos Santos | F85: 46025 | G85: n/d | H85: 46173 | I85: n/d | J85: 0 | K85: Não Iniciada
A86: Nível 1 - 3.1.12 Requisito: Estabelecer e implementar uma sistemática para a realização de testes laboratoriais remotos, assegurando a padronização, rastrear | B86: ONA 2026: Subseção 3.1 Serviços de Análises Clínicas | C86: ONA | D86: =_xlfn.XLOOKUP(E86,Organograma!H:H,Organograma!G:G,"") -> AMB - Unidade Ambulatorial | E86: Camila Amanda Cardoso dos Santos | F86: 46025 | G86: n/d | H86: 46173 | I86: n/d | J86: 0 | K86: Não Iniciada
... A108: Nível 1 - 3.3.7 Requisito: Dispor de fluxo estruturado para o atendimento de situações de urgência e emergência, estejam ou não relacionadas aos exames | B108: ONA 2026: Subseção 3.3 Métodos Gráficos | C108: ONA | D108: =_xlfn.XLOOKUP(E108,Organograma!H:H,Organograma!G:G,"") -> AMB - Unidade Ambulatorial | E108: Camila Amanda Cardoso dos Santos | F108: 46025 | G108: n/d | H108: 46173 | I108: n/d | J108: 0 | K108: Não Iniciada
A109: Nível 1 - 3.4.1 Requisito: identificar, avaliar e monitorar os riscos com potencial impacto assistencial, adotando ações preventivas (CORE) | B109: ONA 2026: Subseção 3.4 Diagnóstico por Imagem | C109: ONA | D109: =_xlfn.XLOOKUP(E109,Organograma!H:H,Organograma!G:G,"") -> AMB - Unidade Ambulatorial | E109: Camila Amanda Cardoso dos Santos | F109: 46025 | G109: 46104 | H109: 46173 | I109: n/d | J109: 0.5 | K109: Em Andamento
A110: Nível 1 - 3.4.2 Requisito: Assegurar que o TCLE (Termo de Consentimento Livre e Esclarecido) seja aplicado e formalizado antes da realização de procedimentos | B110: ONA 2026: Subseção 3.4 Diagnóstico por Imagem | C110: ONA | D110: =_xlfn.XLOOKUP(E110,Organograma!H:H,Organograma!G:G,"") -> AMB - Unidade Ambulatorial | E110: Camila Amanda Cardoso dos Santos | F110: 46025 | G110: 46104 | H110: 46173 | I110: n/d | J110: 0.75 | K110: Em Andamento
A111: Nível 1 - 3.4.3 Requisito: Aplicar o TCLE (Termo de Consentimento Livre e Esclarecido) Anestésico antes da realização de qualquer procedimento que envolva sedaç | B111: ONA 2026: Subseção 3.4 Diagnóstico por Imagem | C111: ONA | D111: =_xlfn.XLOOKUP(E111,Organograma!H:H,Organograma!G:G,"") -> AMB - Unidade Ambulatorial | E111: Camila Amanda Cardoso dos Santos | F111: 46025 | G111: 46104 | H111: 46173 | I111: n/d | J111: 0.25 | K111: Em Andamento
A112: Nível 1 - 3.4.4 Requisito: Estabelecer, revisar periodicamente e aplicar protocolos de Diagnóstico por Imagem baseados em diretrizes clínicas reconhecidas | B112: ONA 2026: Subseção 3.4 Diagnóstico por Imagem | C112: ONA | D112: =_xlfn.XLOOKUP(E112,Organograma!H:H,Organograma!G:G,"") -> AMB - Unidade Ambulatorial | E112: Camila Amanda Cardoso dos Santos | F112: 46025 | G112: 46104 | H112: 46173 | I112: n/d | J112: 0.5 | K112: Em Andamento
A113: Nível 1 - 3.4.5 Requisito: Dispor e aplicar protocolo de segurança para o processo de anestesia e/ou sedação, contemplando todas as etapas | B113: ONA 2026: Subseção 3.4 Diagnóstico por Imagem | C113: ONA | D113: =_xlfn.XLOOKUP(E113,Organograma!H:H,Organograma!G:G,"") -> AMB - Unidade Ambulatorial | E113: Camila Amanda Cardoso dos Santos | F113: 46025 | G113: 46104 | H113: 46173 | I113: n/d | J113: 0.25 | K113: Em Andamento
A114: Nível 1 - 3.4.6 Requisito: Dispor de sistemática formal e padronizada que assegure a concordância e consistência nas interpretações de exames de imagem | B114: ONA 2026: Subseção 3.4 Diagnóstico por Imagem | C114: ONA | D114: =_xlfn.XLOOKUP(E114,Organograma!H:H,Organograma!G:G,"") -> AMB - Unidade Ambulatorial | E114: Camila Amanda Cardoso dos Santos | F114: 46025 | G114: 46104 | H114: 46173 | I114: n/d | J114: 0.25 | K114: Em Andamento
A115: Nível 1 - 3.4.7 Requisito: Estabelecer processos formalizados e rastreáveis para a emissão e comunicação de resultados parciais de exames de Diagnóstico | B115: ONA 2026: Subseção 3.4 Diagnóstico por Imagem | C115: ONA | D115: =_xlfn.XLOOKUP(E115,Organograma!H:H,Organograma!G:G,"") -> AMB - Unidade Ambulatorial | E115: Camila Amanda Cardoso dos Santos | F115: 46025 | G115: 46133 | H115: 46173 | I115: n/d | J115: 0.5 | K115: Em Andamento
A116: Nível 1 - 3.4.8 Requisito: Estabelecer, implementar e manter uma sistemática formal de identificação e comunicação de resultados críticos (CORE) | B116: ONA 2026: Subseção 3.4 Diagnóstico por Imagem | C116: ONA | D116: =_xlfn.XLOOKUP(E116,Organograma!H:H,Organograma!G:G,"") -> AMB - Unidade Ambulatorial | E116: Camila Amanda Cardoso dos Santos | F116: 46025 | G116: 46133 | H116: 46173 | I116: n/d | J116: 0.75 | K116: Em Andamento
A117: Nível 1 - 3.4.9 Requisito: Assegurar que as decisões assistenciais relacionadas aos procedimentos de diagnóstico por imagem sejam compartilhadas e registradas | B117: ONA 2026: Subseção 3.4 Diagnóstico por Imagem | C117: ONA | D117: =_xlfn.XLOOKUP(E117,Organograma!H:H,Organograma!G:G,"") -> AMB - Unidade Ambulatorial | E117: Camila Amanda Cardoso dos Santos | F117: 46025 | G117: 46133 | H117: 46173 | I117: n/d | J117: 0.5 | K117: Em Andamento
A118: Nível 1 - 3.4.10 Requisito: Estabelecer e cumprir o Programa de Proteção Radiológica e Segurança em Diagnóstico por Imagem | B118: ONA 2026: Subseção 3.4 Diagnóstico por Imagem | C118: ONA | D118: =_xlfn.XLOOKUP(E118,Organograma!H:H,Organograma!G:G,"") -> AMB - Unidade Ambulatorial | E118: Camila Amanda Cardoso dos Santos | F118: 46025 | G118: 46104 | H118: 46173 | I118: n/d | J118: 0.75 | K118: Em Andamento
A119: Nível 1 - 3.4.11 Requisito: Estabelecer fluxos padronizados para o atendimento a situações de urgência e emergência, sejam elas decorrentes dos exames | B119: ONA 2026: Subseção 3.4 Diagnóstico por Imagem | C119: ONA | D119: =_xlfn.XLOOKUP(E119,Organograma!H:H,Organograma!G:G,"") -> AMB - Unidade Ambulatorial | E119: Camila Amanda Cardoso dos Santos | F119: 46025 | G119: 46133 | H119: 46173 | I119: n/d | J119: 0.5 | K119: Em Andamento
A120: Nível 1 - 3.4.12 Requisito: Dispor de mecanismos formais e procedimentos padronizados que assegurem a identificação adequada, conservação, rastreabilidade | B120: ONA 2026: Subseção 3.4 Diagnóstico por Imagem | C120: ONA | D120: =_xlfn.XLOOKUP(E120,Organograma!H:H,Organograma!G:G,"") -> AMB - Unidade Ambulatorial | E120: Camila Amanda Cardoso dos Santos | F120: 46025 | G120: 46104 | H120: 46173 | I120: n/d | J120: 0.75 | K120: Em Andamento
A121: Nível 1 - 2.8.1 Requisito: Estabelecer protocolos assistenciais e clínicos alinhados ao perfil epidemiológico da unidade (CORE) | B121: ONA 2026: Subseção 2.8 Internação Materno | C121: ONA | D121: =_xlfn.XLOOKUP(E121,Organograma!H:H,Organograma!G:G,"") -> PAM - Pronto Atendimento Materno | E121: Camila Nascimento Santos Santana | F121: 46025 | G121: n/d | H121: 46173 | I121: n/d | J121: 0 | K121: Não Iniciada
A122: Nível 1 - 2.8.2 Requisito: Estabelecer e cumprir metodologia ou ferramenta para a identificação de pacientes/usuários críticos, bem como para o fluxo (CORE) | B122: ONA 2026: Subseção 2.8 Internação Materno | C122: ONA | D122: =_xlfn.XLOOKUP(E122,Organograma!H:H,Organograma!G:G,"") -> PAM - Pronto Atendimento Materno | E122: Camila Nascimento Santos Santana | F122: 46025 | G122: n/d | H122: 46173 | I122: n/d | J122: 0 | K122: Não Iniciada
A123: Nível 1 - 2.8.3 Requisito: Estabelecer protocolos para o atendimento de urgências e emergências, com base em diretrizes e evidências científicas atualizadas | B123: ONA 2026: Subseção 2.8 Internação Materno | C123: ONA | D123: =_xlfn.XLOOKUP(E123,Organograma!H:H,Organograma!G:G,"") -> PAM - Pronto Atendimento Materno | E123: Camila Nascimento Santos Santana | F123: 46025 | G123: n/d | H123: 46173 | I123: n/d | J123: 0 | K123: Não Iniciada
A124: Nível 1 - 2.8.4 Requisito: Estabelecer, acompanhar, avaliar e, quando necessário, adequar o plano terapêutico individualizado, considerando os diagnósticos | B124: ONA 2026: Subseção 2.8 Internação Materno | C124: ONA | D124: =_xlfn.XLOOKUP(E124,Organograma!H:H,Organograma!G:G,"") -> PAM - Pronto Atendimento Materno | E124: Camila Nascimento Santos Santana | F124: 46025 | G124: n/d | H124: 46173 | I124: n/d | J124: 0 | K124: Não Iniciada
A125: Nível 1 - 2.8.5 Requisito: Estabelecer o plano interdisciplinar de assistência, fundamentado no plano terapêutico definido, considerando o grau de complexidade | B125: ONA 2026: Subseção 2.8 Internação Materno | C125: ONA | D125: =_xlfn.XLOOKUP(E125,Organograma!H:H,Organograma!G:G,"") -> PAM - Pronto Atendimento Materno | E125: Camila Nascimento Santos Santana | F125: 46025 | G125: n/d | H125: 46173 | I125: n/d | J125: 0 | K125: Não Iniciada
A126: Nível 1 - 2.8.6 Requisito: Dispor de plano multidisciplinar de alta, elaborado com conhecimento do paciente/ cliente e/ou acompanhantes | B126: ONA 2026: Subseção 2.8 Internação Materno | C126: ONA | D126: =_xlfn.XLOOKUP(E126,Organograma!H:H,Organograma!G:G,"") -> PAM - Pronto Atendimento Materno | E126: Camila Nascimento Santos Santana | F126: 46025 | G126: n/d | H126: 46173 | I126: n/d | J126: 0 | K126: Não Iniciada
A127: Nível 1 - 2.8.7 Requisito: Promover o envolvimento do paciente/cliente e/ou acompanhante quanto aos seus procedimentos, riscos e plano terapêutico | B127: ONA 2026: Subseção 2.8 Internação Materno | C127: ONA | D127: =_xlfn.XLOOKUP(E127,Organograma!H:H,Organograma!G:G,"") -> PAM - Pronto Atendimento Materno | E127: Camila Nascimento Santos Santana | F127: 46025 | G127: n/d | H127: 46173 | I127: n/d | J127: 0 | K127: Não Iniciada
A128: Nível 1 - 2.11.1 Requisito: Cumprir sistemática de agendamento do pré-natal e acompanha a demanda | B128: ONA 2026: Subseção 2.11 Atendimento Obstétrico Ambulatório | C128: ONA | D128: =_xlfn.XLOOKUP(E128,Organograma!H:H,Organograma!G:G,"") -> PAM - Pronto Atendimento Materno | E128: Camila Nascimento Santos Santana | F128: 46025 | G128: n/d | H128: 46173 | I128: n/d | J128: 0 | K128: Não Iniciada
A129: Nível 1 - 2.11.2 Requisito: Estabelecer critérios clínicos e fluxo de encaminhamento para atendimento no ambulatório de pré-natal de alto risco (CORE) | B129: ONA 2026: Subseção 2.11 Atendimento Obstétrico Ambulatório | C129: ONA | D129: =_xlfn.XLOOKUP(E129,Organograma!H:H,Organograma!G:G,"") -> PAM - Pronto Atendimento Materno | E129: Camila Nascimento Santos Santana | F129: 46025 | G129: n/d | H129: 46173 | I129: n/d | J129: 0 | K129: Não Iniciada
A130: Nível 1 - 2.11.3 Requisito: Estabelecer protocolos assistenciais para as complicações obstétricas | B130: ONA 2026: Subseção 2.11 Atendimento Obstétrico Ambulatório | C130: ONA | D130: =_xlfn.XLOOKUP(E130,Organograma!H:H,Organograma!G:G,"") -> PAM - Pronto Atendimento Materno | E130: Camila Nascimento Santos Santana | F130: 46025 | G130: n/d | H130: 46173 | I130: n/d | J130: 0 | K130: Não Iniciada
A131: Nível 1 - 2.11.4 Requisito: Definir e implantar protocolos assistenciais para o acompanhamento do pré-natal, considerando o perfil das pessoas gestantes | B131: ONA 2026: Subseção 2.11 Atendimento Obstétrico Ambulatório | C131: ONA | D131: =_xlfn.XLOOKUP(E131,Organograma!H:H,Organograma!G:G,"") -> PAM - Pronto Atendimento Materno | E131: Camila Nascimento Santos Santana | F131: 46025 | G131: n/d | H131: 46173 | I131: n/d | J131: 0 | K131: Não Iniciada
A132: Nível 1 - 2.11.5 Requisito: Apoiar a elaboração do plano de parto pelas pessoas gestantes, com mediação de profissionais de saúde, promovendo autonomia | B132: ONA 2026: Subseção 2.11 Atendimento Obstétrico Ambulatório | C132: ONA | D132: =_xlfn.XLOOKUP(E132,Organograma!H:H,Organograma!G:G,"") -> PAM - Pronto Atendimento Materno | E132: Camila Nascimento Santos Santana | F132: 46025 | G132: n/d | H132: 46173 | I132: n/d | J132: 0 | K132: Não Iniciada
... A151: Nível 1 - 2.12.1 Requisito: Estabelecer protocolos e procedimentos assistenciais e clínicos alinhados ao perfil epidemiológico da população atendida. | B151: ONA 2026: Subseção 2.12 Atendimento Neonatal | C151: ONA | D151: =_xlfn.XLOOKUP(E151,Organograma!H:H,Organograma!G:G,"") -> PAM - Pronto Atendimento Materno | E151: Camila Nascimento Santos Santana | F151: 46025 | G151: n/d | H151: 46173 | I151: n/d | J151: 0 | K151: Não Iniciada
A152: Nível 1 - 2.12.2 Requisito: Estabelecer e monitorar critérios para admissão e alta de pacientes na UTI (Unidade de Terapia Intensiva) neonatal (CORE) | B152: ONA 2026: Subseção 2.12 Atendimento Neonatal | C152: ONA | D152: =_xlfn.XLOOKUP(E152,Organograma!H:H,Organograma!G:G,"") -> PAM - Pronto Atendimento Materno | E152: Camila Nascimento Santos Santana | F152: 46025 | G152: 46207 | H152: 46173 | I152: 46207 | J152: 1 | K152: Concluída
A153: Nível 1 - 2.12.3 Requisito: Utilizar metodologia para classificação da gravidade do paciente/cliente, relacionando a taxa de mortalidade (CORE) | B153: ONA 2026: Subseção 2.12 Atendimento Neonatal | C153: ONA | D153: =_xlfn.XLOOKUP(E153,Organograma!H:H,Organograma!G:G,"") -> PAM - Pronto Atendimento Materno | E153: Camila Nascimento Santos Santana | F153: 46025 | G153: 46057 | H153: 46173 | I153: 46057 | J153: 1 | K153: Concluída
A154: Nível 1 - 2.12.4 Requisito: Identificar os riscos assistenciais do paciente/cliente em todas as etapas do cuidado e estabelecer ações preventivas | B154: ONA 2026: Subseção 2.12 Atendimento Neonatal | C154: ONA | D154: =_xlfn.XLOOKUP(E154,Organograma!H:H,Organograma!G:G,"") -> PAM - Pronto Atendimento Materno | E154: Camila Nascimento Santos Santana | F154: 46025 | G154: n/d | H154: 46173 | I154: n/d | J154: 0 | K154: Não Iniciada
A155: Nível 1 - 2.12.5 Requisito: Estabelecer e cumprir o processo de alta do paciente, assegurando a segurança e a continuidade na transição do cuidado | B155: ONA 2026: Subseção 2.12 Atendimento Neonatal | C155: ONA | D155: =_xlfn.XLOOKUP(E155,Organograma!H:H,Organograma!G:G,"") -> PAM - Pronto Atendimento Materno | E155: Camila Nascimento Santos Santana | F155: 46025 | G155: n/d | H155: 46173 | I155: n/d | J155: 0 | K155: Não Iniciada
A156: Nível 1 - 2.12.6 Requisito: Cumprir os procedimentos de segurança na coleta e utilização do leite materno | B156: ONA 2026: Subseção 2.12 Atendimento Neonatal | C156: ONA | D156: =_xlfn.XLOOKUP(E156,Organograma!H:H,Organograma!G:G,"") -> PAM - Pronto Atendimento Materno | E156: Camila Nascimento Santos Santana | F156: 46025 | G156: 46142 | H156: 46173 | I156: n/d | J156: 0.75 | K156: Em Andamento
A157: Nível 1 - 2.12.7 Requisito: Cumprir os procedimentos de segurança para a manipulação do leite | B157: ONA 2026: Subseção 2.12 Atendimento Neonatal | C157: ONA | D157: =_xlfn.XLOOKUP(E157,Organograma!H:H,Organograma!G:G,"") -> PAM - Pronto Atendimento Materno | E157: Camila Nascimento Santos Santana | F157: 46025 | G157: 46142 | H157: 46173 | I157: n/d | J157: 0.75 | K157: Em Andamento
A158: Nível 1 - 2.12.8 Requisito: Cumprir as diretrizes estabelecidas para a identificação e mobilização de doadores de órgãos, tecidos e células | B158: ONA 2026: Subseção 2.12 Atendimento Neonatal | C158: ONA | D158: =_xlfn.XLOOKUP(E158,Organograma!H:H,Organograma!G:G,"") -> PAM - Pronto Atendimento Materno | E158: Camila Nascimento Santos Santana | F158: 46025 | G158: 46142 | H158: 46173 | I158: n/d | J158: 0.25 | K158: Em Andamento
A159: Implantar meios de comunicação clara e eficiente com os usuários (Orientações pré, intra e pós cuidado). | B159: Plano de Ação PE: Desdobramento Implantar Política de Acolhimento | C159: Planejamento Estratégico | D159: =_xlfn.XLOOKUP(E159,Organograma!H:H,Organograma!G:G,"") -> GA - Gerência Assistencial | E159: Clariane Acário Martins | F159: 46026 | G159: n/d | H159: 46326 | I159: n/d | J159: 0 | K159: Não Iniciada
A160: Nível 1 - 2.1.1.1 Requisito: Desenvolver atividades voltadas à promoção de saúde de acordo com o perfil epidemiológico | B160: ONA 2026: Subseção 2.1 Jornada do Paciente | C160: ONA | D160: =_xlfn.XLOOKUP(E160,Organograma!H:H,Organograma!G:G,"") -> GA - Gerência Assistencial | E160: Clariane Acário Martins | F160: 46025 | G160: 46026 | H160: 46173 | I160: n/d | J160: 0.25 | K160: Em Andamento
A161: Nível 1 - 2.1.1.2 Requisito: Estabelecer, implementar e atualizar meios e canais de comunicação para promoção da saúde e prevenção de doenças | B161: ONA 2026: Subseção 2.1 Jornada do Paciente | C161: ONA | D161: =_xlfn.XLOOKUP(E161,Organograma!H:H,Organograma!G:G,"") -> GA - Gerência Assistencial | E161: Clariane Acário Martins | F161: 46025 | G161: 46026 | H161: 46173 | I161: n/d | J161: 0.25 | K161: Em Andamento
A162: Nível 1 - 2.1.1.3 Requisito: Definir escopo de atendimento para acesso aos usuários de acordo com o perfil epidemiológico | B162: ONA 2026: Subseção 2.1 Jornada do Paciente | C162: ONA | D162: =_xlfn.XLOOKUP(E162,Organograma!H:H,Organograma!G:G,"") -> GA - Gerência Assistencial | E162: Clariane Acário Martins | F162: 46025 | G162: n/d | H162: 46173 | I162: n/d | J162: 0 | K162: Não Iniciada
A163: Nível 1 - 2.1.1.4 Requisito: Estabelecer e orientar a população em relação às diretrizes para atendimento por telessaúde | B163: ONA 2026: Subseção 2.1 Jornada do Paciente | C163: ONA | D163: =_xlfn.XLOOKUP(E163,Organograma!H:H,Organograma!G:G,"") -> GA - Gerência Assistencial | E163: Clariane Acário Martins | F163: 46025 | G163: n/d | H163: 46173 | I163: n/d | J163: 0 | K163: Não Iniciada
A164: Nível 1 - 2.1.2.1 Requisito: Definir fluxos e critérios clínicos de precedência para admissão de pacientes/usuários, incluindo os provenientes de outras organiz | B164: ONA 2026: Subseção 2.1 Jornada do Paciente | C164: ONA | D164: =_xlfn.XLOOKUP(E164,Organograma!H:H,Organograma!G:G,"") -> GA - Gerência Assistencial | E164: Clariane Acário Martins | F164: 46025 | G164: n/d | H164: 46173 | I164: n/d | J164: 0 | K164: Não Iniciada
A165: Nível 1 - 2.1.2.2 Requisito: Estabelecer critérios e processos para o gerenciamento de filas, disponibilidade de agendamentos e tempo de espera | B165: ONA 2026: Subseção 2.1 Jornada do Paciente | C165: ONA | D165: =_xlfn.XLOOKUP(E165,Organograma!H:H,Organograma!G:G,"") -> GA - Gerência Assistencial | E165: Clariane Acário Martins | F165: 46025 | G165: n/d | H165: 46173 | I165: n/d | J165: 0 | K165: Não Iniciada
...

Sheet INDICADORES
A1: TiPO | B1: Indicadores | C1: Status | D1: Responsavel | E1: Setor | F1: Data da Verificação | G1: Serial
A2: Atraso na Alimentação | B2: Percentual de Acurácia de Alto Custo - Almoxarifado (Resultado) | C2: Fora do Prazo | D2: =_xlfn.XLOOKUP(E2,Organograma!G:G,Organograma!H:H,"") -> Madson de Souza Santos | E2: ALM - Almoxarifado | F2: 08/05/2026 | G2: NC 3318 / 2026
A3: Atraso na Análise | B3: Percentual de Acurácia de Alto Custo - Almoxarifado (Resultado) | C3: Fora do Prazo | D3: =_xlfn.XLOOKUP(E3,Organograma!G:G,Organograma!H:H,"") -> Madson de Souza Santos | E3: ALM - Almoxarifado | F3: 11/05/2026 | G3: NC 3441 / 2026
A4: Atraso na Alimentação | B4: Percentual de Atendimento (Processo) | C4: Fora do Prazo | D4: =_xlfn.XLOOKUP(E4,Organograma!G:G,Organograma!H:H,"") -> Madson de Souza Santos | E4: ALM - Almoxarifado | F4: 08/05/2026 | G4: NC 3316 / 2026
A5: Atraso na Análise | B5: Percentual de Atendimento (Processo) | C5: Fora do Prazo | D5: =_xlfn.XLOOKUP(E5,Organograma!G:G,Organograma!H:H,"") -> Madson de Souza Santos | E5: ALM - Almoxarifado | F5: 11/05/2026 | G5: NC 3439 / 2026
A6: Atraso na Alimentação | B6: Perda Por Validade E Avarias (Resultado) | C6: Fora do Prazo | D6: =_xlfn.XLOOKUP(E6,Organograma!G:G,Organograma!H:H,"") -> Madson de Souza Santos | E6: ALM - Almoxarifado | F6: 08/05/2026 | G6: NC 3317 / 2026
A7: Atraso na Análise | B7: Perda Por Validade E Avarias (Resultado) | C7: Fora do Prazo | D7: =_xlfn.XLOOKUP(E7,Organograma!G:G,Organograma!H:H,"") -> Madson de Souza Santos | E7: ALM - Almoxarifado | F7: 11/05/2026 | G7: NC 3440 / 2026
A8: Atraso na Análise | B8: Quantidade de Itens Solicitados (Estrutura) | C8: Fora do Prazo | D8: =_xlfn.XLOOKUP(E8,Organograma!G:G,Organograma!H:H,"") -> Madson de Souza Santos | E8: ALM - Almoxarifado | F8: 11/05/2026 | G8: NC 3438 / 2026
A9: Atraso na Análise | B9: Percentual de Pacientes com Tempo de Espera Superior a 30 Minutos no Ambulatório (Processo) | C9: Fora do Prazo | D9: =_xlfn.XLOOKUP(E9,Organograma!G:G,Organograma!H:H,"") -> Camila Amanda Cardoso dos Santos | E9: AMB - Unidade Ambulatorial | F9: 12/05/2026 | G9: NC 3574 / 2026
A10: Atraso na Análise | B10: Taxa de Absenteismo em Consultas Ambulatoriais (Resultado) | C10: Fora do Prazo | D10: =_xlfn.XLOOKUP(E10,Organograma!G:G,Organograma!H:H,"") -> Camila Amanda Cardoso dos Santos | E10: AMB - Unidade Ambulatorial | F10: 12/05/2026 | G10: NC 3573 / 2026
A11: Atraso na Análise | B11: Acompanhamento Transfusional (Processo) | C11: Fora do Prazo | D11: =_xlfn.XLOOKUP(E11,Organograma!G:G,Organograma!H:H,"") -> Camila Amanda Cardoso dos Santos | E11: AT - Agência Transfusional | F11: 12/05/2026 | G11: NC 3588 / 2026
A12: Atraso na Alimentação | B12: Auditoria Não Conformidade Transfusional (Processo) | C12: Fora do Prazo | D12: =_xlfn.XLOOKUP(E12,Organograma!G:G,Organograma!H:H,"") -> Camila Amanda Cardoso dos Santos | E12: AT - Agência Transfusional | F12: 08/05/2026 | G12: NC 3413 / 2026
A13: Atraso na Alimentação | B13: Cobertura de Postos de Acesso (Estrutura) | C13: Fora do Prazo | D13: =_xlfn.XLOOKUP(E13,Organograma!G:G,Organograma!H:H,"") -> Janaina Bernardes Ayer | E13: CA - Controle de Acesso | F13: 08/05/2026 | G13: NC 3360 / 2026
... A286: Atraso na Análise | B286: Diárias de Pacientes na Unidade de Internação Ortopédica (Estrutura) | C286: Fora do Prazo | D286: =_xlfn.XLOOKUP(E286,Organograma!G:G,Organograma!H:H,"") -> Debora De Oliveira Alvarenga | E286: UIO - Unidade de Internação Ortopédica | F286: 13/05/2026 | G286: NC 3606 / 2026
A287: Alimentação em dia | B287: Absenteísmo (Resultado) | C287: Dentro do Prazo | D287: =_xlfn.XLOOKUP(E287,Organograma!G:G,Organograma!H:H,"") -> Mylena Justino da Silva Brito | E287: APGQ - Assessoria de Planejamento e Gestão da Qualidade | F287: 46155 | G287: n/a
A288: Alimentação em dia | B288: Auditorias dos Processos Laboratoriais (Processo) | C288: Dentro do Prazo | D288: =_xlfn.XLOOKUP(E288,Organograma!G:G,Organograma!H:H,"") -> Camila Amanda Cardoso dos Santos | E288: LAB - Unidade de Análises Clínicas | F288: 46155 | G288: n/a
A289: Alimentação em dia | B289: Acompanhamento Transfusional (Processo) | C289: Dentro do Prazo | D289: =_xlfn.XLOOKUP(E289,Organograma!G:G,Organograma!H:H,"") -> Camila Amanda Cardoso dos Santos | E289: AT - Agência Transfusional | F289: 46155 | G289: n/a
A290: Alimentação em dia | B290: Assertividade da Alta Hospitalar conforme Previsão Médica - Clínica Cirúrgica (Resultado) | C290: Dentro do Prazo | D290: =_xlfn.XLOOKUP(E290,Organograma!G:G,Organograma!H:H,"") -> Debora De Oliveira Alvarenga | E290: UICC - Unidade de Internação Cirúrgica | F290: 46155 | G290: n/a
A291: Alimentação em dia | B291: Assertividade da Alta Hospitalar conforme Previsão Médica (Clínica Ortopédica) (Resultado) | C291: Dentro do Prazo | D291: =_xlfn.XLOOKUP(E291,Organograma!G:G,Organograma!H:H,"") -> Debora De Oliveira Alvarenga | E291: UIO - Unidade de Internação Ortopédica | F291: 46155 | G291: n/a
A292: Alimentação em dia | B292: Assuntos Diversos | C292: Dentro do Prazo | D292: =_xlfn.XLOOKUP(E292,Organograma!G:G,Organograma!H:H,"") -> Mylena Justino da Silva Brito | E292: APGQ - Assessoria de Planejamento e Gestão da Qualidade | F292: 46155 | G292: n/a
A293: Alimentação em dia | B293: Atendimentos Ambulatórios Não Médicos | C293: Dentro do Prazo | D293: =_xlfn.XLOOKUP(E293,Organograma!G:G,Organograma!H:H,"") -> Mylena Justino da Silva Brito | E293: APGQ - Assessoria de Planejamento e Gestão da Qualidade | F293: 46155 | G293: n/a
A294: Alimentação em dia | B294: Atendimentos no Pronto Socorro (Estrutura) | C294: Dentro do Prazo | D294: =_xlfn.XLOOKUP(E294,Organograma!G:G,Organograma!H:H,"") -> Mylena Justino da Silva Brito | E294: APGQ - Assessoria de Planejamento e Gestão da Qualidade | F294: 46155 | G294: n/a
A295: Alimentação em dia | B295: Auditoria Não Conformidade Transfusional (Processo) | C295: Dentro do Prazo | D295: =_xlfn.XLOOKUP(E295,Organograma!G:G,Organograma!H:H,"") -> Camila Amanda Cardoso dos Santos | E295: AT - Agência Transfusional | F295: 46155 | G295: n/a
A296: Alimentação em dia | B296: Índice de Hora de Treinamento por Colaborador (Resultado) | C296: Dentro do Prazo | D296: =_xlfn.XLOOKUP(E296,Organograma!G:G,Organograma!H:H,"") -> Cleudimara Pereira Maciel Souza | E296: NEP - Núcleo de Educação Permanente | F296: 46155 | G296: n/a
A297: Alimentação em dia | B297: Avaliação de Desempenho dos Internos/residentes (Resultado) | C297: Dentro do Prazo | D297: =_xlfn.XLOOKUP(E297,Organograma!G:G,Organograma!H:H,"") -> Cintia Kelciane Gomes de Oliveira | E297: CEP - Centro de Ensino e Pesquisa | F297: 46155 | G297: n/a
A298: Alimentação em dia | B298: Cobertura De Estoque De Itens Críticos (Processo) | C298: Dentro do Prazo | D298: =_xlfn.XLOOKUP(E298,Organograma!G:G,Organograma!H:H,"") -> Gleyce Kelly Damaceno Barros Cavalcante | E298: SUP - Suprimentos | F298: 46155 | G298: n/a
... A611: Atraso na Alimentação | B611: Total de Acesso de Pacientes (Processo) | C611: Fora do Prazo | D611: =_xlfn.XLOOKUP(E611,Organograma!G:G,Organograma!H:H,"") -> Janaina Bernardes Ayer | E611: REC - Recepção | F611: 46155 | G611: n/a
A612: Análise em dia | B612: Absenteísmo (Resultado) | C612: Dentro do Prazo | D612: Mylena Justino da Silva Brito | E612: APGQ - Assessoria de Planejamento e Gestão da Qualidade | F612: 46155 | G612: n/a
A613: Análise em dia | B613: Auditorias dos Processos Laboratoriais (Processo) | C613: Dentro do Prazo | D613: Camila Amanda Cardoso dos Santos | E613: LAB - Unidade de Análises Clínicas | F613: 46155 | G613: n/a
A614: Análise em dia | B614: Acompanhamento Transfusional (Processo) | C614: Dentro do Prazo | D614: Camila Amanda Cardoso dos Santos | E614: AT - Agência Transfusional | F614: 46155 | G614: n/a
A615: Análise em dia | B615: Assertividade da Alta Hospitalar conforme Previsão Médica - Clínica Cirúrgica (Resultado) | C615: Dentro do Prazo | D615: Debora De Oliveira Alvarenga | E615: UICC - Unidade de Internação Cirúrgica | F615: 46155 | G615: n/a
A616: Análise em dia | B616: Assertividade da Alta Hospitalar conforme Previsão Médica (Clínica Ortopédica) (Resultado) | C616: Dentro do Prazo | D616: Debora De Oliveira Alvarenga | E616: UIO - Unidade de Internação Ortopédica | F616: 46155 | G616: n/a
A617: Análise em dia | B617: Assuntos Diversos | C617: Dentro do Prazo | D617: Mylena Justino da Silva Brito | E617: APGQ - Assessoria de Planejamento e Gestão da Qualidade | F617: 46155 | G617: n/a
A618: Análise em dia | B618: Atendimentos Ambulatórios Não Médicos | C618: Dentro do Prazo | D618: Mylena Justino da Silva Brito | E618: APGQ - Assessoria de Planejamento e Gestão da Qualidade | F618: 46155 | G618: n/a
A619: Análise em dia | B619: Atendimentos no Pronto Socorro (Estrutura) | C619: Dentro do Prazo | D619: Mylena Justino da Silva Brito | E619: APGQ - Assessoria de Planejamento e Gestão da Qualidade | F619: 46155 | G619: n/a
A620: Análise em dia | B620: Auditoria Não Conformidade Transfusional (Processo) | C620: Dentro do Prazo | D620: Camila Amanda Cardoso dos Santos | E620: AT - Agência Transfusional | F620: 46155 | G620: n/a
A621: Análise em dia | B621: Índice de Hora de Treinamento por Colaborador (Resultado) | C621: Dentro do Prazo | D621: Cleudimara Pereira Maciel Souza | E621: NEP - Núcleo de Educação Permanente | F621: 46155 | G621: n/a
A622: Análise em dia | B622: Avaliação de Desempenho dos Internos/residentes (Resultado) | C622: Dentro do Prazo | D622: Cintia Kelciane Gomes de Oliveira | E622: CEP - Centro de Ensino e Pesquisa | F622: 46155 | G622: n/a
A623: Análise em dia | B623: Cobertura De Estoque De Itens Críticos (Processo) | C623: Dentro do Prazo | D623: Gleyce Kelly Damaceno Barros Cavalcante | E623: SUP - Suprimentos | F623: 46155 | G623: n/a
... A898: Análise em dia | B898: Volume de Leite Humano Aproveitado (Resultado) | C898: Dentro do Prazo | D898: Flavia de Souza Moura | E898: BLH - Banco de Leite Humano | F898: 46155 | G898: n/a

Sheet NOTIFICAÇÕES
A1: Titulo | B1: Serial | C1: Departamento/Setor | D1: Responsável | E1: Situação | F1: Anexos | G1: Autor | H1: Criado em | I1: Data da ocorrência | J1: Descrição | K1: Status | L1: Última verificação | M1: Processo Notificado | N1: Processo Notificador | O1: Local onde ocorreu o incidente (Nºleito | P1: Classificação Incidente | Q1: Tipo
A2: RN sem alimentação | B2: INC 1511 / 2026 | C2: Gerência de Cuidados Materno/Infantil / Unidade de Internação Ginecobstétrica - ALCOM | D2: Mylena Justino da Silva Brito | E2: Finalizada | F2: 0 | G2: Ana Carolina da Costa Frazao Cerqueira | H2: 01/01/2026 | I2: 01/01/2026 | J2: por volta das 16h recebo RN D.X.R juntamente com su avó, pois a genitora estava para laqueadura desde as 11h, segundo relato da acompanhante (bem chateada porque o PAM não ofertou leite) RN estava desde as 11h sem se alimentar, segundo acompanhante que chamou a enfermeira 2x e não teve resposta rn apresentando irritabilidade verificamos dx 45mg/dl ofertamos fórmula , aceitou 20ml de 11 até 16h rn não se alimentou | K2: Arquivo | L2: 08/01/2026 | M2: PAM - Pronto Atendimento Materno | N2: Unidade de Internação Gineco Obstétrica | O2: 15 cgo2 | P2: Circunstância de Risco | Q2: Incidente
A3: HPP | B3: INC 1512 / 2026 | C3: Gerência de Cuidados Materno/Infantil / Unidade de Internação Ginecobstétrica - ALCOM | D3: Mylena Justino da Silva Brito | E3: Finalizada | F3: 0 | G3: Vitoria da Silva Couto | H3: 03/01/2026 | I3: 03/01/2026 | J3: Recebo paciente provinda de CC as 16:30 avalio paciente, não foi trocada antes de vir, fralda encharcada com sangramento ativo. 16:35 RECEBO PACIENTE EM LEITO, AVALIO PACIENTE, UTERO ACIMA DA CICATRIZ UMBILICAL COM SANGRAMENTO ATIVO FRALDA CHEIA DE SANGUE, FAÇO MASSAGEM FUNDO DO UTERO COM SAIDA DA DE COAGULOS EM GRANDE QUANTIDADE, ACIONO MEDICO DOUGLAS QUE VEM DE IMEDIATO REALIZA MASSAGEM BIMANUAL CURAGEM COM SAIDA DE GRANDE QUANTIDADE DE COAGULOS E SANGRAMENTO. UTERO CONTRAIDO ABAIXO DA CICATRIZ UMBILICAL, LOQUIOS FISIOLOGICOS, REALIZO TROCA DA FRALDA E PERMANEÇO AVALIANDO SANGRAMENTO. 17:35 ACOMPANHANTE ACIONA EQUIPE INFORMANDO QUE O SANGRAMENTO AUMENTOU, AVALIO PACIENTE FRALDA ENCHARCADA, UTERO CONTRAIDO NA CICATRIZ UMBILICAL. SANGRAMENTO AINDA ATIVO INFORMO MEDICO QUE SOLICITA HEMOGRAMA E PRESCREVE PROTOCOLO DE HPP. REALIZO A TROCA DA FRALDA 17:58 ABERTO PROTOCOLO DE HPP, ACIONO MEDICO DOUGLAS QUE VEM DE IMEDIATO, REALIZADO NOVA CURAGEM MASSAGEM BIMANUAL SAIDA DE COAGULOS EM GRANDE QUANTIDADE REALIZADO S.F 0,9% 500ML COM 4 AMPOLAS DE OXITOSINA + 1 ERGOTRAT PA 8X6 REALIZADO SORO RINGER LACTATO 18:10 REALIZADO 4 AMPOLAS DE TRANSAMIN NO S.F GLICOSADO. 18:25 REALIZADO NOVO ERGOTRAT 18:40 REALIZADO 4 COMP. DE MISO VIA RETAL. 19:00 LOQUIOS FISIOLOGICO | K3: Arquivo | L3: 07/01/2026 | M3: Unidade de Internação Gineco Obstétrica | N3: Unidade de Internação Gineco Obstétrica | O3: CGO2 LT 17 | P3: Evento Adverso Moderado | Q3: Incidente
A4: Encaminhamento de paciente ao setor de Radiologia sem comunicação prévia | B4: INC 1513 / 2026 | C4: Gerência Ambulatorial e de Apoio Diagnóstico / Gerência Ambulatorial e de Apoio Diagnóstico | D4: Mylena Justino da Silva Brito | E4: Convertida | F4: 0 | G4: Nadja Keilane Dantas Espinola | H4: 05/01/2026 | I4: 05/01/2026 | J4: Encaminhamento de um paciente ao setor de Radiologia sem a devida comunicação prévia à equipe assistencial e sem registro formal no fluxo institucional. Tal ocorrência caracteriza falha de processo e quebra de comunicação, configurando risco direto à Segurança do Paciente, conforme previsto: Portaria MS nº 529/2013 - Programa Nacional de Segurança do Paciente (PNSP), que estabelece a comunicação efetiva como uma prática obrigatória para prevenção de incidentes. RDC nº 36/2013 - ANVISA, que institui ações para segurança do paciente e determina que todos os serviços de saúde devem implementar processos padronizados, incluindo a comunicação clara e tempestiva entre setores. Protocolo Nacional de Comunicação Efetiva, que reforça a necessidade de aviso prévio, confirmação de entendimento e continuidade segura do cuidado. Normativas específicas da Radiologia, que exigem avaliação prévia do paciente, revisão de indicações, preparo adequado e garantia de condições técnicas para realização segura do exame. A ausência de comunicação prévia impede que a equipe de Radiologia verifique elementos críticos como: condição clínica e estabilidade do paciente; necessidade de monitoramento; contraindicações específicas (ex.: risco de queda, precauções, alergias, dispositivos implantáveis); preparo adequado para o exame; disponibilidade da sala e da equipe. | K4: Arquivo | L4: 05/01/2026 | M4: PS - Pronto Atendimento Adulto | N4: SADT - Unidade de Diagnóstico Por Imagem | O4: TOMOGRAFIA | Q4: Incidente
A5: Encaminhamento de paciente com tuberculose positiva ao setor de Radiologia sem comunicação prévia | B5: INC 1514 / 2026 | C5: Gerência Ambulatorial e de Apoio Diagnóstico / Gerência Ambulatorial e de Apoio Diagnóstico | D5: Mylena Justino da Silva Brito | E5: Finalizada | F5: 1 | G5: Nadja Keilane Dantas Espinola | H5: 05/01/2026 | I5: 05/01/2026 | J5: Foi encaminhado ao setor de Radiologia um paciente com diagnóstico confirmado de Tuberculose (TB positiva) sem comunicação prévia à equipe do setor, em desacordo com os fluxos assistenciais e protocolos institucionais de segurança. Tal ocorrência configura falha grave de comunicação e de processo assistencial, gerando risco à Segurança do Paciente, exposição ocupacional da equipe e potencial risco sanitário a outros pacientes, especialmente em ambientes compartilhados. A ausência de comunicação prévia impossibilitou a adoção imediata de medidas obrigatórias de precaução, tais como: implementação de precaução por aerossóis; uso adequado de Equipamentos de Proteção Individual (EPI); organização do fluxo seguro do paciente; preparo da sala e redução do risco de transmissão cruzada. Fundamentação legal e normativa A situação contraria dispositivos legais e normativos, entre eles: Portaria MS nº 529/2013 - Programa Nacional de Segurança do Paciente (PNSP); RDC nº 36/2013 - ANVISA, que estabelece ações para prevenção de incidentes e eventos adversos; RDC nº 222/2018 - ANVISA (biossegurança e riscos biológicos); RDC nº 330/2019 - ANVISA, que dispõe sobre Radioproteção e segurança em serviços de diagnóstico por imagem; Normas de Controle de Infecção Relacionada à Assistência à Saúde (IRAS); Protocolos assistenciais para manejo de pacientes com tuberculose, que exigem comunicação prévia e medidas de isolamento. Riscos identificados Exposição ocupacional da equipe de Radiologia; Risco de transmissão da tuberculose a outros pacientes e profissionais; Comprometimento das medidas de biossegurança; Não conformidade sanitária passível de notificação à Vigilância Sanitária. | K5: Arquivo | L5: 08/01/2026 | M5: PS - Pronto Atendimento Adulto | N5: SADT - Unidade de Diagnóstico Por Imagem | O5: TOMOGRAFIA | P5: Circunstância de Risco | Q5: Incidente
A6: APARENTE NÃO HOUVE COLETA DE EXAMES LABORATORIAIS SOLICITADOS | B6: INC 1515 / 2026 | C6: Diretoria Técnica / SCIH - Serviço de Controle de Infecção Hospitalar | D6: Mylena Justino da Silva Brito | E6: Finalizada | F6: 0 | G6: Tiago Soares Fonseca | H6: 05/01/2026 | I6: 05/01/2026 | J6: EM 03/01/26 SOLICITADOS OS EXAMES CULTURA DE FUNGO (SANGUE), SOROLOLGIA ANTI-HAV IGG E IGM, SOROLOGIA T CRUZI, SOROLOGIA HTLV, ANTI-HBC IGG PARA A PACIENTE C.M.S. ATÉ AS 09:06H DA PRESENTE DATA SEM REGISTRO NA PLATAFORMA LIS WEB SE A COLETA FOI OU NÃO REALIZADA. OUTROS EXAMES SOLICITADOS NA MESMA DATA JÁ COM CONFIRMAÇÃO DE COLETA REGISTRADA NA PLATAFORMA. ALÉM DISSO, FOI SOLICITADO O EXAME PROTEINAS TOTAIS E FRAÇÕES, PORÉM FOI LIBERADO APENAS O RESULTADO DE PROTEINAS TOTAIS. | K6: Arquivo | L6: 07/01/2026 | M6: Unidades de Análises Clínicas | N6: SCIH - Serviço de Controle de Infecção Hospitalar | O6: CLINICA CIRURGICA LEITO 29 | P6: Circunstância de Risco | Q6: Incidente
A7: NÃO HOUVE COLETA DE URINA PARA REALIZAÇÃO DE EXAME | B7: INC 1516 / 2026 | C7: Diretoria Técnica / SCIH - Serviço de Controle de Infecção Hospitalar | D7: Mylena Justino da Silva Brito | E7: Finalizada | F7: 0 | G7: Tiago Soares Fonseca | H7: 05/01/2026 | I7: 05/01/2026 | J7: SOLICITADO EXAME EAS EM 03/01/26. ENTRATANTO ATÉ AS 09:13H DA PRESENTE DATA, O EXAME APARECE COMO "FALTA MATERIAL" NO STATUS DA PLATAFORMA LIS WEB DO LABORATÓRIO DE ANÁLISES CLINICAS. A NÃO REALIZAÇÃO DE EXAMES SOLICITADOS PODE COMPROMETER A ASSISTÊNCIA AO PACIENTE. | K7: Arquivo | L7: 08/01/2026 | M7: Unidade de Internação Cirúrgica | N7: SCIH - Serviço de Controle de Infecção Hospitalar | O7: LEITO 29 | P7: Circunstância de Risco | Q7: Incidente
A8: Falta de registro em prontuário e conduta inadequada de colaborador médico | B8: INC 1517 / 2026 | C8: Gerência de Cuidados Cirúrgicos / Unidade de Internação Cirúrgica | D8: Mylena Justino da Silva Brito | E8: Finalizada | F8: 0 | G8: Debora De Oliveira Alvarenga | H8: 05/01/2026 | I8: 05/01/2026 | J8: Durante plantão assistencial, foram identificadas condutas médicas inadequadas, pelo cirurgião Geral A.M. com repercussão direta na assistência, no fluxo institucional, no dimensionamento da equipe e na segurança do paciente. Avaliação médica realizada por volta das 4h da manhã em paciente vítima de ferimento por arma branca; contudo, a equipe de enfermagem não foi informada da avaliação, e__ não houve registro de evolução médica nem prescrição em prontuário__. __Atraso na definição formal de conduta__, mantendo a equipe de enfermagem sem respaldo técnico para continuidade do cuidado. Comunicação de possível alta de forma verbal a pacientes, sem prescrição ou evolução formal. Recusa ou resistência a avaliações presenciais conforme demanda assistencial. Comunicação inadequada e postura desrespeitosa com a equipe de enfermagem, comprometendo o trabalho multiprofissional. Proferimento de falas indecorosas na sala de prescrição, gerando constrangimento à equipe e quebra do ambiente profissional.__Uso de cigarro eletrônico__ em área assistencial, em desacordo com normas institucionais. | K8: Arquivo | L8: 08/01/2026 | M8: Unidade de Internação Cirúrgica | N8: Unidade de Internação Cirúrgica | O8: LCIR19 | P8: Circunstância de Risco | Q8: Incidente
A9: Falha no registro do horário de recebimento de hemoconcentrado | B9: INC 1518 / 2026 | C9: Gerência de Cuidados Cirúrgicos / Unidade de Internação Cirúrgica | D9: Mylena Justino da Silva Brito | E9: Ignorada | F9: 0 | G9: Debora De Oliveira Alvarenga | H9: 05/01/2026 | I9: 05/01/2026 | J9: Durante verificação de registros assistenciais, foi identificada ausência do horário de recebimento da bolsa de hemoconcentrado. Esse dado é essencial para a rastreabilidade do hemocomponente, controle do tempo de liberação/infusão e segurança do paciente, conforme protocolos institucionais e normas vigentes. Reforça-se a necessidade de atenção ao preenchimento completo e fidedigno dos registros relacionados à hemoterapia. | K9: Arquivo | L9: 07/01/2026 | M9: Unidade de Internação Clínica Médica | N9: Comissões | O9: 15 | P9: Circunstância de Risco | Q9: Incidente
A10: Falha no registro do tipo de hemocomponente | B10: INC 1519 / 2026 | C10: Gerência de Cuidados Cirúrgicos / Unidade de Internação Cirúrgica | D10: Mylena Justino da Silva Brito | E10: Ignorada | F10: 0 | G10: Debora De Oliveira Alvarenga | H10: 05/01/2026 | I10: 05/01/2026 | J10: Durante a verificação dos registros assistenciais, foi identificada a ausência de registro do tipo de hemocomponente administrado. Essa informação é essencial para a rastreabilidade, segurança do paciente e conformidade com os protocolos institucionais e normas de hemoterapia. Reforça-se a obrigatoriedade do preenchimento completo e fidedigno dos registros relacionados à administração de hemocomponentes. | K10: Arquivo | L10: 07/01/2026 | M10: Unidade de Internação Ortopédica | N10: Comissões | O10: 10 | Q10: Incidente
A11: Tempo de transfusão inferior ao preconizado | B11: INC 1520 / 2026 | C11: Gerência de Cuidados Cirúrgicos / Unidade de Internação Cirúrgica | D11: Mylena Justino da Silva Brito | E11: Ignorada | F11: 0 | G11: Debora De Oliveira Alvarenga | H11: 05/01/2026 | I11: 05/01/2026 | J11: Durante a análise dos registros assistenciais, foi identificado tempo de transfusão inferior a 1 hora, em desacordo com os protocolos institucionais e diretrizes de hemoterapia. O cumprimento do tempo adequado de transfusão é fundamental para a segurança do paciente, monitoramento de reações transfusionais e rastreabilidade do processo. Reforça-se a necessidade de adesão aos protocolos e do registro correto das informações relacionadas ao procedimento. | K11: Arquivo | L11: 08/01/2026 | M11: Centro Cirúrgico | N11: Comissões | O11: SALA | Q11: Incidente
A12: Falha no Dimensionamento e Assistência ao Paciente | B12: INC 1521 / 2026 | C12: Gerência de Cuidados Cirúrgicos / Unidade de Internação Cirúrgica | D12: Mylena Justino da Silva Brito | E12: Finalizada | F12: 0 | G12: Debora De Oliveira Alvarenga | H12: 07/01/2026 | I12: 07/01/2026 | J12: Durante o plantão do dia 06/01/2026 sob os cuidados das Enfermeiras Sarah e Antônia, identificou-se que a paciente M.J.D.S leito1 cirúrgica Prontuário 184602, não foi devidamente dimensionada a nenhum técnico de enfermagem. Não houve registro do dimensionamento no livro de ocorrências, tampouco a finalização do referido livro ao término do plantão. Em decorrência dessas falhas, a paciente permaneceu todo o período sem assistência direta da equipe técnica, configurando risco à segurança do paciente e não conformidade com os protocolos assistenciais da instituição. | K12: Arquivo | L12: 07/01/2026 | M12: Unidade de Internação Cirúrgica | N12: Unidade de Internação Cirúrgica | O12: 1 | P12: Circunstância de Risco | Q12: Incidente
A13: Encaminhamento inadequado sem acompanhamento médico de paciente crítico para exame diagnóstico | B13: INC 1522 / 2026 | C13: Gerência Ambulatorial e de Apoio Diagnóstico / Gerência Ambulatorial e de Apoio Diagnóstico | D13: Mylena Justino da Silva Brito | E13: Finalizada | F13: 2 | G13: Nadja Keilane Dantas Espinola | H13: 08/01/2026 | I13: 08/01/2026 | J13: Paciente por volta das proveniente da Sala Vermelha, em estado clínico instável, agitado, sem condições clínicas de colaborar com a realização do exame, sem acompanhamento médico, foi encaminhado ao setor de Tomografia Computadorizada. Durante a permanência no setor, o paciente apresentou vômitos repetidos, mantendo-se agitado e sem estabilidade clínica, o que impossibilitou a realização do exame. Diante da condição apresentada, o exame foi cancelado, e o paciente necessitou retorno imediato ao setor de origem. Ressalta-se que o transporte e a permanência do paciente no setor diagnóstico ocorreram sem a presença de médico assistente, apesar do quadro de instabilidade. RISCOS IDENTIFICADOS AO PACIENTE Risco de broncoaspiração, em razão de vômitos associados à posição supina necessária para o exame de tomografia. Risco de parada cardiorrespiratória, devido ao estado clínico instável e ausência de monitorização contínua. Risco de agravamento do quadro clínico, pela retirada do paciente de ambiente crítico (Sala Vermelha). Risco de trauma físico, decorrente de agitação psicomotora durante tentativa de posicionamento no equipamento. Atraso na assistência adequada, com interrupção de cuidados intensivos necessários. Risco de queda e lesões, pela instabilidade e agitação. Risco infeccioso e ocupacional, pela exposição da equipe a vômitos e secreções em ambiente não preparado para manejo emergencial. IMPLICAÇÕES LEGAIS E NORMATIVAS 1. Segurança do Paciente RDC ANVISA nº 36/2013 Estabelece a obrigatoriedade de práticas assistenciais seguras e da avaliação de risco antes de procedimentos diagnósticos, especialmente em pacientes críticos. 2. Responsabilidade Médica Código de Ética Médica (CFM) É vedado ao médico expor o paciente a risco desnecessário, bem como ausentar-se da assistência a paciente grave sob seus cuidados. Pacientes instáveis devem ser acompanhados por médico durante transporte e exames. 3. Responsabilidade Institucional Encaminhamento inadequado pode caracterizar: Falha no processo assistencial Não conformidade com protocolos de paciente crítico Risco de responsabilização civil da instituição, em caso de dano ao paciente. 4. Boas Práticas em Radiologia Pacientes agitados, instáveis ou com risco clínico elevado não devem ser submetidos a exames de imagem eletivos ou diagnósticos sem estabilização prévia. A realização de exames em pacientes críticos exige: Avaliação médica prévia Condições clínicas adequadas Acompanhamento médico durante todo o procedimento | K13: Arquivo | L13: 08/01/2026 | M13: PS - Pronto Atendimento Adulto | N13: SADT - Unidade de Diagnóstico Por Imagem | O13: TOMOGRAFIA HGP | P13: Circunstância de Risco | Q13: Incidente
A14: LPP SACRAL e CALCÂNEA | B14: INC 1526 / 2026 | C14: Gerência de Cuidados Cirúrgicos / Unidade de Internação Cirúrgica | D14: Mylena Justino da Silva Brito | E14: Finalizada | F14: 0 | G14: Ana Carolina de Oliveira Souza | H14: 08/01/2026 | I14: 08/01/2026 | J14: Lesão por pressão em região sacral e em calcâneo esquerdo, apresentando tecido desvitalizado e risco de infecção associado à pressão prolongada e imobilidade, classificada como Não Estadiável. Realizada avaliação da ferida, limpeza conforme protocolo institucional e curativo com placa de hidrocolóide. Intensificado reposicionamento, ajustada superfície de suporte e orientada equipe quanto ao alívio de pressão. Registro fotográfico realizado. Equipe médica, Equipe de Enfermagem e Comissão de Feridas comunicadas. Segue sem sinais sistêmicos de infecção no momento. Paciente não tolera procedimentos. Está em paliatividade exclusiva. Mantida vigilância diária da evolução da ferida. No prontuário eletrônico há registro em evolução de enfermagem, de início das lesões no mês de novembro (28/11/25), e evolução para grau não estadiável em dezembro (11/12/25). Notifico para registro do caso. | K14: Arquivo | L14: 08/01/2026 | M14: UTI - Unidade de Terapia Intensiva | N14: Comissões | O14: 3 | P14: Evento Adverso Moderado | Q14: Incidente
A15: Medicação suspensa e equipe seguiu com administração | B15: INC 1527 / 2026 | C15: Gerência de Cuidados Materno/Infantil / Unidade de Internação Ginecobstétrica - ALCOM | D15: Mylena Justino da Silva Brito | E15: Finalizada | F15: 1 | G15: Ana Carolina da Costa Frazao Cerqueira | H15: 08/01/2026 | I15: 08/01/2026 | J15: no plantão do dia 06 diurno, o médico suspendeu a medicação "ceftriaxona" da paciente R.S.F.B (333256) para iniciar amoxicilina+ clavulanato, devido a bacteria ser resistente ao ceftriaxona, paciente de isolamento devido tratamento de ITU a enfermeira não cumpriu a meta 2 e nem a meta 3 não identificou na passagem de plantão...a medicação que tinha sido suspensa, continuaram fazendo assumo plantão no dia 07 com as 2 medicaçoes checadas, confirmaram que foram usadas as 2 medicações tanto ceftriaxona como amoxicilina+clavulanato enfermeira do plantão anterior diurno não falou, equipe noturna continuou adm normalmente | K15: Arquivo | L15: 08/01/2026 | M15: Unidade de Internação Gineco Obstétrica | N15: Unidade de Internação Gineco Obstétrica | O15: ISOLAMENTO 2 | P15: Evento sem Dano | Q15: Incidente
A16: Não conformidades nas práticas de Segurança do Paciente - Soro sem identificação | B16: INC 1530 / 2026 | C16: Gerência de Cuidados Cirúrgicos / Unidade de Internação Cirúrgica | D16: Mylena Justino da Silva Brito | E16: Finalizada | F16: 2 | G16: Maria Karoline Miranda Oliveira | H16: 09/01/2026 | I16: 09/01/2026 | J16: Prezados, Venho por meio desta notificar que, na data de hoje as 14h, foi encaminhado ao nosso setor o paciente proveniente do Centro Cirúrgico com soro/medicação em uso sem a devida identificação (nome do paciente, medicamento, concentração e horário). Ressalto que a identificação correta das medicações é uma medida essencial de segurança do paciente, conforme protocolos institucionais e boas práticas assistenciais, sendo indispensável para a continuidade segura do cuidado. Solicitamos, por gentileza, atenção ao cumprimento desse procedimento, a fim de evitar riscos e garantir a qualidade da assistência prestada. | K16: Arquivo | L16: 26/01/2026 | M16: Centro Cirúrgico | N16: Unidade de Internação Cirúrgica | O16: 12 | P16: Circunstância de Risco | Q16: Incidente
A17: CURATIVO NÃO IDENTIFICADO | B17: INC 1531 / 2026 | C17: Gerência de Cuidados Cirúrgicos / Unidade de Internação Cirúrgica | D17: Mylena Justino da Silva Brito | E17: Finalizada | F17: 1 | G17: Ana Carolina de Oliveira Souza | H17: 12/01/2026 | I17: 12/01/2026 | J17: Durante avaliação assistencial, identificado curativo sem identificação, sem data, horário e assinatura do profissional responsável. Situação configura não conformidade assistencial, com potencial impacto na continuidade e segurança do cuidado. Notifico para registro e tratativa. | K17: Arquivo | L17: 27/01/2026 | M17: UTI - Unidade de Terapia Intensiva | N17: Comissões | O17: 1 | P17: Circunstância de Risco | Q17: Incidente
A18: Curativos não identificados | B18: INC 1532 / 2026 | C18: Gerência de Cuidados Cirúrgicos / Unidade de Internação Cirúrgica | D18: Mylena Justino da Silva Brito | E18: Finalizada | F18: 2 | G18: Ana Carolina de Oliveira Souza | H18: 12/01/2026 | I18: 12/01/2026 | J18: Durante avaliação assistencial, identificado 2 curativos sem identificação, sem data, horário e assinatura do profissional responsável. Situação configura não conformidade assistencial, com potencial impacto na continuidade e segurança do cuidado. Notifico para registro e tratativa. | K18: Arquivo | L18: 27/01/2026 | M18: UTI - Unidade de Terapia Intensiva | N18: Comissões | O18: 2 | P18: Circunstância de Risco | Q18: Incidente
A19: CURATIVOS NÃO IDENTIFICADOS | B19: INC 1533 / 2026 | C19: Gerência de Cuidados Cirúrgicos / Unidade de Internação Cirúrgica | D19: Mylena Justino da Silva Brito | E19: Finalizada | F19: 2 | G19: Ana Carolina de Oliveira Souza | H19: 12/01/2026 | I19: 12/01/2026 | J19: Durante avaliação assistencial, identificados 2 curativos sem identificação, sem data, horário e assinatura do profissional responsável. Situação configura não conformidade assistencial, com potencial impacto na continuidade e segurança do cuidado. Notifico para registro e tratativa. | K19: Arquivo | L19: 27/01/2026 | M19: UTI - Unidade de Terapia Intensiva | N19: Comissões | O19: 8 | P19: Circunstância de Risco | Q19: Incidente
A20: Más Condições de higiene e desorganização no leito | B20: INC 1534 / 2026 | C20: Diretoria Geral / Núcleo de Segurança do Paciente | D20: Mylena Justino da Silva Brito | E20: Finalizada | F20: 1 | G20: Talita Andrade Calado da Silva | H20: 12/01/2026 | I20: 12/01/2026 | J20: Durante ronda do núcleo de segurança do paciente, foi identificada más condições de higiene no leito, restos alimentares, roupas sujas e ambiente desorganizado. Segue foto em anexo para melhoria do processo. | K20: Arquivo | L20: 27/01/2026 | M20: PSICO - Unidade de Atenção à Saúde Mental | N20: NSP - Núcleo de Segurança do Paciente | O20: 05 | P20: Circunstância de Risco | Q20: Incidente
A21: Não conformidades nas práticas de Segurança do paciente - Leitos sem identificação beira leito | B21: INC 1535 / 2026 | C21: Diretoria Geral / Núcleo de Segurança do Paciente | D21: Mylena Justino da Silva Brito | E21: Finalizada | F21: 1 | G21: Talita Andrade Calado da Silva | H21: 12/01/2026 | I21: 12/01/2026 | J21: Durante ronda do núcleo de segurança do paciente, foi identificado leitos no ambulatório sem identificado beira leito. segue foto em anexo para ciência. | K21: Arquivo | L21: 27/01/2026 | M21: Unidade Ambulatorial | N21: NSP - Núcleo de Segurança do Paciente | O21: 01 e 02 | P21: Circunstância de Risco | Q21: Incidente
A22: NAO COLETADA URINA PARA REALIZAÇÃO DE EXAME | B22: INC 1536 / 2026 | C22: Diretoria Técnica / SCIH - Serviço de Controle de Infecção Hospitalar | D22: Mylena Justino da Silva Brito | E22: Finalizada | F22: 0 | G22: Tiago Soares Fonseca | H22: 13/01/2026 | I22: 13/01/2026 | J22: EM 12/01/26 SOLICITADO EXAME EAS, POREM, SEGUNDO PLATAFORMA LIS WEB NÃO FOI COLETADA AMOSTRA PARA EXAME. | K22: Arquivo | L22: 27/01/2026 | M22: PS - Pronto Atendimento Adulto | N22: SCIH - Serviço de Controle de Infecção Hospitalar | O22: UDC | P22: Circunstância de Risco | Q22: Incidente
A23: NÃO COLETADA AMOSTRA DE URINA PARA REALIZAÇÃO DE EXAME | B23: INC 1537 / 2026 | C23: Diretoria Técnica / SCIH - Serviço de Controle de Infecção Hospitalar | D23: Mylena Justino da Silva Brito | E23: Finalizada | F23: 0 | G23: Tiago Soares Fonseca | H23: 13/01/2026 | I23: 13/01/2026 | J23: SOLICITADO EAS, PORÉM NÃO FOI COLETADA AMOSTRA. | K23: Arquivo | L23: 27/01/2026 | M23: PS - Pronto Atendimento Adulto | N23: SCIH - Serviço de Controle de Infecção Hospitalar | O23: UDC | P23: Circunstância de Risco | Q23: Incidente
... A30: Não conformidades nas práticas de segurança do paciente - Falha na identificação de Soro e de riscos assistenciais | B30: INC 1544 / 2026 | C30: Diretoria Geral / Núcleo de Segurança do Paciente | D30: Mylena Justino da Silva Brito | E30: Finalizada | F30: 2 | G30: Talita Andrade Calado da Silva | H30: 13/01/2026 | I30: 13/01/2026 | J30: Durante auditoria dos protocolos de segurança foi observado, soro com nome incompleto, quadro beira leito sem risco de queda. segue foto em anexo. | K30: Arquivo | L30: 27/01/2026 | M30: Unidade de Internação Ortopédica | N30: NSP - Núcleo de Segurança do Paciente | O30: 12 | P30: Circunstância de Risco | Q30: Incidente
A31: TRANSFUSÃO DE HC EM MENOS DE 1H | B31: INC 1545 / 2026 | C31: Gerência de Cuidados Cirúrgicos / Unidade de Internação Cirúrgica | D31: Mylena Justino da Silva Brito | E31: Ignorada | F31: 0 | G31: Debora De Oliveira Alvarenga | H31: 13/01/2026 | I31: 13/01/2026 | J31: Foi identificado que a transfusão de hemocomponente foi realizada em tempo inferior a 1 (uma) hora, em desacordo com o protocolo institucional vigente, que estabelece tempo mínimo recomendado para infusão segura do produto. | K31: Arquivo | L31: 23/01/2026 | M31: Centro Cirúrgico | N31: Comissões | O31: CENTRO CIRURGICO | Q31: Incidente
A32: Ausência de registro do horário de chegada do Concentrado de Hemácias | B32: INC 1546 / 2026 | C32: Gerência de Cuidados Cirúrgicos / Unidade de Internação Cirúrgica | D32: Mylena Justino da Silva Brito | E32: Ignorada | F32: 0 | G32: Debora De Oliveira Alvarenga | H32: 13/01/2026 | I32: 13/01/2026 | J32: Identificada a ausência de registro do horário de chegada da bolsa de Concentrado de Hemácias na ficha de acompanhamento transfusional, em desacordo com o protocolo transfusional vigente. Tal registro é obrigatório para rastreabilidade, controle do tempo de armazenamento/uso e segurança do paciente. | K32: Arquivo | L32: 27/01/2026 | M32: UTI - Unidade de Terapia Intensiva | N32: Comissões | O32: 06 | Q32: Incidente
A33: Paciente não recebe medicação por falta de prescrição médica | B33: INC 1547 / 2026 | C33: Gerência de Cuidados Cirúrgicos / Unidade de Internação Cirúrgica | D33: Mylena Justino da Silva Brito | E33: Finalizada | F33: 0 | G33: Debora De Oliveira Alvarenga | H33: 13/01/2026 | I33: 13/01/2026 | J33: Durante o plantão noturno do dia 09/01/26, foi identificado que paciente OCB permaneceu sem prescrição médica vigente. A técnica de enfermagem comunicou o fato ao enfermeiro responsável, contudo nenhuma providência foi adotada no momento da comunicação. A regularização da prescrição médica ocorreu apenas no dia seguinte, ocasionando atraso e não realização de medicações prescritas, caracterizando falha no fluxo assistencial e risco à segurança do paciente. | K33: Arquivo | L33: 22/01/2026 | M33: Unidade de Internação Cirúrgica | N33: Unidade de Internação Cirúrgica | O33: 04 | P33: Evento sem Dano | Q33: Incidente
A34: Prescrição Médica Não Realizada | B34: INC 1548 / 2026 | C34: Diretoria Técnica / NVEH - Núcleo de Vigilância Epidemiológica Hospitalar | D34: Mylena Justino da Silva Brito | E34: Finalizada | F34: 1 | G34: Evila Ellen Sa De Moraes Matias | H34: 13/01/2026 | I34: 13/01/2026 | J34: Comunicamos que, após análise do prontuário eletrônico e físico da paciente em tratamento para tuberculose, foi constatado que não houve prescrição/administração do esquema RIPE no dia 12/01/2026. Paciente iniciou tratamento em 06/01/2026-D1/60 ainda no pronto socorro e foi transferida para UTI onde deu continuidade. Entretanto, no dia 12/01/2026 que seria D7/60, a Farmácia informou ao médico infectologista por volta de 20:14 que a medicação havia sido registrada como prescrita para 20:00, em razão de não ter sido prescrita para o dia 12/01/2026. Diante da proximidade com o horário da próxima dose, o médico infectologista orientou pela não realização da medicação naquele momento. Contudo, após revisão detalhada dos registros, verificou-se que a paciente não recebeu a medicação em nenhum horário no dia 12/01/2026, caracterizando falha na administração do tratamento. O ocorrido está sendo formalmente notificado para ciência da equipe da UTI, registro institucional e adoção das medidas necessárias para prevenção de recorrências, considerando o impacto potencial na continuidade e eficácia do tratamento A medicação não foi prescrita e não foi observada pela equipe a falta da realização da administração da medicação diaria da paciente. . | K34: Arquivo | L34: 22/01/2026 | M34: UTI - Unidade de Terapia Intensiva | N34: NVEH - Núcleo de Vigilância Epidemiológica Hospitalar | O34: UTI | P34: Evento sem Dano | Q34: Incidente
A35: Flebite Química Associada ao Uso de Propofol em Paciente de UTI. | B35: INC 1549 / 2026 | C35: Diretoria Técnica / SCIH - Serviço de Controle de Infecção Hospitalar | D35: Mylena Justino da Silva Brito | E35: Finalizada | F35: 1 | G35: Tais Lima da Silva | H35: 14/01/2026 | I35: 14/01/2026 | J35: Paciente internado em leito de Unidade de Terapia Intensiva (UTI) evoluiu com quadro de flebite química, associada ao uso de Propofol por via intravenosa, medicamento que se encontrava em infusão contínua no momento da ocorrência. Esse processo inflamatório da parede venosa é decorrente da infusão de substâncias com potencial irritativo, sem evidências clínicas ou laboratoriais de infecção local ou sistêmica associada. O Propofol é amplamente descrito na literatura científica e reconhecido em normativas técnicas como um fármaco com potencial para desencadear flebite, especialmente quando administrado por acesso venoso periférico, em veias de pequeno calibre ou por períodos prolongados. Sua formulação lipídica, bem como suas características físico-químicas, como pH e osmolaridade, podem causar irritação endotelial, favorecendo o desenvolvimento de complicações vasculares. De acordo com as recomendações técnicas de terapia intravenosa, protocolos institucionais e diretrizes relacionadas à Segurança do Paciente, medicamentos com potencial irritativo exigem monitorização rigorosa do sítio de infusão, avaliação frequente do acesso venoso, troca oportuna de dispositivos e avaliação criteriosa da via de administração, com preferência por acesso venoso central quando indicado, a fim de prevenir eventos adversos. Diante do exposto, o quadro apresentado caracteriza-se como um Evento Adverso relacionado à terapia intravenosa, necessário monitoramento, análise de risco, rastreabilidade e implementação de medidas preventivas, conforme preconizado pelas políticas de segurança do paciente e qualidade assistencial. | K35: Arquivo | L35: 22/01/2026 | M35: UTI - Unidade de Terapia Intensiva | N35: SCIH - Serviço de Controle de Infecção Hospitalar | O35: 04 | P35: Evento Adverso Moderado | Q35: Incidente
A36: Falha na técnica cobertura de acesso venoso periférico | B36: INC 1550 / 2026 | C36: Gerência de Cuidados Cirúrgicos / Unidade de Internação Cirúrgica | D36: Mylena Justino da Silva Brito | E36: Finalizada | F36: 1 | G36: Debora De Oliveira Alvarenga | H36: 14/01/2026 | I36: 14/01/2026 | J36: Identificado uso inadequado de curativo transparente em acesso venoso periférico, com fixação incorreta, deixando o óstil exposto, em desacordo com os protocolos institucionais de segurança do paciente e prevenção de infecção. | K36: Arquivo | L36: 27/01/2026 | M36: Unidade de Internação Cirúrgica | N36: Unidade de Internação Cirúrgica | O36: CIR3 | P36: Circunstância de Risco | Q36: Incidente
A37: AVP FLEBITADO | B37: INC 1551 / 2026 | C37: Gerência de Cuidados Cirúrgicos / Unidade de Internação Cirúrgica | D37: Mylena Justino da Silva Brito | E37: Finalizada | F37: 1 | G37: Maria Karoline Miranda Oliveira | H37: 14/01/2026 | I37: 14/01/2026 | J37: Notifico a clínica cirúrgica devido paciente encontra-se com AVP flebitado. Solicito, cordialmente, maior observação da equipe técnica quanto aos AVPs. | K37: Arquivo | L37: 22/01/2026 | M37: Unidade de Internação Cirúrgica | N37: Unidade de Internação Cirúrgica | O37: leito 28 cg | P37: Evento Adverso Moderado | Q37: Incidente
A38: Risco à Segurança do Paciente - Tomografia em Politrauma | B38: INC 1552 / 2026 | C38: Gerência Ambulatorial e de Apoio Diagnóstico / Gerência Ambulatorial e de Apoio Diagnóstico | D38: Mylena Justino da Silva Brito | E38: Finalizada | F38: 2 | G38: Nadja Keilane Dantas Espinola | H38: 15/01/2026 | I38: 15/01/2026 | J38: Venho por meio desta notificar evento adverso com risco grave à segurança do paciente, identificado durante o fluxo de atendimento para realização de exame de Tomografia Computadorizada em paciente politraumatizado. Foi constatado que o paciente foi encaminhado ao setor de Tomografia em desacordo com os protocolos assistenciais, normas de segurança do paciente e legislações vigentes, apresentando as seguintes não conformidades: Encaminhamento sem contenção e imobilização adequada, incluindo ausência de colar cervical e prancha rígida; Ausência de acompanhamento médico do setor solicitante durante o deslocamento e permanência no setor de imagem; Posterior confirmação diagnóstica, conforme documento em anexo, de fraturas na coluna cervical, evidenciando a gravidade da condição clínica e o alto risco envolvido. Tal conduta configura grave falha assistencial, contrariando princípios fundamentais da Segurança do Paciente, do atendimento ao politrauma, bem como normas aplicáveis à Radiologia Diagnóstica, que determinam que pacientes instáveis ou com suspeita de lesões cervicais devem permanecer imobilizados e sob supervisão médica contínua durante todo o trajeto e realização do exame. Riscos e Situações Agravantes ao Paciente A ausência de contenção adequada e de acompanhamento médico expôs o paciente a riscos significativos, incluindo, mas não se limitando a: Agravamento das lesões cervicais existentes; Lesão medular secundária por movimentação inadequada; Tetraplegia ou paraplegia irreversível; Comprometimento respiratório e hemodinâmico; Risco iminente de óbito; Retardo em intervenções emergenciais em caso de intercorrência durante o exame. Ressalta-se que o setor de Radiologia não detém autonomia assistencial para compensar falhas no preparo clínico do paciente, sendo responsabilidade do setor solicitante garantir que o paciente esteja clinicamente estabilizado, devidamente imobilizado e acompanhado por médico, conforme preconizam as boas práticas e legislações vigentes. | K38: Arquivo | L38: 26/01/2026 | M38: PS - Pronto Atendimento Adulto | N38: SADT - Unidade de Diagnóstico Por Imagem | O38: TOMOGRAFIA NO HORARIO NOTURNO | P38: Circunstância de Risco | Q38: Incidente
A39: Encaminhamento Indevido ao Setor de Imagem | B39: INC 1553 / 2026 | C39: Gerência Ambulatorial e de Apoio Diagnóstico / Gerência Ambulatorial e de Apoio Diagnóstico | D39: Mylena Justino da Silva Brito | E39: Finalizada | F39: 1 | G39: Nadja Keilane Dantas Espinola | H39: 15/01/2026 | I39: 15/01/2026 | J39: Venho, por meio desta, notificar evento adverso com risco grave à segurança do paciente, identificado durante o fluxo de encaminhamento ao setor de diagnóstico por imagem. Com guia médica sem justificativa médica e amassada. Foi constatado que paciente em situação de vulnerabilidade social (moradora de rua), apresentando condições clínicas incompatíveis com estabilidade, incluindo alteração das funções vitais e suspeita de uso de substâncias psicoativas ilícitas, foi encaminhada ao setor de imagem sem qualquer acompanhamento assistencial, tais como equipe de enfermagem e/ou maqueiro, contrariando protocolos institucionais e normas de segurança. Tal situação caracteriza grave falha assistencial, uma vez que pacientes com rebaixamento do nível de consciência, possível intoxicação exógena e instabilidade clínica não devem ser deslocados desacompanhados, especialmente para setores diagnósticos que não possuem caráter assistencial direto, como é o caso da Radiologia. Riscos e Situações Agravantes ao Paciente A conduta observada expôs a paciente a riscos significativos, incluindo, mas não se limitando a: Queda da própria altura durante deslocamento ou permanência no setor; Aspiração de conteúdo gástrico em caso de vômitos; Parada cardiorrespiratória sem assistência imediata; Agravamento do quadro clínico por ausência de monitorização; Retardo no reconhecimento de intercorrências clínicas agudas; Violação dos princípios da dignidade, equidade e segurança do cuidado. Além dos riscos ao paciente, a situação também expôs a equipe do SADT a riscos ocupacionais, uma vez que não compete ao setor de imagem realizar contenção clínica, manejo comportamental ou assistência direta em pacientes instáveis ou sob efeito de substâncias psicoativas. Ressalta-se que o setor solicitante é integralmente responsável por garantir que o paciente esteja: Clinicamente avaliado e estável; Devidamente acompanhado por profissional habilitado; Sob condições seguras para deslocamento e realização do exame. | K39: Arquivo | L39: 27/01/2026 | M39: PS - Pronto Atendimento Adulto | N39: SADT - Unidade de Diagnóstico Por Imagem | O39: SETOR RAIO X DO HGP HORÁRIO NOTURNO | P39: Circunstância de Risco | Q39: Incidente
A40: Encaminhamento Indevido para Tomografia sem presença de médico | B40: INC 1554 / 2026 | C40: Gerência Ambulatorial e de Apoio Diagnóstico / Gerência Ambulatorial e de Apoio Diagnóstico | D40: Mylena Justino da Silva Brito | E40: Finalizada | F40: 2 | G40: Nadja Keilane Dantas Espinola | H40: 15/01/2026 | I40: 15/01/2026 | J40: Venho, por meio desta, notificar evento adverso com risco grave à segurança do paciente, identificado durante o fluxo de encaminhamento para realização de Tomografia Computadorizada. Sem acompanhamento médico também. Paciente apresentou no laudo fratura na região lombar. Foi constatado que paciente vítima de queda de aproximadamente 5 (cinco) metros de altura foi encaminhado ao setor de imagem sem a devida contenção e imobilização, em desacordo com os protocolos de atendimento ao trauma, normas de segurança do paciente e boas práticas assistenciais, apresentando as seguintes não conformidades: Ausência de colar cervical; Ausência de prancha rígida; Ausência de traçado/dispositivo adequado para transferência segura do paciente para a mesa do tomógrafo; Paciente referindo dor em região lombar após a queda, sinalizando possível lesão vertebral. Tal conduta configura grave falha assistencial, uma vez que quedas de grande altura são consideradas mecanismo de trauma de alta energia, com risco elevado de lesões na coluna cervical, torácica e lombar, exigindo imobilização completa e transporte seguro até completa exclusão de lesões instáveis. Riscos e Situações Agravantes ao Paciente A ausência de contenção adequada e de técnicas seguras de transferência expôs o paciente a riscos relevantes, incluindo, mas não se limitando a: Agravamento de possíveis fraturas vertebrais ocultas; Lesão medular secundária por movimentação inadequada; Paraplegia ou tetraplegia irreversível; Instabilidade hemodinâmica decorrente de dor intensa ou lesões associadas; Dor exacerbada e sofrimento desnecessário; Risco de queda durante a transferência para a mesa do equipamento; Retardo no manejo adequado e na tomada de condutas emergenciais. Ressalta-se que o setor de Radiologia não possui competência assistencial para correção de falhas no preparo do paciente, sendo de responsabilidade do setor solicitante assegurar que todo paciente vítima de trauma: Esteja adequadamente imobilizado; Seja transferido de forma segura, com dispositivos apropriados; Tenha condições clínicas mínimas para realização do exame diagnóstico. | K40: Arquivo | L40: 27/01/2026 | M40: PS - Pronto Atendimento Adulto | N40: SADT - Unidade de Diagnóstico Por Imagem | O40: 336891 | P40: Circunstância de Risco | Q40: Incidente
A41: FALHA NA COMUNICAÇÃO E ENCAMINHAMENTO DE PACIENTE AO CENTRO CIRURGICO | B41: INC 1555 / 2026 | C41: Gerência de Cuidados Cirúrgicos / Centro Cirúrgico | D41: Mylena Justino da Silva Brito | E41: Finalizada | F41: 0 | G41: Iara Victoria Pinheiro de Lima | H41: 15/01/2026 | I41: 09/01/2026 | J41: No dia 09/01/2026, por volta das 05h15, foi encaminhada ao Centro Cirúrgico uma paciente gestante G.M.S (prontuário: n°188305) para realização de cesariana sem comunicação prévia com a equipe do setor. A paciente foi enviada ao bloco cirúrgico sem passagem de caso pela enfermeira do Pronto Atendimento Materno (PAM), sem prontuário e sem solicitação médica de emergência, acompanhada pela técnica que não soube repassar as informações da paciente. O prontuário foi entregue apenas após a paciente já se encontrar anestesiada, comprometendo o acesso prévio às informações clínicas necessárias para uma assistência segura tanto para mãe quanto para o rn. A passagem de caso pela enfermeira do PAM ocorreu somente após questionamento da enfermeira do Centro Cirúrgico quanto à ausência de informações, quando o procedimento já havia sido finalizado. Notifico para melhoria do processo. | K41: Arquivo | L41: 27/01/2026 | M41: PAM - Pronto Atendimento Materno | N41: PAM - Pronto Atendimento Materno | O41: 00000 | P41: Circunstância de Risco | Q41: Incidente
A42: NÃO ADESÃO MÉDICA AO PROTOCOLO DE SEPSE | B42: INC 1556 / 2026 | C42: Diretoria Técnica / SCIH - Serviço de Controle de Infecção Hospitalar | D42: Mylena Justino da Silva Brito | E42: Finalizada | F42: 1 | G42: Suellen Andrade Sousa Coelho | H42: 15/01/2026 | I42: 15/01/2026 | J42: Durante visita de rotina à Clínica Cirúrgica, fui acionada pela enfermeira Flávia, responsável pelo plantão diurno, a qual informou sobre a abertura de Protocolo de Sepse previamente validado pelo médico cirurgião geral, Dr. Ageu. No entanto, constatou-se a ausência da solicitação dos exames laboratoriais previstos no pacote inicial de sepse, conforme estabelecido no protocolo institucional. A enf. Flávia havia discutido com o médico a importância do seguimento integral do protocolo, especialmente no que se refere à solicitação tempestiva dos exames laboratoriais. Apesar disso, houve recusa médica em proceder com as solicitações, sob a justificativa de existência de exames realizados no dia anterior, conduta que diverge das diretrizes do Protocolo Institucional de Sepse. Ainda assim, foi prescrita antibioticoterapia com Piperacilina associada a Tazobactam. Durante minha permanência no setor, o médico compareceu à unidade de internação e foi novamente questionado quanto à necessidade de continuidade do protocolo, incluindo o devido preenchimento e registro das etapas obrigatórias. O profissional manifestou-se de forma contrária, relatando que não "perderia tempo" com o preenchimento do formulário, afirmando que a paciente já se encontrava sob acompanhamento clínico. Foi reforçado que o cumprimento adequado do Protocolo Institucional de Sepse é fundamental para garantir a segurança do paciente, a rastreabilidade das condutas adotadas, o monitoramento da resposta terapêutica e a redução do risco de desfechos desfavoráveis, incluindo óbito por sepse. Mesmo após as orientações prestadas, o médico manteve a decisão de não dar seguimento ao protocolo. Diante disso solicitou-se, que o protocolo fosse formalmente encerrado pelo médico (Dr. Ageu), com a devida justificativa registrada no formulário de SEPSE; entretanto, o profissional informou que tal procedimento poderia ser realizado pela enfermeira do Serviço de Controle de Infecção Hospitalar (SCIH), encerrando a conversa e retirando-se do local. Diante do exposto, a situação foi devidamente notificada para ciência da Coordenação, Gerência Médica e Comissão de Sepse, com o objetivo de promover o alinhamento de condutas, reforçar institucionalmente a obrigatoriedade do cumprimento do Protocolo de Sepse e contribuir para a melhoria contínua do processo assistencial, com foco na segurança do paciente e na adesão às diretrizes vigentes. | K42: Arquivo | L42: 26/01/2026 | M42: Unidade de Internação Cirúrgica | N42: SCIH - Serviço de Controle de Infecção Hospitalar | O42: 04 | P42: Circunstância de Risco | Q42: Incidente
A43: Uso de Adorno em Área Crítica (Centro Cirúrgico). | B43: INC 1557 / 2026 | C43: Diretoria Técnica / SCIH - Serviço de Controle de Infecção Hospitalar | D43: Mylena Justino da Silva Brito | E43: Finalizada | F43: 1 | G43: Tais Lima da Silva | H43: 15/01/2026 | I43: 15/01/2026 | J43: Durante visita técnica ao setor do Centro Cirúrgico que são realizadas pelo Serviço de Controle de Infecção Hospitalar (SCIH), foi observado que o médico cirurgião Dr. Miqueis encontrava-se em uso de aliança, inclusive durante o período em que foi submetido a procedimento cirúrgico, mantendo o adorno durante todo o ato operatório. A conduta observada caracteriza não conformidade com os protocolos institucionais de prevenção e controle de infecções, os quais preconizam a política de adorno zero em áreas críticas. O uso de adornos compromete a efetividade da higienização das mãos, conforme evidenciado na literatura científica, favorecendo a permanência de microrganismos e aumentando o risco de Infecções Relacionadas à Assistência à Saúde (IRAS). Ressalta-se que a prática encontra-se em desacordo com as recomendações da Agência Nacional de Vigilância Sanitária (ANVISA), em especial a RDC nº 36/2013, que dispõe sobre ações para a segurança do paciente nos serviços de saúde, bem como com os princípios do Programa de Controle de Infecção Hospitalar (PCIH), que estabelece medidas para redução de riscos biológicos durante a assistência. | K43: Arquivo | L43: 23/01/2026 | M43: Centro Cirúrgico | N43: SCIH - Serviço de Controle de Infecção Hospitalar | O43: 000 | P43: Circunstância de Risco | Q43: Incidente
A44: PACIENTE DÁ ENTRADA NO CENTRO CIRURGICO COM ACESSO NÃO FUNCIONANTE | B44: INC 1558 / 2026 | C44: Gerência de Cuidados Cirúrgicos / Centro Cirúrgico | D44: Mylena Justino da Silva Brito | E44: Finalizada | F44: 0 | G44: Iara Victoria Pinheiro de Lima | H44: 16/01/2026 | I44: 13/01/2026 | J44: NO DIA 13/01/2026, ÀS 06H:00MIN, PACIENTE MENOR G.C.F. (PRONTUÁRIO N°334694) DEU ENTRADA NO CENTRO CIRÚRGICO PROVENIENTE DA PEDIATRIA, PARA REALIZAR PROCEDIMENTO CIRÚRGICO. AO TESTAR AVP, NOTOU-SE QUE ESTE NÃO ESTAVA PÉRVIO. GENITORA REFERE QUE MENOR SÓ REALIZOU MEDICAÇÃO NO PS, INFORMANDO QUE DURANTE INTERNAÇÃO NA PEDIATRIA O ACESSO NÃO FOI UTILIZADO E NEM TESTADO ANTES DE VIR PARA O BLOCO CIRÚRGICO. NOTIFICO PARA MELHORIA DO PROCESSO. | K44: Arquivo | L44: 26/01/2026 | M44: Unidade de Internação Pediátrica | N44: Centro Cirúrgico | O44: 00000 | P44: Circunstância de Risco | Q44: Incidente
... A46: Não Conformidade no Preenchimento de Bundles de Ventilação Mecânica. | B46: INC 1560 / 2026 | C46: Diretoria Técnica / SCIH - Serviço de Controle de Infecção Hospitalar | D46: Mylena Justino da Silva Brito | E46: Finalizada | F46: 1 | G46: Tais Lima da Silva | H46: 16/01/2026 | I46: 16/01/2026 | J46: Paciente internado em leito de (UCI), em uso de intubação orotraqueal. Verificou-se a ausência de abertura do Bundle de Manutenção pela equipe de Fisioterapia, documentos essenciais para o acompanhamento diário do dispositivo invasivo. Ressalta-se que os bundles consistem em um conjunto de boas práticas assistenciais baseadas em evidências, fundamentais para o monitoramento sistemático, a padronização dos cuidados e a prevenção de eventos adversos, especialmente infecções relacionadas à ventilação mecânica. A não abertura e o não preenchimento desses instrumentos impactam negativamente o controle diário, a rastreabilidade das condutas adotadas e a segurança do paciente. Diante do exposto, recomenda-se que a equipe de Fisioterapia se atente à abertura e ao correto preenchimento dos Bundles de Inserção e Manutenção, garantindo o registro adequado, a continuidade do cuidado e a adesão aos protocolos institucionais e às boas práticas de segurança do paciente. | K46: Arquivo | L46: 27/01/2026 | M46: UCI - Unidade de Cuidados Intensivos Neonatal | N46: SCIH - Serviço de Controle de Infecção Hospitalar | O46: 03 | P46: Circunstância de Risco | Q46: Incidente
A47: RETRABALHO DEVIDO ALGO INERENTE AO MVPEP | B47: INC 1561 / 2026 | C47: Diretoria Técnica / SCIH - Serviço de Controle de Infecção Hospitalar | D47: Mylena Justino da Silva Brito | E47: Ignorada | F47: 0 | G47: Tiago Soares Fonseca | H47: 17/01/2026 | I47: 17/01/2026 | J47: ACREDITO QUE NÃO SE TRATA EXATAMENTE DE UM INCIDENTE. SERIA MAIS INTERAÇÃO DE PROCESSO. MESMO ASSIM NOTIFICO PARA ANÁLISE. SOLICITADA PARA PACIENTE G.M.C. TC DE TORAX (PLANTAO DIA, PERIODO DA MANHA, DA DATA DE 17/01/26). TODAVIA TIVE QUE SUSPENDER A SOLICITAÇÃO ANTERIOR (DEVIDO TER FICADO SEM JUSTIFICATIVA) E SOLICITEI NOVA TC DE TORAX EM QUE CONSTAVA NO CAMPO OBSERVAÇÃO A JUSTIFICATIVA DE SOLICITAÇÃO DO EXAME DE IMAGEM. FOI INFORMADO PELA ENFERMAGEM QUE O SETOR DE SADT NÃO ACEITOU O PEDIDO "RASURADO" NAS PALAVRAS DA COLABORADORA DO SADT QUE RECEBEU A SOLICITAÇÃO (ANEXO COPIA DA SOLICITAÇÃO). TODAVIA SOLICITAÇÃO DE EXAME NÃO ESTAVA RASURADA, APENAS CONTINHA A SUSPENSÃO DA TC DE TORAX EM QUE NÃO COLOQUEI A JUSTIFICATIVA E CONTINHA A SOLICITAÇÃO DA TC DE TORAX COM A DEVIDA JUSTIFICATIVA. LIGUEI NO SETOR E CONVERSEI COM A COLABORADORA DO SADT POREM ELA INFORMOU QUE TINHA QUE SER REALIZADO OUTRO PEDIDO PORQUE A SOLICITAÇÃO ENVIADA ESTAVA "RASURADA". EXPLIQUEI A ELA QUE ISSO NÃO É RASURA, MAS SIM O CANCELAMENTO DO PEDIDO DA TC DE TORAX EM QUE HAVIA ESQUECIDO DE COLOCAR A JUSTIFICATIVA E QUE DAVA PARA VERIFICAR QUE AS DUAS SOLICITAÇÕES (A SUSPENSA E A OUTRA) ERAM DISTINTAS PORQUE UMA TINHA JUSTIFICATIVA E A OUTRA NÃO TINHA. ENTRETANTO A COLABORADORA SE MOSTROU IRREDUTIVEL E DISSE QUE CUMPRIA ORDENS E QUE TINHA QUE SER FEITO NOVA SOLICITAÇÃO. NA MINHA OPINIÃO, NÃO FAZ SENTIDO ESSE TIPO DE BUROCRACIA QUE SÓ CAUSA RETRABALHO TENDO EM VISTA QUE É NÍTIDO QUE OS DOIS PEDIDOS ERAM DISTINTOS. ACHO QUE PRECISA SER REVISITADA ESSA BARREIRA PARA VER SE HÁ UM SENTIDO NESSE TIPO DE SOLICITAÇÃO DE RETRABALHO PELO OUTRO. LEMBRANDO QUE É PRÓPRIO DO SISTEMA MVPEP O CANCELAMENTO DE UM EXAME EM QUE O MESMO APARECE RISCADO, SENDO POSSIVEL DISTINGUIR QUE AS DUAS SOLICITAÇÕES SÃO DIFERENTES (UMA NÃO CANCELOU A OUTRA DA MESMA FOLHA DE SOLICITAÇÃO DO EXAME). TODOS TEM MUITO TRABALHO A FAZER. ESSE TIPO DE RETRABALHO, APARENTEMENTE SEM SENTIDO, ADICIONA TEMPO A UMA ROTINA JÁ ACELERADA. GOSTARIA DE TER RESPOSTA EM RELAÇÃO A ESSA NOTIFICAÇÃO. | K47: Arquivo | L47: 26/01/2026 | M47: SADT - Unidade de Diagnóstico Por Imagem | N47: Unidade de Internação Clínica Médica | O47: SADT | Q47: Incidente
A48: Reação Transfusional CGO | B48: INC 1562 / 2026 | C48: Gerência de Cuidados Materno/Infantil / Unidade de Internação Ginecobstétrica - ALCOM | D48: Mylena Justino da Silva Brito | E48: Finalizada | F48: 5 | G48: Ana Carolina da Costa Frazao Cerqueira | H48: 17/01/2026 | I48: 17/01/2026 | J48: Paciente do leito 17 J. M.S (209174) Precisou de bolsa de CH e apresentou cefaleia, hipertensão e escotomas número da bolsa 21635706 ts da paciente o+ ts da bolsa o+ volume 250ml bolsa chegou 12:24 adm 13:02 ssvv pa 120x80 // fc 89 // t 36,2 13:12 - 10 min ssvv pa 120x80 // fc 79 // t 36,7 15:14 término ssvv 160x100 // fc 80 // t 36,5 - cefaleia, escotomas e hipertensão acionado médico do pam, iniciado hidralazina, feito 2 etapas de hidralazina adm losartana + nifedipina suspenso a 2ª bolsa ate estabilizar a PA entrego plantão com a paciente em controle pressórico | K48: Arquivo | L48: 22/01/2026 | M48: Unidade de Internação Gineco Obstétrica | N48: Unidade de Internação Gineco Obstétrica | O48: 17 | P48: Evento Adverso Moderado | Q48: Incidente
A49: ENCAMINHAMENTO DE PACIENTE GRAVE PARA TOMOGRAFIA SEM ACOMPANHAMENTO MÉDICO Notificação encaminhada para análise. | B49: INC 1563 / 2026 | C49: Gerência Ambulatorial e de Apoio Diagnóstico / Gerência Ambulatorial e de Apoio Diagnóstico | D49: Mylena Justino da Silva Brito | E49: Finalizada | F49: 1 | G49: Nadja Keilane Dantas Espinola | H49: 19/01/2026 | I49: 19/01/2026 | J49: Data do evento: 17/01/2026 Horário aproximado: 06h20 Setor: Tomografia Computadorizada - SADT Paciente: E M dos S Classificação clínica: Paciente grave - Sala Vermelha Descrição do Evento Por volta das 06h20 do dia 17/01/2026, o paciente E M dos S, classificado como grave (Sala Vermelha), deu entrada no setor de Tomografia Computadorizada para realização de exames de TC de crânio, face, coluna cervical, coluna dorsal e tórax. O paciente foi encaminhado sem acompanhamento médico, estando acompanhado apenas por técnico de enfermagem e maqueiros, apesar da gravidade do quadro clínico e da complexidade dos exames solicitados. A condução do paciente ao setor de imagem sem a presença de médico assistente configura não conformidade grave, considerando: A instabilidade clínica potencial do paciente grave oriundo da Sala Vermelha; O risco de intercorrências clínicas súbitas durante o deslocamento e a realização dos exames; A impossibilidade de intervenção médica imediata em caso de deterioração clínica; A exposição do paciente a risco evitável, contrariando os princípios da Segurança do Paciente. Fundamentação Legal e Normativa O evento contraria dispositivos normativos e princípios legais, tais como: RDC nº 330/2019 e RDC n° 611/2022 - ANVISA Determina que os serviços de radiologia devem garantir condições seguras para a realização dos exames, incluindo avaliação clínica adequada e suporte necessário ao paciente durante todo o processo. RDC nº 36/2013 - ANVISA (Segurança do Paciente) Estabelece a obrigatoriedade da adoção de práticas que minimizem riscos e eventos adversos relacionados à assistência à saúde. Código de Ética Médica (CFM) Prevê que pacientes graves devem permanecer sob assistência médica contínua, especialmente durante procedimentos diagnósticos que envolvam risco. Boas Práticas Assistenciais e Protocolos de Urgência e Emergência Pacientes críticos devem ser transportados e submetidos a exames diagnósticos com acompanhamento médico, garantindo resposta imediata a intercorrências. Riscos Associados ao Evento Parada cardiorrespiratória sem suporte médico imediato Rebaixamento do nível de consciência durante o exame Complicações respiratórias e hemodinâmicas Atraso na tomada de decisão clínica em situação de urgência Conclusão O encaminhamento de paciente grave, oriundo da Sala Vermelha, para realização de tomografia sem acompanhamento médico caracteriza falha assistencial grave, representando risco significativo à segurança do paciente e descumprimento das normas vigentes de radiologia e assistência em urgência e emergência. | K49: Arquivo | L49: 27/01/2026 | M49: PS - Pronto Atendimento Adulto | N49: SADT - Unidade de Diagnóstico Por Imagem | O49: TOMOGRAFIA HGP | P49: Circunstância de Risco | Q49: Incidente
A50: Lactente evoluiu a óbito após duas idas a UPA e internação com piora do sintomas gripais. | B50: INC 1564 / 2026 | C50: Gerência de Cuidados Materno/Infantil / UCI - Unidade de Cuidados Intensivos Neonatal | D50: Mylena Justino da Silva Brito | E50: Finalizada | F50: 0 | G50: Larissa Talita da Silva | H50: 19/01/2026 | I50: 19/01/2026 | J50: Lactente com histórico de inicio de sintomas gripais no dia 10/01/26 com 02 idas a UPA sem melhora do quadro. No dia 13/01/26 deu entrada no PS as 04 horas com desconforto respiratório, gemência e sintomas gripais, realizou exames e ficou em observação, a tarde por volta das 14 horas teve uma piora e foi encaminhado para sala vermelha em uso de cateter nasal e as 19:46 internou na UCI neo, apresentando gasping, taqupneico, taquicardia e sinais de insuficiência respiratória foi intubado e iniciado DVA. Foi solicitado transfusão, mais sem bolsas compatível disponivel e transferência para UTI pediátrica. No dia 14/01/26 foi realizado AVC para medicações e continou mantendo gravidade. No dia 15/01/26 apresentou bradicardia e evoluiu para PCR, foi realizado RCP sem reposta e evoluiu com óbitp as 02:5o horas. | K50: Arquivo | L50: 22/01/2026 | M50: UCI - Unidade de Cuidados Intensivos Neonatal | N50: UCI - Unidade de Cuidados Intensivos Neonatal | O50: 9 | P50: Evento Catastrófico | Q50: Incidente
A51: Prescrição de medicação com diluição inadequada/ risco flebite | B51: INC 1565 / 2026 | C51: Gerência de Cuidados Clínicos e Intensivos / Clínica Médica | D51: Mylena Justino da Silva Brito | E51: Finalizada | F51: 1 | G51: Marisol Luise Vilhene da Silva | H51: 21/01/2026 | I51: 21/01/2026 | J51: Foi identificado que a medicação ceftriaxona vem sendo prescrita utilizando 10 ml de ABD (água bidestilada) como diluente para administração intravenosa, em desacordo com a recomendação do fabricante e protocolo institucional, que orienta a diluição em diluente adequado (SF 0,9% ou conforme prescrição). A utilização de ABD como diluente para ceftriaxona por via endovenosa configura alto risco de flebite, dor local, irritação vascular e possíveis eventos adversos ao paciente, devido à osmolaridade inadequada da solução. | K51: Arquivo | L51: 27/01/2026 | M51: Unidade de Internação Clínica Médica | N51: Unidade de Internação Clínica Médica | O51: 29 | P51: Circunstância de Risco | Q51: Incidente
A52: Risco à segurança do paciente Setor: Ala Psicossocial | B52: INC 1566 / 2026 | C52: Gerência de Cuidados Clínicos e Intensivos / Clínica Médica | D52: Mylena Justino da Silva Brito | E52: Finalizada | F52: 1 | G52: Marisol Luise Vilhene da Silva | H52: 21/01/2026 | I52: 21/01/2026 | J52: Ao tentar adentrar na Ala Psicossocial, foi observada a ausência do agente de portaria no local e, em seguida, identificada a chave da porta de acesso à ala pendurada no portão, visível e acessível a qualquer pessoa. Ressalta-se que a Ala Psicossocial é um ambiente fechado, com pacientes que apresentam alto risco de fuga, sendo imprescindível o controle rigoroso de acesso. A situação configura alto risco de evasão/fuga de pacientes, além de comprometimento da segurança institucional, uma vez que qualquer pessoa poderia ter acesso à chave e abrir a porta sem autorização. | K52: Arquivo | L52: 27/01/2026 | M52: Controle de acesso | N52: Unidade de Internação Clínica Médica | O52: 000 | P52: Circunstância de Risco | Q52: Incidente
A53: Erro de cadastro / Identificação do paciente | B53: INC 1567 / 2026 | C53: Gerência de Cuidados Clínicos e Intensivos / Clínica Médica | D53: Mylena Justino da Silva Brito | E53: Finalizada | F53: 1 | G53: Marisol Luise Vilhene da Silva | H53: 21/01/2026 | I53: 21/01/2026 | J53: Paciente, ao dar entrada no hospital, foi cadastrada com o nome incorreto "Elane Cosmo Santos", sendo que o nome correto é "Elane Cosme Santos". Esse erro de grafia resultou na criação de um novo registro no sistema, fazendo com que a internação anterior da paciente não estivesse disponível para consulta e acompanhamento médico. Devido à indisponibilidade do histórico clínico correto, a paciente correu risco de não receber a medicação adequada (imunoglobulina), uma vez que a médica assistente encontrou apenas um registro de tratamento com pulsoterapia, sem acesso à informação de que a paciente já havia realizado pulsoterapia previamente, o que justificava a falha terapêutica e a necessidade do uso de imunoglobulina. | K53: Arquivo | L53: 27/01/2026 | M53: Recepção | N53: Unidade de Internação Clínica Médica | O53: 15 | P53: Circunstância de Risco | Q53: Incidente
A54: Falha de processo de Agendamento de exame | B54: INC 1568 / 2026 | C54: Gerência de Cuidados Clínicos e Intensivos / Clínica Médica | D54: Mylena Justino da Silva Brito | E54: Finalizada | F54: 1 | G54: Marisol Luise Vilhene da Silva | H54: 21/01/2026 | I54: 21/01/2026 | J54: Foi recebido na Clínica Médica o formulário de agendamento externo do paciente R.S.A., constando marcação de EDA (Endoscopia Digestiva Alta) para o dia 19/01/2026. O paciente realizou todo o preparo necessário para o exame, incluindo jejum e demais orientações pré-procedimento. Contudo, no momento em que o paciente seria encaminhado para a clínica de realização do exame, foi informado que o exame não constava como agendado no sistema. A situação gerou desgaste físico e emocional ao paciente, além de risco assistencial devido ao jejum prolongado desnecessário, atraso diagnóstico e possível impacto na conduta terapêutica. | K54: Arquivo | L54: 27/01/2026 | M54: NIR - Núcleo de Regulação Interno | N54: Unidade de Internação Clínica Médica | O54: 17 | P54: Circunstância de Risco | Q54: Incidente
A55: PROFISSIONAL SEM USAR EPI ADEQUADO | B55: INC 1569 / 2026 | C55: Diretoria Técnica / SCIH - Serviço de Controle de Infecção Hospitalar | D55: Mylena Justino da Silva Brito | E55: Finalizada | F55: 0 | G55: Suellen Andrade Sousa Coelho | H55: 21/01/2026 | I55: 21/01/2026 | J55: Durante visita de rotina ao Pronto Socorro, foi observado paciente em precaução para aerossóis por diagnóstico de tuberculose. No momento da observação, identificou-se técnica do laboratório realizando procedimento de coleta na referida paciente sem a utilização do Equipamento de Proteção Individual (EPI) adequado, especificamente máscara respiratória do tipo N95/PFF2, conforme preconizado pelos protocolos institucionais e normas de biossegurança. Diante da inconformidade identificada, notifico para fins de melhoria do processo, reforço das medidas de segurança ocupacional e prevenção da transmissão de infecções, visando à proteção dos profissionais de saúde e dos pacientes. | K55: Arquivo | L55: 26/01/2026 | M55: Unidade de Análises Clínicas | N55: SCIH - Serviço de Controle de Infecção Hospitalar | O55: ESTABILIZAÇÃO | P55: Circunstância de Risco | Q55: Incidente
A56: Falha de identificação de soro na dispensação | B56: INC 1570 / 2026 | C56: Gerência de Cuidados Clínicos e Intensivos / Clínica Médica | D56: Mylena Justino da Silva Brito | E56: Finalizada | F56: 1 | G56: Marisol Luise Vilhene da Silva | H56: 21/01/2026 | I56: 21/01/2026 | J56: Foi recebido na Clínica Médica um frasco de soro fisiológico sem identificação de rótulo, vindo na fita de dispensação junto com outras medicações. O frasco encontrava-se sem qualquer identificação contendo nome da solução, concentração, lote, validade e via de administração, impossibilitando a rastreabilidade e o uso seguro do produto. A ausência de identificação do rótulo configura alto risco de erro de medicação, podendo resultar em administração incorreta, troca de soluções, contaminação, eventos adversos ao paciente e falha na rastreabilidade. | K56: Arquivo | L56: 27/01/2026 | M56: Farmácia | N56: Unidade de Internação Clínica Médica | O56: 10 | P56: Circunstância de Risco | Q56: Incidente
A57: EQUIPO SEM IDENTIFICAÇÃO | B57: INC 1571 / 2026 | C57: Gerência de Cuidados Cirúrgicos / Unidade de Internação Cirúrgica | D57: Mylena Justino da Silva Brito | E57: Finalizada | F57: 1 | G57: Maria Karoline Miranda Oliveira | H57: 21/01/2026 | I57: 21/01/2026 | J57: Prezados, Notifico que, na data de hoje as 16:40, foi encaminhado ao setor paciente proveniente do Centro Cirúrgico sem a devida identificação de equipo. Ressalto que a identificação correta é essencial para garantir a segurança do paciente e a rastreabilidade do material, conforme protocolos institucionais vigentes. Solicito, por gentileza, a orientação da equipe quanto ao cumprimento desse procedimento, a fim de evitar recorrências. | K57: Arquivo | L57: 27/01/2026 | M57: Centro Cirúrgico | N57: Unidade de Internação Cirúrgica | O57: LEITO 16 | P57: Circunstância de Risco | Q57: Incidente
A58: PACIENTE SEM PULSEIRA DE ALERGIA. | B58: INC 1572 / 2026 | C58: Gerência de Cuidados Cirúrgicos / Unidade de Internação Cirúrgica | D58: Mylena Justino da Silva Brito | E58: Finalizada | F58: 2 | G58: Maria Karoline Miranda Oliveira | H58: 21/01/2026 | I58: 21/01/2026 | J58: Prezados, Notifico que no dia de hoje, às 16h40, foi encaminhado paciente proveniente do Centro Cirúrgico que refere alergia medicamentosa, porém sem a pulseira de identificação de alergia. Ressalto que o uso da pulseira é indispensável para a segurança do paciente e para a prevenção de eventos adversos, conforme os protocolos institucionais. Solicito a orientação e reforço junto à equipe quanto ao cumprimento desse procedimento, a fim de evitar recorrências. | K58: Arquivo | L58: 26/01/2026 | M58: Centro Cirúrgico | N58: Unidade de Internação Cirúrgica | O58: LEITO 16 | P58: Circunstância de Risco | Q58: Incidente
A59: PACIENTE SEM PULSEIRA DE ALERGIA | B59: INC 1573 / 2026 | C59: Gerência de Cuidados Cirúrgicos / Unidade de Internação Cirúrgica | D59: Mylena Justino da Silva Brito | E59: Finalizada | F59: 0 | G59: Maria Karoline Miranda Oliveira | H59: 21/01/2026 | I59: 21/01/2026 | J59: Notifico o Centro Cirúrgico que, por encaminhar paciente que refere alergia medicamentosa, porém sem pulseira de identificação de alergia, em desacordo com os protocolos institucionais de segurança do paciente. | K59: Arquivo | L59: 26/01/2026 | M59: Centro Cirúrgico | N59: Unidade de Internação Cirúrgica | O59: leito 27 | P59: Circunstância de Risco | Q59: Incidente
... A82: Erro de dispensação, medicação errada. | B82: INC 1596 / 2026 | C82: Diretoria Técnica / Gerência de Enfermagem | D82: Mylena Justino da Silva Brito | E82: Finalizada | F82: 1 | G82: Brenda Viana de Oliveira | H82: 27/01/2026 | I82: 18/01/2026 | J82: DURANTANTE CONFERÊNCIA DE MEDICAÇÃO PARA ADMINISTRAÇÃO NO PACIENTE, FOI IDENTIFICADO O ERRO DE ROTULAGEM. O FRASCO SERIA PARA ADMINISTRAÇÃO DE SIMETICONA DO PACIENTE CONFORME A PRESCRIÇÃO E O MESMO NÃO TEM PRESCRITO CLONAZEPAM. NO FRASCO CONTIA SIMETICONA PORÉM O RÓTULO EXTERNO APRESENTAVA A IDENTIFICAÇÃO DE OUTRO MEDICAMENTO (CLONAZEPAM). TRATA-SE DE DESVIO DE QUALIDADE, COM POTENCIAL RISCO À SEGURANÇA DO PACIENTE. O PRODUTO FOI IMEDIATAMENTO SEGREGADO, NÃO SENDO ADMINISTRADO AO PACIENTE. | K82: Arquivo | L82: 04/02/2026 | M82: Farmácia | N82: Gerência de Cuidado Materno Infantil | O82: 0000 | P82: Circunstância de Risco | Q82: Incidente
A83: Falta de informações e prontuario. | B83: INC 1597 / 2026 | C83: Gerência de Cuidados Cirúrgicos / Centro Cirúrgico | D83: Mylena Justino da Silva Brito | E83: Ignorada | F83: 0 | G83: Fernanda Khetlyn da Silva Sousa | H83: 27/01/2026 | I83: 18/01/2026 | J83: Tec de Enf. do CC Fernanda Laysa, recebe paciente D. P. O. mas a tec que acompanhava a paciente não sabia do caso e não trouxe nenhum prontuário da mesma. Paciente precaução de contato e tec também não soube dizer o motivo. | K83: Arquivo | L83: 04/02/2026 | M83: Unidade de Internação Gineco Obstétrica | N83: Unidade de Internação Gineco Obstétrica | O83: 00000 | Q83: Incidente
A84: Soro sem identificação | B84: INC 1598 / 2026 | C84: Gerência de Cuidados Cirúrgicos / Unidade de Internação Cirúrgica | D84: Mylena Justino da Silva Brito | E84: Finalizada | F84: 1 | G84: Maria Karoline Miranda Oliveira | H84: 27/01/2026 | I84: 27/01/2026 | J84: Paciente encaminhado sem a devida identificação da medicação, em desacordo com os protocolos institucionais de segurança do paciente. Tal ocorrência representa risco assistencial, podendo comprometer a rastreabilidade, a administração segura de medicamentos e a qualidade do cuidado prestado. Solicita-se orientação e reforço junto à equipe quanto à obrigatoriedade da identificação correta de todas as medicações antes do encaminhamento do paciente, a fim de prevenir recorrências. | K84: Arquivo | L84: 27/01/2026 | M84: Centro Cirúrgico | N84: Unidade de Internação Ortopédica | O84: LEITO 02 ORTOPEDIA | P84: Circunstância de Risco | Q84: Incidente
A85: HIGIENIZAÇÃO DAS MÃOS PREJUDICADA | B85: INC 1599 / 2026 | C85: Diretoria Técnica / SCIH - Serviço de Controle de Infecção Hospitalar | D85: Mylena Justino da Silva Brito | E85: Finalizada | F85: 1 | G85: Suellen Andrade Sousa Coelho | H85: 27/01/2026 | I85: 27/01/2026 | J85: Durante visita de rotina à Unidade de Decisão Clínica (UDC), foi observado o posicionamento inadequada de lixeiras em frente à pia destinada à higienização das mãos. Tal situação dificulta a correta execução da prática de higienização das mãos pelos profissionais, configurando inconformidade com as boas práticas assistenciais e contribuindo para o aumento do risco de infecção relacionada à assistência à saúde. A situação foi registrada para fins de correção e melhoria do processo. | K85: Arquivo | L85: 27/01/2026 | M85: PS - Pronto Atendimento Adulto | N85: SCIH - Serviço de Controle de Infecção Hospitalar | O85: 000 | P85: Circunstância de Risco | Q85: Incidente
A86: IDENTIFICAÇÃO DE MEDICAÇÃO COM O NOME ERRADO DO PACIENTE | B86: INC 1600 / 2026 | C86: Gerência de Cuidados Cirúrgicos / Unidade de Internação Cirúrgica | D86: Mylena Justino da Silva Brito | E86: Finalizada | F86: 1 | G86: Maria Karoline Miranda Oliveira | H86: 27/01/2026 | I86: 27/01/2026 | J86: Notifico o Centro Cirúrgico pela identificação de medicação rotulada com o nome incorreto do paciente, em desacordo com os protocolos institucionais de segurança do paciente. Tal ocorrência representa risco assistencial grave, podendo comprometer a administração segura de medicamentos, a rastreabilidade e a qualidade do cuidado prestado ao paciente. Solicita-se orientação e reforço junto à equipe quanto à obrigatoriedade da conferência correta da identificação do paciente em todas as medicações, antes do preparo, rotulagem e encaminhamento, a fim de prevenir recorrências. | K86: Arquivo | L86: 27/01/2026 | M86: Centro Cirúrgico | N86: Unidade de Internação Ortopédica | O86: LEITO 14 ORTOPEDIA | P86: Circunstância de Risco | Q86: Incidente
A87: RESIDUO INFECTANTE JUNTO COM COMUM | B87: INC 1601 / 2026 | C87: Diretoria Técnica / SCIH - Serviço de Controle de Infecção Hospitalar | D87: Mylena Justino da Silva Brito | E87: Convertida | F87: 0 | G87: Suellen Andrade Sousa Coelho | H87: 27/01/2026 | I87: 27/01/2026 | J87: Durante visita de rotina à Unidade de Curta Permanência (UCP), foi identificada lixeira destinada a resíduos infectantes sem tampa, contendo resíduos comuns misturados aos resíduos infectantes. Tal situação caracteriza inconformidade no processo de segregação de resíduos, em desacordo com as normas de biossegurança e gerenciamento de resíduos de serviços de saúde, representando risco potencial à segurança dos profissionais, pacientes e ao meio ambiente. A não conformidade foi registrada para fins de correção imediata e melhoria do processo. | K87: Arquivo | L87: 27/01/2026 | M87: PS - Pronto Atendimento Adulto | N87: SCIH - Serviço de Controle de Infecção Hospitalar | O87: 000 | Q87: Incidente
A88: CADEIRA DE COLETA NÃO CONFORME | B88: INC 1602 / 2026 | C88: Diretoria Técnica / SCIH - Serviço de Controle de Infecção Hospitalar | D88: Mylena Justino da Silva Brito | E88: Finalizada | F88: 1 | G88: Suellen Andrade Sousa Coelho | H88: 27/01/2026 | I88: 27/01/2026 | J88: Durante visita de rotina à enfermaria de pediatria do Pronto Socorro, foi identificada cadeira utilizada para coleta de exames apresentando parte do apoio de braço recoberta com esparadrapo. Tal condição configura inconformidade, uma vez que o material impede a adequada limpeza e desinfecção da superfície, contrariando as normas de biossegurança e de controle de infecção. A situação representa risco potencial à segurança do paciente e dos profissionais, favorecendo a contaminação cruzada. A inconformidade foi registrada para correção e adequação do mobiliário conforme os padrões institucionais. | K88: Arquivo | L88: 27/01/2026 | M88: PS - Pronto Atendimento Adulto | N88: SCIH - Serviço de Controle de Infecção Hospitalar | O88: 000 | P88: Circunstância de Risco | Q88: Incidente
A89: Lata de leite sem identificação | B89: INC 1603 / 2026 | C89: Gerência de Cuidados Materno/Infantil / Unidade de Internação Ginecobstétrica - ALCOM | D89: Mylena Justino da Silva Brito | E89: Finalizada | F89: 3 | G89: Ana Carolina da Costa Frazao Cerqueira | H89: 27/01/2026 | I89: 19/01/2026 | J89: Recebo plantão diurno 19/01 com lata de leite sem identificação toda lata ao ser aberta deve ser identificada com data e hora | K89: Arquivo | L89: 27/01/2026 | M89: Unidade de Internação Gineco Obstétrica | N89: Unidade de Internação Gineco Obstétrica | O89: 00000 | P89: Circunstância de Risco | Q89: Incidente
A90: Divergência diagnóstica, solicitação inadequada de exame e erro em notificação compulsória - Leishmaniose | B90: INC 1604 / 2026 | C90: Diretoria Técnica / NVEH - Núcleo de Vigilância Epidemiológica Hospitalar | D90: Mylena Justino da Silva Brito | E90: Finalizada | F90: 4 | G90: Evila Ellen Sa De Moraes Matias | H90: 27/01/2026 | I90: 19/01/2026 | J90: Notifico formalmente o Pronto Socorro e Profissional medica notificada: Dra. N.V.F - CRM/PA 20933 por erro identificado no atendimento realizado em 19/01/2026, envolvendo a paciente: Paciente: M.J.N.G Data de nascimento: 14/10/1950 Prontuário: 178795 Conforme registro em prontuário, a paciente apresentou lesões pruriginosas em membros inferiores (MMII) e membro superior direito (MMSD), sendo solicitada investigação para Leishmaniose Visceral, com respectiva abertura de notificação compulsória para essa forma da doença. Após análise do caso, observou-se que as características clínicas descritas são compatíveis com Leishmaniose Tegumentar Americana (LTA), e não com Leishmaniose Visceral. Para esse quadro clínico, o exame recomendado é o raspado da lesão, e não os exames específicos para a forma visceral da doença. Adicionalmente, identificou-se que a ficha de notificação compulsória foi preenchida de forma incorreta, classificando o agravo como Leishmaniose Visceral, sendo este preenchimento realizado por auxiliar administrativo, profissional sem atribuição técnica e sem formação específica para avaliação clínica ou validação diagnóstica, o que contribuiu para a manutenção do erro. Tal situação pode acarretar: Inconsistência nos dados epidemiológicos; Prejuízo à vigilância epidemiológica municipal; Risco de atraso ou inadequação na condução diagnóstica e terapêutica; Não conformidade com os fluxos e normativas do Ministério da Saúde. | K90: Arquivo | L90: 27/01/2026 | M90: PS - Pronto Atendimento Adulto | N90: NVEH - Núcleo de Vigilância Epidemiológica Hospitalar | O90: 0000 | P90: Evento sem Dano | Q90: Incidente
A91: Banqueta inadequada impossibilitando higienização | B91: INC 1605 / 2026 | C91: Diretoria Técnica / SCIH - Serviço de Controle de Infecção Hospitalar | D91: Mylena Justino da Silva Brito | E91: Finalizada | F91: 1 | G91: Suellen Andrade Sousa Coelho | H91: 27/01/2026 | I91: 27/01/2026 | J91: Durante visita à sala de sutura, foi identificada banqueta com o assento totalmente recoberto por esparadrapo e fita adesiva. Tal condição configura inconformidade, uma vez que o material utilizado impossibilita a adequada limpeza e desinfecção da superfície, contrariando as normas de biossegurança, controle de infecção e segurança do paciente. A situação representa risco potencial de contaminação cruzada entre pacientes e profissionais, especialmente em ambiente destinado à realização de procedimentos invasivos. A inconformidade foi registrada para providências imediatas. | K91: Arquivo | L91: 27/01/2026 | M91: PS - Pronto Atendimento Adulto | N91: SCIH - Serviço de Controle de Infecção Hospitalar | O91: 000 | P91: Circunstância de Risco | Q91: Incidente
A92: Não utilização de EPI em paciente sob precaução para aerossóis | B92: INC 1606 / 2026 | C92: Diretoria Técnica / NVEH - Núcleo de Vigilância Epidemiológica Hospitalar | D92: Mylena Justino da Silva Brito | E92: Finalizada | F92: 0 | G92: Evila Ellen Sa De Moraes Matias | H92: 27/01/2026 | I92: 21/01/2026 | J92: Em passagem realizada hoje pelo setor de Pronto-Socorro, foi identificada uma técnica de enfermagem prestando cuidados assistenciais a uma paciente em precaução para aerossóis, em tratamento para tuberculose, sem o uso do Equipamento de Proteção Individual (EPI) adequado, especificamente máscara N95/PFF2, conforme preconizado pelos protocolos de biossegurança e controle de infecção. Ressalta-se que o não uso do EPI indicado expõe o profissional, outros pacientes e a equipe assistencial ao risco de infecção, além de configurar não conformidade com as normas institucionais, diretrizes do Ministério da Saúde e recomendações do Serviço de controle de Infecção Hospitalar (SCIH). | K92: Arquivo | L92: 04/02/2026 | M92: PS - Pronto Atendimento Adulto | N92: NVEH - Núcleo de Vigilância Epidemiológica Hospitalar | O92: 00000 | P92: Circunstância de Risco | Q92: Incidente
A93: carteira do RN sem registros do exames realizados no setor | B93: INC 1607 / 2026 | C93: Gerência de Cuidados Materno/Infantil / Unidade de Internação Ginecobstétrica - ALCOM | D93: Mylena Justino da Silva Brito | E93: Ignorada | F93: 3 | G93: Ana Carolina da Costa Frazao Cerqueira | H93: 27/01/2026 | I93: 21/01/2026 | J93: boa tarde, mais uma vez, recebo plantão com RN de alta, sem registro do teste do coraçãozinho e peso de alta RN recebeu alta no dia 20, a técnica não realizou o peso de alta, não registrou obviamente ...não registrou o teste do coraçãozinho na alta da mãe no dia 21 percebemos a falha, durante a dupla checagem da alta. | K93: Arquivo | L93: 04/02/2026 | M93: Unidade de Internação Gineco Obstétrica | N93: Unidade de Internação Gineco Obstétrica | O93: 0000 | Q93: Incidente
A94: CADEIRA COM ASSENTO RASGADO | B94: INC 1608 / 2026 | C94: Diretoria Técnica / SCIH - Serviço de Controle de Infecção Hospitalar | D94: Mylena Justino da Silva Brito | E94: Finalizada | F94: 1 | G94: Suellen Andrade Sousa Coelho | H94: 27/01/2026 | I94: 27/01/2026 | J94: Durante visita de rotina na Clínica Cirúrgica, foi identificada cadeira com o assento totalmente rasgado, sem condições adequadas de uso. A situação configura inconformidade, uma vez que o dano no revestimento impossibilita a correta higienização e desinfecção da superfície, contrariando as normas de biossegurança, controle de infecção e segurança do paciente. Tal condição representa risco potencial de contaminação, além de comprometer a segurança de pacientes, acompanhantes e profissionais. A inconformidade foi registrada para ciência e adoção de medidas corretivas. | K94: Arquivo | L94: 27/01/2026 | M94: Unidade de Internação Cirúrgica | N94: SCIH - Serviço de Controle de Infecção Hospitalar | O94: 000 | P94: Circunstância de Risco | Q94: Incidente
A95: Não encaminhamento de amostras e ausência de documentação (Carga Viral e CD4) | B95: INC 1609 / 2026 | C95: Diretoria Técnica / NVEH - Núcleo de Vigilância Epidemiológica Hospitalar | D95: Mylena Justino da Silva Brito | E95: Finalizada | F95: 2 | G95: Evila Ellen Sa De Moraes Matias | H95: 27/01/2026 | I95: 21/01/2026 | J95: Em nome do setor responsável pelo acompanhamento epidemiológico, vimos por meio deste notificar uma não conformidade relacionada ao fluxo de exames laboratoriais do paciente R. L. D. S, Prontuário nº 336365. Conforme registros, as amostras para Carga Viral e CD4 foram cadastradas em 13/01/2026, entretanto: Não houve o encaminhamento das amostras ao CTA; Não foram recebidos os formulários de solicitação de Carga Viral e CD4, tampouco a ficha de notificação compulsória,(motivo pelo qual nao foi enviada as amostras) O setor solicitante não foi comunicado sobre a ausência da documentação necessária; A pendência não foi registrada em passagem de plantão, impossibilitando a identificação e correção em tempo oportuno. Em decorrência dessa falha de fluxo e comunicação, o CTA não liberou a medicação do paciente na data de hoje, gerando impacto direto na continuidade do tratamento e no cuidado assistencial. | K95: Arquivo | L95: 27/01/2026 | M95: Unidades de Análises Clínicas | N95: NVEH - Núcleo de Vigilância Epidemiológica Hospitalar | O95: 0000 | P95: Evento sem Dano | Q95: Incidente
A96: Impacto assistencial por falha no fluxo de exames (Carga Viral e CD4) | B96: INC 1610 / 2026 | C96: Diretoria Técnica / NVEH - Núcleo de Vigilância Epidemiológica Hospitalar | D96: Mylena Justino da Silva Brito | E96: Ignorada | F96: 2 | G96: Evila Ellen Sa De Moraes Matias | H96: 27/01/2026 | I96: 21/01/2026 | J96: Em nome do setor responsável pelo acompanhamento epidemiológico, vimos por meio deste comunicar e notificar ocorrência relacionada ao fluxo de solicitação e acompanhamento de exames do paciente R. L. D. S, Prontuário nº 336365. Conforme apurado, as amostras para Carga Viral e CD4 foram cadastradas em 13/01/2026, entretanto, não houve o encaminhamento das amostras ao CTA, pois não foram recebidos os formulários de solicitação dos exames carga viral e TCD4 nem a ficha de notificação compulsória. Destacamos ainda que: Não houve solicitação posterior do laboratório quanto à ausência da documentação e das amostras; A pendência não foi repassada em passagem de plantão, dificultando a identificação da falha e a adoção de medidas oportunas; Em decorrência dessa situação, o CTA não liberou a medicação do paciente na data de hoje, ocasionando impacto direto na continuidade do tratamento. | K96: Arquivo | L96: 27/01/2026 | M96: Unidade de Internação Clínica Médica | N96: NVEH - Núcleo de Vigilância Epidemiológica Hospitalar | O96: 0000 | Q96: Incidente
A97: PACIENTE COM SNG NÃO IDENTIFICADA | B97: INC 1611 / 2026 | C97: Gerência de Cuidados Cirúrgicos / Unidade de Internação Cirúrgica | D97: Mylena Justino da Silva Brito | E97: Finalizada | F97: 0 | G97: Almir Silva dos Santos | H97: 27/01/2026 | I97: 22/01/2026 | J97: NO DIA 21/01 RECEBO PLANTÃO DIURNO EM CLÍNICA ORTOPÉDICA DO PLANTÃO NOTURNO COM PACIENTE A.C, LEITO 13 ORTO, ATENDIMENTO Nº 215801, EM USO DE SNG QUE HAVIA SIDO REALIZADO NA CLÍNICA PELO ENFERMEIRO DO PLANTÃO NOTURNO, PORÉM A MESMA SE ENCONTRAVA SEM IDENTIFICAÇÃO. [fig:vfs:1425] | K97: Arquivo | L97: 27/01/2026 | M97: Unidade de Internação Ortopédica | N97: Unidade de Internação Ortopédica | O97: 13 | P97: Circunstância de Risco | Q97: Incidente
A98: Liberação de Dieta no PS por profissional não habilitado | B98: INC 1612 / 2026 | C98: Coordenação de Internação / Coordenação de Internação | D98: Mylena Justino da Silva Brito | E98: Finalizada | F98: 1 | G98: Janaina Bernardes Ayer | H98: 27/01/2026 | I98: 26/01/2026 | J98: Prezados, Venho por meio deste registrar Relato de Não Conformidade referente ao processo de liberação de dieta no Pronto Atendimento. Foi identificado que a liberação de dieta vem sendo realizada e assinada por fluxista, conforme documentação anexa, profissional que não possui formação técnica, competência legal ou atribuição institucional para avaliação das necessidades nutricionais e liberação de dieta ao paciente. Ressalta-se que o protocolo institucional vigente estabelece de forma clara que: A liberação de dieta deve ser realizada pela nutricionista, em horário comercial; Em períodos noturnos, finais de semana e feriados, excepcionalmente, a liberação pode ser realizada por enfermeiros, exclusivamente devido à ausência da nutricionista nesses horários, mediante utilização de impresso próprio. O descumprimento do referido protocolo configura não conformidade assistencial, além de colocar o paciente em risco, uma vez que a decisão está sendo tomada sem avaliação por profissional devidamente habilitado, em desacordo com as normas internas e os princípios de segurança do paciente. Solicita-se avaliação da situação, orientação às equipes envolvidas e adoção das medidas cabíveis para adequação imediata ao protocolo institucional, prevenindo reincidências. | K98: Arquivo | L98: 27/01/2026 | M98: PS - Pronto Atendimento Adulto | N98: NVEH - Núcleo de Vigilância Epidemiológica Hospitalar | O98: 0000 | P98: Circunstância de Risco | Q98: Incidente
A99: Falha de registro em prontuário | B99: INC 1613 / 2026 | C99: Diretoria Técnica / NVEH - Núcleo de Vigilância Epidemiológica Hospitalar | D99: Mylena Justino da Silva Brito | E99: Finalizada | F99: 2 | G99: Evila Ellen Sa De Moraes Matias | H99: 27/01/2026 | I99: 24/01/2026 | J99: Durante auditoria/análise de prontuário, foi identificada evolução médica e prescrição incompatíveis com o diagnóstico e com a condição clínica da paciente, caracterizando registro em paciente incorreto. Consta no prontuário evolução médica do profissional: ELSON VALADARES DE CASTRO FILHO - CRM - PA: 4991 de pós-operatório de cesariana, bem como prescrição correspondente a esse quadro, entretanto, o diagnóstico e o histórico clínico da paciente eram outros, não havendo registro de procedimento cirúrgico obstétrico (cesariana) relacionado a esta paciente. Após verificação, constatou-se que o profissional médico realizou evolução e prescrição em prontuário de paciente distinto daquele efetivamente assistido, configurando erro de identificação do paciente e falha grave no registro assistencial. Riscos identificados: Comprometimento da segurança do paciente Risco de administração de conduta e medicações inadequadas Inconsistência documental e legal no prontuário Impacto na continuidade e qualidade da assistência | K99: Arquivo | L99: 02/02/2026 | M99: Unidade de Internação Clínica Médica | N99: NVEH - Núcleo de Vigilância Epidemiológica Hospitalar | O99: 0000 | P99: Circunstância de Risco | Q99: Incidente
A100: Curativo incorreto de filme transparente | B100: INC 1614 / 2026 | C100: Diretoria Técnica / SCIH - Serviço de Controle de Infecção Hospitalar | D100: Mylena Justino da Silva Brito | E100: Finalizada | F100: 1 | G100: Suellen Andrade Sousa Coelho | H100: 27/01/2026 | I100: 27/01/2026 | J100: Durante visita de rotina, foi identificado paciente em uso de cateter venoso periférico (CVP) com curativo de filme transparente aplicado de forma inadequada. Tal inconformidade dificulta a adequada visualização do óstio de inserção, comprometendo a avaliação diária de sinais flogísticos e a detecção precoce de possíveis complicações, como infecção ou extravasamento. Notifico para melhoria do processo. | K100: Arquivo | L100: 27/01/2026 | M100: Unidade de Internação Cirúrgica | N100: SCIH - Serviço de Controle de Infecção Hospitalar | O100: 18 | P100: Circunstância de Risco | Q100: Incidente
A101: CATETER NASAL EXPOSTO | B101: INC 1615 / 2026 | C101: Diretoria Técnica / SCIH - Serviço de Controle de Infecção Hospitalar | D101: Mylena Justino da Silva Brito | E101: Finalizada | F101: 1 | G101: Suellen Andrade Sousa Coelho | H101: 27/01/2026 | I101: 27/01/2026 | J101: Durante visita de rotina, foi visualizado paciente em uso de cateter nasal de oxigênio sem o devido armazenamento e acondicionamento adequados quando fora de uso. Tal inconformidade compromete a segurança do paciente, uma vez que o dispositivo permanece exposto, favorecendo o contato com superfícies potencialmente contaminadas e aumentando o risco de colonização e infecção. Ressalta-se que o cateter nasal deve ser mantido protegido e armazenado conforme protocolo institucional, a fim de preservar sua integridade e reduzir riscos associados à assistência. A situação foi sinalizada à equipe assistencial, com orientações para correção imediata e reforço das boas práticas de controle de infecção, visando à melhoria do processo e à segurança do paciente. | K101: Arquivo | L101: 27/01/2026 | M101: Unidade de Internação Cirúrgica | N101: SCIH - Serviço de Controle de Infecção Hospitalar | O101: 21 | P101: Circunstância de Risco | Q101: Incidente
A102: CADEIRAS DE BANHO INAPROPRIADAS | B102: INC 1616 / 2026 | C102: Diretoria Técnica / SCIH - Serviço de Controle de Infecção Hospitalar | D102: Mylena Justino da Silva Brito | E102: Finalizada | F102: 2 | G102: Suellen Andrade Sousa Coelho | H102: 27/01/2026 | I102: 27/01/2026 | J102: Durante verificação de rotina, foram identificadas cadeiras de banho contendo esparadrapo em sua estrutura, configurando inconformidade aos padrões de biossegurança e controle de infecção. Tal condição dificulta a adequada higienização e desinfecção do equipamento, favorecendo a retenção de sujidade e microrganismos, o que representa risco potencial de contaminação e infecção para os pacientes, especialmente aqueles em condição de maior vulnerabilidade. Notifico para melhoria do processo. | K102: Arquivo | L102: 27/01/2026 | M102: Unidade de Internação Cirúrgica | N102: SCIH - Serviço de Controle de Infecção Hospitalar | O102: 000 | P102: Circunstância de Risco | Q102: Incidente
A103: PROFISSIONAIS SEM EPI | B103: INC 1617 / 2026 | C103: Diretoria Técnica / SCIH - Serviço de Controle de Infecção Hospitalar | D103: Mylena Justino da Silva Brito | E103: Finalizada | F103: 2 | G103: Suellen Andrade Sousa Coelho | H103: 27/01/2026 | I103: 27/01/2026 | J103: Durante visita de rotina na Clínica Cirúrgica, foram identificados profissionais realizando procedimento de curativo sem a utilização do capote (EPIs). Tal prática configura inconformidade grave, uma vez que aumenta o risco de contaminação do sítio do curativo, exposição ocupacional do profissional e possibilidade de infecção relacionada à assistência à saúde (IRAS). Notifico para melhoria do processo. | K103: Arquivo | L103: 27/01/2026 | M103: Unidade de Internação Cirúrgica | N103: SCIH - Serviço de Controle de Infecção Hospitalar | O103: 000 | P103: Circunstância de Risco | Q103: Incidente
A104: PROFISSIONAIS SEM EPI | B104: INC 1618 / 2026 | C104: Diretoria Técnica / SCIH - Serviço de Controle de Infecção Hospitalar | D104: Mylena Justino da Silva Brito | E104: Finalizada | F104: 2 | G104: Suellen Andrade Sousa Coelho | H104: 27/01/2026 | I104: 27/01/2026 | J104: DURANTE VISITA DE ROTINA NA CLÍNICA CIRÚRGICA, FORAM IDENTIFICADOS PROFISSIONAIS REALIZANDO PROCEDIMENTO DE CURATIVO SEM A UTILIZAÇÃO DO CAPOTE (EPIS). TAL PRÁTICA CONFIGURA INCONFORMIDADE GRAVE, UMA VEZ QUE AUMENTA O RISCO DE CONTAMINAÇÃO DO SÍTIO DO CURATIVO, EXPOSIÇÃO OCUPACIONAL DO PROFISSIONAL E POSSIBILIDADE DE INFECÇÃO RELACIONADA À ASSISTÊNCIA À SAÚDE (IRAS). NOTIFICO PARA MELHORIA DO PROCESSO. | K104: Arquivo | L104: 27/01/2026 | M104: Unidade de Internação Cirúrgica | N104: SCIH - Serviço de Controle de Infecção Hospitalar | O104: 000 | P104: Circunstância de Risco | Q104: Incidente
A105: PROFISSIONAL SEM USO DO EPI | B105: INC 1619 / 2026 | C105: Diretoria Técnica / SCIH - Serviço de Controle de Infecção Hospitalar | D105: Mylena Justino da Silva Brito | E105: Finalizada | F105: 1 | G105: Suellen Andrade Sousa Coelho | H105: 27/01/2026 | I105: 27/01/2026 | J105: Durante visita de rotina na Clínica Médica, foi visualizada técnica de enfermagem realizando procedimento de curativo em paciente sob precaução de contato, sem a devida paramentação, especificamente sem o uso de capote/EPI obrigatório. Tal inconformidade configura falha grave no cumprimento das medidas de precaução, aumentando o risco de contaminação cruzada, exposição ocupacional do profissional e disseminação de microrganismos multirresistentes no ambiente assistencial. Notifico para melhoria do processo. | K105: Arquivo | L105: 27/01/2026 | M105: Unidade de Internação Clínica Médica | N105: SCIH - Serviço de Controle de Infecção Hospitalar | O105: 000 | P105: Circunstância de Risco | Q105: Incidente
A106: FALHA NA TÉCNICA DE CURATIVO DE ACESSO VENOSO PERIFÉRICO | B106: INC 1620 / 2026 | C106: Diretoria Técnica / SCIH - Serviço de Controle de Infecção Hospitalar | D106: Mylena Justino da Silva Brito | E106: Finalizada | F106: 2 | G106: Suellen Andrade Sousa Coelho | H106: 27/01/2026 | I106: 27/01/2026 | J106: Durante visita de rotina, foi identificado paciente em uso de acesso venoso periférico com o óstio de inserção exposto, apresentando lesão cutânea no local da punção. O curativo encontrava-se realizado de forma inadequada, ocasionando ferimento na pele adjacente ao sítio de inserção. No momento da abordagem, a paciente referia dor local. Tal inconformidade compromete a integridade da pele, dificulta a avaliação do sítio de inserção e aumenta o risco de infecção relacionada ao acesso venoso periférico. Notifico para melhoria do processo. | K106: Arquivo | L106: 27/01/2026 | M106: Unidade de Internação Clínica Médica | N106: SCIH - Serviço de Controle de Infecção Hospitalar | O106: 03 | P106: Circunstância de Risco | Q106: Incidente
A107: INICIO DE LPP | B107: INC 1621 / 2026 | C107: Gerência de Cuidados Cirúrgicos / Unidade de Internação Cirúrgica | D107: Mylena Justino da Silva Brito | E107: Finalizada | F107: 1 | G107: Flavia Natalia Rebouças Ferreira | H107: 28/01/2026 | I107: 28/01/2026 | J107: __FOI OBSERVADO, INICIO DE LPP, EM REGIÃO SACRAL. PELE APRSENTANDO ERITEMA LOCALIZADO, FEITO TESTE DE BRANQUEAMENTO, AQUECIDA E COM SENSIBILIDADE AO TOQUE. ORIENTO MUDANÇA DE DECUBITO FREQUENTE E HIDRATAÇÃO DA PELE.__ | K107: Arquivo | L107: 04/02/2026 | M107: Unidade de Internação Cirúrgica | N107: Unidade de Internação Cirúrgica | O107: LEITO 28 | P107: Evento Adverso Moderado | Q107: Incidente
A108: IRAS JANEIRO 2026 | B108: INC 1622 / 2026 | C108: Diretoria Técnica / SCIH - Serviço de Controle de Infecção Hospitalar | D108: Mylena Justino da Silva Brito | E108: Finalizada | F108: 0 | G108: Suellen Andrade Sousa Coelho | H108: 28/01/2026 | I108: 28/01/2026 | J108: 23/12/2025 GESTANTE 24 ANOS, IG 1 USG // HOJE COM 40 SEM + 1 DIA. COMPARECE A UNIDADE PARA CESARIA ELETIVA. NEGA SANGRAMNETO OU PERDA DE LIQUIDO. BOA MOVIMENTAÇÃO FETAL. AO EXAME: PA 129 X 80 / - AU 39 / - MF + / - DU AUSENTE / - BCF 142. TOQUE: EVITADO. ÁS 10:53 PACIENTE G2PC1A0, COM CESAREA PRÉVIA, SUBMETIDA À CESAREANA SEGMENTAR ARCIFORME + LAQUEADURA TUBÁRIA BILATERAL À POMEROY. PÓS-OPERATÓRIO IMEDIATO SEM INTERCORRÊNCIAS, CD: VPM. OBS.: PACIENTE COM SGTO PERSISTENTE, COLOCADO DRENO DE PENROSE SUBAPONEURÓTICO. ATB (D1/2) CEFALOTINA. 24/12 QUEIXA PRINCIPAL: VEIO PARA CESARIA ELETIVA. CESARIANA EM 23/12 COM RELATO DE SANGRAMENTO PERSISTENTE, SENDO DEIXADO DRENO DE PENROSE SUBAPONEUROTICO. DRENO COM MININA SECREÇÃO SEROHEMATICA. RETIRADO DRENO. ÚTERO NORMOCONTRAÍDO, FO BOM ASPECTO. 25/12 PACIENTE SEM QUEIXAS, ALIMENTA, AMAMENTA E DEAMBULA, DIURESE ESPONTÂNEA, ELIMINA GASES. FO LIMPA E SECA, SEM DRENAGEM. ALTA COM ORIENTAÇÕES. ATB DE ALTA CEFALEXINA TOMAR 01 CP DE 6/6H, POR 7 DIAS. 04/01/26 PACIENTE VEM A UNIDADE QUEIXANDO DOR E INFLAMAÇÃO EM FO. NO MOMENTO DA AVALIAÇÃO PERCEBO INFECÇÃO DE FO, QUESTIONO SOBRE O USO DO ATB PRESCRITO, RELATOU USO INCORRETO DO MESMO. SEM FEBRE ASSOCIADA, NEGA OUTROS SINTOMAS. AO EXAME: FO COM RUBOR, CALOR E SAÍDA DE SECREÇÃO PURULENTA. CONDUTA: ORIENTAÇÕES SOBRE O USO CORRETO DO ATB / - PRESCREVO / - ALTA MÉDICA. ATB CLAVULIN 875 + 125 MG. TOMAR 01 CP DE 12/12H POR 7 DIAS. ISC INCISIONAL SUPERFICIAL (IS). | K108: Arquivo | L108: 29/01/2026 | M108: PAM - Pronto Atendimento Materno | N108: SCIH - Serviço de Controle de Infecção Hospitalar | O108: 00 | P108: Evento Adverso Moderado | Q108: Incidente
... A124: Testagem do carro de emergência não realizada | B124: INC 1638 / 2026 | C124: Diretoria Técnica / Gerência de Enfermagem | D124: Mylena Justino da Silva Brito | E124: Finalizada | F124: 0 | G124: Clariane Acário Martins | H124: 29/01/2026 | I124: 29/01/2026 | J124: FORMULÁRIO DE CONFERÊNCIA E TESTAGEM DO CARRO DE EMERGÊNCIA SEM CHECAGEM EM ALGUNS PLANTÕES. | K124: Arquivo | L124: 04/02/2026 | M124: UCI - Unidade de Cuidados Intensivos Neonatal | N124: Gerência de Enfermagem | O124: N/A | P124: Circunstância de Risco | Q124: Incidente
A125: Auditoria Setorial / Visita Técnica | B125: INC 1639 / 2026 | C125: Diretoria Técnica / Gerência de Enfermagem | D125: Mylena Justino da Silva Brito | E125: Ignorada | F125: 0 | G125: Clariane Acário Martins | H125: 29/01/2026 | I125: 29/01/2026 | J125: LACRE VERMELHO EM CIMA DO CARRO DE EMERGÊNCIA E O CARRO ESTAVA LACRADO. | K125: Arquivo | L125: 04/02/2026 | M125: UCI - Unidade de Cuidados Intensivos Neonatal | N125: Gerência de Enfermagem | O125: N/A | Q125: Incidente
A126: Gel sem identificação de validade | B126: INC 1640 / 2026 | C126: Diretoria Técnica / Gerência de Enfermagem | D126: Mylena Justino da Silva Brito | E126: Finalizada | F126: 0 | G126: Clariane Acário Martins | H126: 29/01/2026 | I126: 29/01/2026 | J126: GEL PARA ULTRASSOM ABERTO, SEM DATA DE ABERTURA E VALIDADE E COM TAMPA QUE NÃO ERA ORIGINAL DO FRASCO. | K126: Arquivo | L126: 04/02/2026 | M126: Unidade de Internação Cirúrgica | N126: Gerência de Enfermagem | O126: N/A | P126: Circunstância de Risco | Q126: Incidente
A127: Ambú vencido | B127: INC 1641 / 2026 | C127: Diretoria Técnica / Gerência de Enfermagem | D127: Mylena Justino da Silva Brito | E127: Finalizada | F127: 0 | G127: Clariane Acário Martins | H127: 29/01/2026 | I127: 29/01/2026 | J127: AMBU COM DATA DE VALIDADE VENCIDA. | K127: Arquivo | L127: 04/02/2026 | M127: Unidade de Internação Cirúrgica | N127: Gerência de Enfermagem | O127: N/A | P127: Circunstância de Risco | Q127: Incidente
A128: Ambú sem data de validade | B128: INC 1642 / 2026 | C128: Diretoria Técnica / Gerência de Enfermagem | D128: Mylena Justino da Silva Brito | E128: Finalizada | F128: 0 | G128: Clariane Acário Martins | H128: 29/01/2026 | I128: 29/01/2026 | J128: AMBU SEM ETIQUETA E DATA DE VALIDADE | K128: Arquivo | L128: 04/02/2026 | M128: CPN - Centro de Parto Normal | N128: Gerência de Enfermagem | O128: N/A | P128: Circunstância de Risco | Q128: Incidente
A129: Falha na cadeia medicamentosa | B129: INC 1643 / 2026 | C129: Gerência de Cuidados Clínicos e Intensivos / PS - Pronto Socorro | D129: Mylena Justino da Silva Brito | E129: Finalizada | F129: 0 | G129: Mardone Lima Da Silva | H129: 29/01/2026 | I129: 29/01/2026 | J129: Paciente M.A.M.S., prontuário nº 1544889, com registro de alergia à dipirona devidamente sinalizado em prontuário, recebeu prescrição médica contendo dipirona, configurando erro de prescrição. A medicação foi dispensada pela farmácia, apesar da sinalização de alergia registrada no prontuário eletrônico, caracterizando falha no processo de dispensação. Antes da administração, a equipe de enfermagem identificou a inconformidade durante a conferência da prescrição, realizando a barreira de segurança e impedindo a administração do medicamento ao paciente, evitando a ocorrência de dano. O evento caracteriza quase dano, envolvendo falhas em mais de uma etapa do processo assistencial. | K129: Arquivo | L129: 04/02/2026 | M129: PS - Pronto Atendimento Adulto | N129: PS - Pronto Atendimento Adulto | O129: SALA DE MEDICAÇÃO | P129: Quase Evento | Q129: Incidente
A130: Erro de prescrição - Superdose | B130: INC 1644 / 2026 | C130: Gerência de Cuidados Clínicos e Intensivos / PS - Pronto Socorro | D130: Mylena Justino da Silva Brito | E130: Finalizada | F130: 0 | G130: Mardone Lima Da Silva | H130: 29/01/2026 | I130: 29/01/2026 | J130: Paciente R.M.L.M., prontuário nº 1544855, deu entrada na unidade e foi avaliada pelo médico assistencial, que realizou prescrição contendo dose elevada de medicação, incompatível com os parâmetros assistenciais recomendados. A inconformidade foi identificada pela equipe de enfermagem durante a conferência da prescrição, sendo realizada a barreira de segurança. A situação foi comunicada a outro médico, que procedeu com a correção da dose prescrita. O evento foi notificado para análise do processo e implementação de melhorias, visando o fortalecimento da segurança do paciente. | K130: Arquivo | L130: 04/02/2026 | M130: PS - Pronto Atendimento Adulto | N130: PS - Pronto Atendimento Adulto | O130: PEDIATRIA/ PS | P130: Circunstância de Risco | Q130: Incidente
A131: Atraso na autorização de exame crítico com impacto assistencial | B131: INC 1645 / 2026 | C131: Gerência de Cuidados Clínicos e Intensivos / PS - Pronto Socorro | D131: Mylena Justino da Silva Brito | E131: Finalizada | F131: 0 | G131: Mardone Lima Da Silva | H131: 29/01/2026 | I131: 29/01/2026 | J131: Em 14/01/2026, a paciente M.A.S.A., prontuário nº 1533709, deu entrada na Sala Vermelha em quadro clínico crítico. Foi solicitado exame de imagem, tomografia computadorizada de tórax com contraste, considerado essencial para definição diagnóstica e conduta médica adequada. O pedido foi encaminhado ao setor SADT (VIA GRUPO DE WHATSAP) às 10:59h. Houve múltiplas tentativas de contato para autorização do exame às 11:12h, 15:57h e 16:59h, permanecendo sem resposta. Somente às 17:35h foi recebida devolutiva negativa, informando que o exame proposto não correspondia ao indicado pelo radiologista. O atraso prolongado na comunicação e na autorização do exame resultou na não realização do procedimento crítico, comprometendo o manejo clínico do paciente, que evoluiu a óbito às 20:59h. O evento evidencia falha no fluxo de comunicação e no atendimento de solicitações de exames críticos, impactando diretamente a segurança do paciente e a efetividade da assistência prestada. Recomenda-se revisão e padronização do fluxo de solicitações de exames críticos, estabelecimento de prazos máximos para devolutiva em situações urgentes, definição de protocolo de escalonamento, treinamento das equipes assistenciais e do setor SADT para comunicação efetiva e registro adequado de demandas críticas, além de monitoramento e auditoria periódica do cumprimento do fluxo estabelecido. | K131: Arquivo | L131: 04/02/2026 | M131: SADT - Unidade de Diagnóstico Por Imagem | N131: PS - Pronto Atendimento Adulto | O131: SALA VERMELHA/ PS | P131: Evento Adverso Grave | Q131: Incidente
A132: Falha na adesão a Precaução de Contato | B132: INC 1646 / 2026 | C132: Diretoria Técnica / SCIH - Serviço de Controle de Infecção Hospitalar | D132: Mylena Justino da Silva Brito | E132: Finalizada | F132: 1 | G132: Ana Paula Silva dos Santos | H132: 29/01/2026 | I132: 29/01/2026 | J132: Durante visita ao setor de observação da Clínica Médica, foi identificado que a técnica de enfermagem prestava assistência ao paciente do leito 09, em precaução de contato devido a crescimento de Klebsiella pneumoniae resistente, sem a utilização dos Equipamentos de Proteção Individual (EPIs) preconizados para essa condição. Tal conduta representa risco de transmissão cruzada de microrganismos multirresistentes para outros pacientes, profissionais de saúde e para o ambiente hospitalar, podendo contribuir para aumento da incidência de infecções relacionadas à assistência à saúde (IRAS). Ressalta-se a importância do cumprimento rigoroso das precauções de contato e do uso adequado dos EPIs, conforme protocolos institucionais, como medida essencial para a segurança do paciente, dos profissionais e para o controle da disseminação de microrganismos resistentes. Notifico tal conduta, para melhoria dos processos. | K132: Arquivo | L132: 04/02/2026 | M132: Unidade de Internação Clínica Médica | N132: SCIH - Serviço de Controle de Infecção Hospitalar | O132: VOBS 09 | P132: Circunstância de Risco | Q132: Incidente
A133: LPP SACRAL | B133: INC 1647 / 2026 | C133: Gerência de Cuidados Cirúrgicos / Unidade de Internação Cirúrgica | D133: Mylena Justino da Silva Brito | E133: Finalizada | F133: 2 | G133: Ana Carolina de Oliveira Souza | H133: 29/01/2026 | I133: 29/01/2026 | J133: LPP Estágio 1 - Eritema não branqueável/sem alteração de cor Presença de área com eritema não branqueável em região sacral, pele íntegra, quente ao toque, paciente acamado, Braden = __. Realizado alívio de pressão imediata, mudança de decúbito, proteção local com placa de espuma/silicone, hidratação da pele, orientação à equipe quanto à vigilância da área. Área mantida íntegra, sem progressão da lesão, paciente confortável, pele monitorada continuamente. | K133: Arquivo | L133: 04/02/2026 | M133: UTI - Unidade de Terapia Intensiva | N133: Comissões | O133: 7 | P133: Evento Adverso Moderado | Q133: Incidente
A134: Paciente com alergia sem identificação | B134: INC 1648 / 2026 | C134: Diretoria Técnica / Gerência de Enfermagem | D134: Mylena Justino da Silva Brito | E134: Finalizada | F134: 0 | G134: Vanuza Batista Barbosa | H134: 29/01/2026 | I134: 29/01/2026 | J134: No dia 27/01/2026 paciente R.L.A proveniente do pam veio para o centro cirurgico para procediemtno de curetagem uterina sem pulseira de identificação de alergia. reforço que a identificação de alergia do paciente é crucial para garantir a assistência segura. Notifico para a melhoria do processo. | K134: Arquivo | L134: 02/02/2026 | M134: PAM - Pronto Atendimento Materno | N134: Centro Cirúrgico | O134: 00000 | P134: Circunstância de Risco | Q134: Incidente
A135: CATETER NASAL SEM PROTEÇÃO | B135: INC 1649 / 2026 | C135: Diretoria Técnica / SCIH - Serviço de Controle de Infecção Hospitalar | D135: Mylena Justino da Silva Brito | E135: Finalizada | F135: 2 | G135: Suellen Andrade Sousa Coelho | H135: 30/01/2026 | I135: 30/01/2026 | J135: Em visita de rotina, foi observado paciente idoso em uso de cateter nasal para oxigenoterapia. No momento da visita, o dispositivo encontrava-se fora de uso, sem a devida proteção e disposto diretamente sobre o leito, em condições inadequadas de armazenamento, o que aumenta o risco de contaminação. Notifico para melhoria do processo. | K135: Arquivo | L135: 04/02/2026 | M135: PS - Pronto Atendimento Adulto | N135: SCIH - Serviço de Controle de Infecção Hospitalar | O135: Semi crítico | P135: Circunstância de Risco | Q135: Incidente
A136: DISPENSER DESABASTECIDO | B136: INC 1650 / 2026 | C136: Diretoria Técnica / SCIH - Serviço de Controle de Infecção Hospitalar | D136: Mylena Justino da Silva Brito | E136: Finalizada | F136: 1 | G136: Suellen Andrade Sousa Coelho | H136: 30/01/2026 | I136: 30/01/2026 | J136: Durante visita de rotina à Clínica Médica, ao tentar realizar higienização das mãos com álcool gel, foi verificado que o dispenser disponível na parede encontrava-se sem refil, impossibilitando o uso do insumo no momento da necessidade. A indisponibilidade do produto compromete a adesão às práticas de higiene das mãos e aumenta o risco de falhas nas medidas de prevenção e controle de infecção. Notifico para melhoria do processo. | K136: Arquivo | L136: 04/02/2026 | M136: SHL - Serviço de Higienização e Limpeza | N136: SCIH - Serviço de Controle de Infecção Hospitalar | O136: 000 | P136: Circunstância de Risco | Q136: Incidente
A137: Falha no uso deEPI | B137: INC 1651 / 2026 | C137: Diretoria Técnica / SCIH - Serviço de Controle de Infecção Hospitalar | D137: Mylena Justino da Silva Brito | E137: Finalizada | F137: 1 | G137: Suellen Andrade Sousa Coelho | H137: 30/01/2026 | I137: 30/01/2026 | J137: Durante visita de rotina, foi observada técnica de enfermagem realizando procedimento de curativo sem a utilização do Equipamento de Proteção Individual (EPI) indicado para a atividade, especificamente o capote. A conduta encontra-se em desacordo com os protocolos de biossegurança e com as medidas de prevenção e controle de infecções relacionadas à assistência à saúde. Notifico para melhoria do processo. | K137: Arquivo | L137: 04/02/2026 | M137: Unidade de Internação Cirúrgica | N137: SCIH - Serviço de Controle de Infecção Hospitalar | O137: 000 | P137: Circunstância de Risco | Q137: Incidente
... A144: RISCO IMINENTE DE MORTE DE PACIENTE VINDA DO PS | B144: INC 1658 / 2026 | C144: Gerência de Cuidados Materno/Infantil / UCI - Unidade de Cuidados Intensivos Neonatal | D144: Mylena Justino da Silva Brito | E144: Finalizada | F144: 1 | G144: Larissa Talita da Silva | H144: 03/02/2026 | I144: 03/02/2026 | J144: Paciente admitida inicialmente no Pronto-Socorro com quadro de desconforto respiratório associado a crise asmática. Foi solicitada avaliação da médica da Unidade de Cuidados Intensivos (UCI), que ao examinar a paciente identificou ausência de exames complementares, incluindo exames laboratoriais e radiografia de tórax, o que limitava a adequada avaliação da gravidade clínica e definição de conduta precoce. Durante a permanência no PS, foram instituídas medidas de suporte, incluindo administração de medicações para broncoespasmo e tentativa de estabilização clínica, além de suporte ventilatório não invasivo (VNI). Apesar das intervenções realizadas, a paciente manteve piora progressiva do padrão respiratório, evoluindo com sinais de insuficiência respiratória aguda e importante esforço respiratório. Diante da gravidade, foi realizado resgate pela equipe da UCI Neonatal, sendo a paciente transferida em estado crítico, com risco iminente de morte. À admissão na unidade, apresentava franco esforço respiratório, sendo necessária aspiração imediata de vias aéreas, com retirada de grande quantidade de secreção espessa. Devido à falha do suporte não invasivo e à gravidade do quadro, foi indicada sedação e intubação orotraqueal de urgência, procedimento realizado sem intercorrências imediatas, com estabilização inicial após ventilação mecânica invasiva. Paciente permanece em estado grave, sendo indicada transferência para UTI Pediátrica, considerando a piora clínica progressiva e a necessidade de suporte intensivo contínuo. Ressalta-se que a ausência de investigação diagnóstica inicial e atraso na definição de condutas no Pronto-Socorro configuram fatores que podem ter contribuído para a evolução desfavorável do quadro respiratório, caracterizando incidente assistencial grave com risco de morte, devendo o caso ser analisado para fins de avaliação de processo de trabalho e segurança do paciente. | K144: Arquivo | L144: 04/02/2026 | M144: PS - Pronto Atendimento Adulto | N144: UCI - Unidade de Cuidados Intensivos Neonatal | O144: 9 | P144: Evento Catastrófico | Q144: Incidente
A145: Demora na Regulação PARA A SALAT DE ALTA Comprometendo Liberação de Leito | B145: INC 1659 / 2026 | C145: Gerência de Cuidados Cirúrgicos / Gerência de Cuidados Cirúrgicos | D145: Mylena Justino da Silva Brito | E145: Convertida | F145: 0 | G145: Sarah Fernandes de Oliveira Amaral | H145: 03/02/2026 | I145: 03/02/2026 | J145: foi identificado atraso significativo na aceitação de pacientes destinados à sala de alta. Essa pendência está comprometendo diretamente a liberação de leitos hospitalares, ocasionando impacto negativo na gestão da capacidade assistencial e na organização do fluxo de internações. Diante da relevância da situação, solicitamos atenção na análise e liberação dos casos pendentes. A agilidade nesse processo é fundamental para assegurar a continuidade do cuidado aos pacientes, otimizar a utilização dos recursos disponíveis e evitar sobrecarga nos demais setores da instituição. | K145: Arquivo | L145: 03/02/2026 | M145: NIR - Núcleo de Regulação Interno | N145: Unidade de Internação Cirúrgica | O145: clinica cirurgica ortopedica, leiro 11 | Q145: Incidente
A146: CURATIVO INADEQUADO | B146: INC 1660 / 2026 | C146: Diretoria Técnica / SCIH - Serviço de Controle de Infecção Hospitalar | D146: Mylena Justino da Silva Brito | E146: Finalizada | F146: 1 | G146: Suellen Andrade Sousa Coelho | H146: 04/02/2026 | I146: 04/02/2026 | J146: Durante visita de rotina na Observação, foi identificado paciente em uso de acesso venoso periférico cujo dispositivo apresentava identificação incompleta, constando apenas a data de inserção, sem o nome e/ou identificação do profissional responsável pela realização do procedimento. Notifico para fins de adequação às normas institucionais e rastreabilidade do cuidado. | K146: Arquivo | L146: 04/02/2026 | M146: Unidade de Internação Clínica Médica | N146: SCIH - Serviço de Controle de Infecção Hospitalar | O146: 07 | P146: Circunstância de Risco | Q146: Incidente
A147: CATETER NASAL SEM PROTEÇÃO | B147: INC 1661 / 2026 | C147: Diretoria Técnica / SCIH - Serviço de Controle de Infecção Hospitalar | D147: Mylena Justino da Silva Brito | E147: Finalizada | F147: 1 | G147: Suellen Andrade Sousa Coelho | H147: 04/02/2026 | I147: 04/02/2026 | J147: Durante visita de rotina na observação, foi identificado paciente em uso de cateter nasal, o qual se encontrava sem a devida proteção, permanecendo exposto sobre superfícies inadequadas quando fora de uso. Tal condição caracteriza armazenamento incorreto do dispositivo, em desacordo com as boas práticas assistenciais, aumentando o risco de contaminação e infecção ao paciente. Notifico para melhoria do processo. | K147: Arquivo | L147: 04/02/2026 | M147: Unidade de Internação Clínica Médica | N147: SCIH - Serviço de Controle de Infecção Hospitalar | O147: 09 | P147: Circunstância de Risco | Q147: Incidente
A148: PERFURO CORTANTE | B148: INC 1662 / 2026 | C148: Diretoria Técnica / SCIH - Serviço de Controle de Infecção Hospitalar | D148: Mylena Justino da Silva Brito | E148: Convertida | F148: 0 | G148: Suellen Andrade Sousa Coelho | H148: 04/02/2026 | I148: 04/02/2026 | J148: Durante visita de rotina na clínica médica, foram identificadas agulhas soltas e desencapadas no carrinho de curativo, em desacordo com as normas de segurança e com o protocolo institucional para descarte adequado de materiais perfurocortantes. A situação observada representa risco ocupacional à equipe assistencial, bem como potencial risco biológico. Notifico para melhoria do processo. | K148: Arquivo | L148: 04/02/2026 | M148: Unidade de Internação Clínica Médica | N148: SCIH - Serviço de Controle de Infecção Hospitalar | O148: 000 | Q148: Incidente
A149: FALHA NO USO DE EPI | B149: INC 1663 / 2026 | C149: Diretoria Técnica / SCIH - Serviço de Controle de Infecção Hospitalar | D149: Mylena Justino da Silva Brito | E149: Finalizada | F149: 1 | G149: Suellen Andrade Sousa Coelho | H149: 04/02/2026 | I149: 04/02/2026 | J149: Durante visita na clínica médica, foi observada técnica de enfermagem realizando banho no leito de paciente sem a utilização do Equipamento de Proteção Individual (EPI) adequado, especificamente o capote, em desacordo com as normas de biossegurança e com as legislações vigentes. A prática expõe o profissional e o paciente a riscos biológicos. Reforço o uso correto dos EPIs durante a realização de procedimentos assistenciais, visando à proteção individual, à segurança do paciente e à conformidade com as normas regulatórias. Notifico para melhoria do processo. | K149: Arquivo | L149: 04/02/2026 | M149: Unidade de Internação Clínica Médica | N149: SCIH - Serviço de Controle de Infecção Hospitalar | O149: 000 | P149: Circunstância de Risco | Q149: Incidente
A150: MATERIAL SEM IDENTIFICAÇÃO | B150: INC 1664 / 2026 | C150: Diretoria Técnica / SCIH - Serviço de Controle de Infecção Hospitalar | D150: Mylena Justino da Silva Brito | E150: Finalizada | F150: 1 | G150: Suellen Andrade Sousa Coelho | H150: 04/02/2026 | I150: 04/02/2026 | J150: Durante visita de rotina, foi verificado material médico-hospitalar provenientes do Centro de Material e Esterilização (CME) sem a devida identificação. Observou-se ausência de informações essenciais, como data de esterilização, prazo de validade, método utilizado e identificação do lote ou responsável, em desacordo com os protocolos institucionais e normas de segurança. A não conformidade compromete a rastreabilidade do material e a segurança do paciente. Notifico para melhoria do processo. | K150: Arquivo | L150: 04/02/2026 | M150: Unidade de Internação Clínica Médica | N150: SCIH - Serviço de Controle de Infecção Hospitalar | O150: 000 | P150: Circunstância de Risco | Q150: Incidente
...
